Workbook

Sheet 00_GUIDE
B2: MODE A + MODE B + MODE C + BEP + Scenario Compare + Volume Profit Excel Simulator — Pricing Harness
B4: Source of Truth 구조 (반드시 지켜야 하는 원칙)
B5: A. Formula Source of Truth = docs/features/mode_a_current_price/SPEC.md (MODE A), docs/features/mode_b_target_price/SPEC.md (MODE B), docs/features/mode_c_allowable_cost/SPEC.md (MODE C), docs/features/bep/SPEC.md (BEP) — 계산식의 공식 기준.
B6: B. Reference Implementation = core/engine/modes/mode_a.py, core/engine/modes/mode_b.py, core/engine/modes/mode_c.py, core/engine/modes/bep.py (Python), core/engine/economics.py(MODE A/BEP가 공유하는 Contribution Margin economic primitive — 실제 shared-cost 배부 엔진이 아님) — SPEC을 구현/테스트하는 기준 엔진. tests/test_mode_a.py 13/13, tests/test_mode_b.py 24/24, tests/test_mode_c.py 26/26, tests/test_bep.py 32/32 PASS.
B7: C. Interactive Simulation Layer = 이 Excel 파일 — 사용자가 값을 바꿔가며 결과 변화를 체감하는 도구. 수식은 반드시 A/B와 동일한 논리를 따른다. Excel은 독립적인 계산 엔진이 아니며, Python과 다른 계산 규칙을 만들지 않는다.
B8: D. Official Result Source = analysis_result.json (core/schemas/analysis_result.schema.json) — 실제 컨설팅 판단에 쓰는 공식 결과. Dashboard/Report/Quotation은 이 파일만 읽고, Excel 셀을 재계산하거나 직접 읽지 않는다.
B10: blank ≠ 0 원칙
B11: 필수 입력이 비어 있으면 그 값에 의존하는 결과는 0이 아니라 "미입력" 또는 "계산불가"로 표시됩니다. #DIV/0!, #VALUE!, #N/A 같은 Excel 기본 오류가 사용자 화면에 그대로 노출되지 않도록 모든 계산 셀은 IFERROR로 감쌌습니다.
B13: 이번 버전(v0.7)이 완전히 지원하는 범위
B14: • 01_SIMULATOR(MODE A)는 단일 컴포넌트 상품(simple one-time product, ecommerce product)만 대화형으로 지원합니다.
B15: • 03_PARITY_TEST(MODE A)에서 두 시나리오(simple / ecommerce) 모두 Python 엔진 결과와 대조 검증되어 있습니다.
B16: • 04_MODE_B_SIMULATOR는 단일 컴포넌트, shared-cost 없음 기준으로 목표가격(N/G/판매가/정가)을 대화형으로 계산합니다 — C/b/a는 이미 합산된 값을 입력합니다(01_SIMULATOR와 동일한 단순화).
... B29: 컴포넌트가 2개 이상인 하이브리드 상품은 단일-컴포넌트 Simulator 구조로 표현할 수 없어 이 Excel에서는 임의로 계산하지 않습니다. 아래는 Python Engine이 실제로 계산한 결과(core/schemas/examples/analysis_results/03_hybrid_hw_saas.analysis_result.json)를 그대로 옮긴 참고용 수치입니다 — 이 시트에서 재계산되지 않는 고정값입니다.
B30: Component | C30: Gross Profit | D30: Gross Profit Rate | E30: Contribution Margin
B31: hardware | C31: 181.48 USD (OK) | D31: 54.4% (OK) | E31: UNKNOWN — blended.allocation[pg_fee, channel_fee, maintenance_visit] 미구현
B32: saas_subscription | C32: 22.59 USD (OK) | D32: 87.1% (OK) | E32: UNKNOWN — blended.allocation[pg_fee, channel_fee, maintenance_visit] 미구현
B34: MODE B Shared Cost Status — Excel-only simulation control
B35: 04_MODE_B_SIMULATOR / 05_MODE_B_PARITY_TEST의 'Shared Cost Status' (none/unresolved/invalid) 입력은 client_input.schema.json의 정식 필드가 아닙니다. Shared Cost Status is an Excel simulation control only. It is not a field in client_input.schema.json. The production Python engine derives this state from actual cost item / applies_to_component / allocation_rule data (core/engine/modes/mode_b.py, dependency_rules.md §4) — never from a flag. 이 플래그는 shared 비용의 실제 배부(allocation) 금액을 계산하지 않고, 배부가 미구현/모순인 상태에서 MODE B가 UNKNOWN(unresolved) 또는 ERROR(invalid)를 정확히 산출하는지만 검증합니다 — Excel v0.2에도 실제 allocation engine은 추가되지 않았습니다. 아래는 05_MODE_B_PARITY_TEST의 #14/#15와 동일한 시나리오를 core/engine/modes/mode_b.py로 직접 실행한 결과(빌드 시점 고정값)입니다.
B36: Scenario | C36: denominator | D36: required_net_sales_ex_vat | E36: Warning code
B37: #14 shared + fixed_share (unresolved) | C37: UNKNOWN | D37: UNKNOWN | E37: UNSUPPORTED_SHARED_COST_ALLOCATION
B38: #15 shared + direct (invalid config) | C38: ERROR | D38: ERROR | E38: INVALID_ALLOCATION_CONFIGURATION
B39: MODE C Allocation Status — Excel-only simulation controls (TWO, independent)
B40: 06_MODE_C_SIMULATOR / 07_MODE_C_PARITY_TEST는 'Variable Cost Allocation Status'와 'Direct Cost Allocation Status', 2개의 독립된 Excel-only 컨트롤을 사용합니다 — 둘 다 client_input.schema.json의 정식 필드가 아닙니다(Excel simulation control only, not a field in client_input.schema.json). Variable Cost Allocation Status는 F/b/a(변동비)에 대한 공유비용 배부 상태를 시뮬레이션하며, unresolved/invalid일 때 allowable_direct_cost(ADC)·direct_cost_gap·expected_contribution_margin(_rate)까지 전부 UNKNOWN/ERROR로 전파됩니다. Direct Cost Allocation Status는 실제 직접원가(actual_direct_cost)에 대한 공유비용 배부 상태만 시뮬레이션하며, unresolved/invalid여도 이는 actual_direct_cost와 direct_cost_gap에만 영향을 주고 allowable_direct_cost·expected_contribution_margin(_rate)은 절대 영향받지 않습니다 — 이것이 MODE C Excel의 가장 중요한 dependency-isolation 테스트입니다 (docs/features/mode_c_allowable_cost/SPEC.md §9, core/schemas/dependency_rules.md §6). 07_MODE_C_PARITY_TEST의 TC19/TC20이 이 분리를 실시간으로 증명합니다.
B42: BEP — Break-Even Point
B43: • 질문: 현재 가격 + Contribution Margin + fixed operating cost → 손익분기 판매량(Q_BEP)은? BEP는 항상 현재 실제가격(actual_price, MODE A와 동일한 가격 기준) 기준으로 계산합니다 — MODE B의 required price나 MODE C의 market price를 대입하는 기능은 없습니다(향후 Scenario Compare 범위).
B44: • Fixed Operating Cost Basis(예: per_month)는 quantity unit이 아니라 analysis period context입니다. break_even_quantity_exact의 unit은 항상 "units"이고, Fixed Operating Cost가 정의된 기간을 별도의 'Analysis Period Basis' 셀로 분리해서 보여줍니다 — 둘을 하나로 섞어 표시하지 않습니다.
B45: • blank=UNKNOWN / 0=explicit zero 원칙은 BEP에도 동일하게 적용됩니다 — 단, fixed_operating_cost 항목이 '아예 없음'과 '항목은 있지만 값이 비어 있음'은 서로 다른 상태입니다(전자는 확정된 0/OK, 후자는 UNKNOWN) — Fixed Cost Allocation Status='none'으로 전자를, 'component'+금액 공백으로 후자를 표현합니다.
B46: • Contribution Margin per Unit(CMu)이 0 또는 음수인 경우는 계산 오류(ERROR)가 아니라 BEP 고유의 NOT_APPLICABLE 상태입니다 — 모든 입력값이 확정되어 있지만 손익분기 판매량이라는 개념 자체가 성립하지 않는 경우이며, 0이나 음수를 Q_BEP로 표시하지 않습니다. module status는 낮아지지 않습니다.
B47: • BEP v0.1은 단일 컴포넌트 상품만 지원합니다. 09_BEP_PARITY_TEST의 Component Count 컨트롤(Excel-only, schema field 아님)로 2개 이상 컴포넌트 시나리오를 시뮬레이션하면 즉시 ERROR/MULTI_COMPONENT_BEP_NOT_SUPPORTED로 처리되고, 이후 어떤 basis/CM/fixed-cost 계산도 수행되지 않습니다 — 이 gate가 다른 모든 validation보다 우선합니다.
B48: • 실제 shared-cost 배부(allocation) 엔진은 여전히 구현되어 있지 않습니다. Fixed Cost Allocation Status(component/unresolved/blended_only/invalid_direct)와 09_BEP_PARITY_TEST의 Fixed Cost Basis Consistency는 전부 Excel-only 시뮬레이션 컨트롤이며 client_input.schema.json의 정식 필드가 아닙니다. 특히 blended_only는 다른 모드의 '배부 대상 아님 → 0으로 제외' 규칙을 그대로 쓰지 않고 UNKNOWN으로 처리합니다 — BEP의 분자가 바로 fixed_operating_cost이기 때문에, 실제 존재하는 고정비를 조용히 0으로 만드는 것을 방지하기 위한 의도적인 편차입니다(docs/features/bep/SPEC.md §12).
B50: Scenario Compare — orchestration layer (not a new calculation mode)
B51: • Scenario Compare는 새로운 가격 계산 엔진이 아니라, 기존 MODE A/B/C/BEP를 여러 가정(base + override)에 대해 반복 실행하고 그 결과를 나란히 비교하는 orchestration layer입니다. Contribution Margin/BEP/VAT normalization/cost allocation 규칙을 새로 정의하지 않으며, 모든 숫자는 4개 모드의 기존 출력을 그대로 읽어온 것입니다.
B52: • Excel v0.1은 최대 5개 시나리오(A~E)로 제한됩니다 — 이는 presentation-layer 제한이며, Python Core(core/engine/scenario_compare.py)는 이 제한이 없습니다(2개 이상 임의 개수 지원).
... B58: • Scenario Compare는 자동 ranking이나 recommendation을 하지 않습니다 — 여러 시나리오를 나란히 비교해서 보여주는 descriptive comparison layer일 뿐입니다. '최적 시나리오' 자동 선정은 향후 AI Pricing Strategy layer의 몫입니다.

Sheet 01_SIMULATOR
B2: 01. MODE A Simulator — Interactive
B4: INPUT (노란 셀만 입력)
B5: Product Name | C5: 프리미엄 텀블러 | D5: 예시 시나리오 — 자유롭게 바꿔서 실험 가능
B6: Actual Price | C6: 35000 | D6: 실제 판매가격
B7: Price Includes VAT | C7: TRUE | D7: TRUE = 판매가에 VAT 포함 / FALSE = 별도 / 빈칸 = 모름
B8: VAT Rate | C8: 0.1 | D8: Price Includes VAT=FALSE면 비워둬도 계산 가능
B9: Product/Service Direct Cost | C9: 13500 | D9: Gross Profit 계산에 반영 (product_service_direct_cost)
B10: Channel Fee Rate | C10: 0 | D10: rate_of_net_sales — Net Sales(ex VAT)에 곱함. 채널 없으면 0
B11: PG Fee Rate | C11: 0.025 | D11: rate_of_gross_payment — Actual Price(결제금액)에 곱함
B12: Delivery / Installation Cost | C12: 3000 | D12: variable_selling_delivery (Harness 기본 분류)
B13: Other Variable Selling Cost | C13: 0 | D13: 기타 판매 변동비
B15: RESULT (계산값 — 직접 입력 금지)
B16: Actual Price ex VAT | C16: =IFERROR(IF(ISBLANK($C$6),"미입력",IF(ISBLANK($C$7),"미입력",IF($C$7=FALSE,$C$6,IF(ISBLANK($C$8),"미입력",$C$6/(1+$C$8))))),"계산불가") | D16: = actual_price / (1+vat_rate), 조건부 (SPEC.md §VAT 규칙) | J16: =IFERROR(IF(ISBLANK($C$6),"미입력",IF(ISBLANK($C$7),"미입력",IF($C$7=TRUE,$C$6,IF(ISBLANK($C$8),"미입력",$C$6*(1+$C$8))))),"계산불가")
B17: Direct Cost Total | C17: =IFERROR(IF(ISBLANK($C$9),"미입력",$C$9),"계산불가") | D17: product_service_direct_cost 합계
B18: Gross Profit | C18: =IFERROR(IF(AND(ISNUMBER($C$16),ISNUMBER($C$17)),$C$16-$C$17,"미입력"),"계산불가") | D18: = Actual Price ex VAT − Direct Cost Total
B19: Gross Profit Rate | C19: =IFERROR(IF(OR(NOT(ISNUMBER($C$18)),NOT(ISNUMBER($C$16))),"미입력",IF($C$16=0,"계산불가",$C$18/$C$16)),"계산불가") | D19: = Gross Profit / Actual Price ex VAT
B20: Variable Cost Total | C20: =IFERROR(IF(OR(ISBLANK($C$10),ISBLANK($C$11),ISBLANK($C$12),ISBLANK($C$13),NOT(ISNUMBER($C$16)),NOT(ISNUMBER($J$16))),"미입력",$C$16*$C$10+$J$16*$C$11+$C$12+$C$13),"계산불가") | D20: channel_fee×NetSales + pg_fee×GrossPayment(=NetSales×(1+VAT)) + delivery + other
B21: Contribution Margin | C21: =IFERROR(IF(AND(ISNUMBER($C$18),ISNUMBER($C$20)),$C$18-$C$20,"미입력"),"계산불가") | D21: = Gross Profit − Variable Cost Total (fixed cost 제외)
B22: Contribution Margin Rate | C22: =IFERROR(IF(OR(NOT(ISNUMBER($C$21)),NOT(ISNUMBER($C$16))),"미입력",IF($C$16=0,"계산불가",$C$21/$C$16)),"계산불가") | D22: = Contribution Margin / Actual Price ex VAT
B24: STATUS
B25: Data Complete / Incomplete / Error | C25: =IF((IF($C$16="계산불가",1,0)+IF($C$18="계산불가",1,0)+IF($C$19="계산불가",1,0)+IF($C$20="계산불가",1,0)+IF($C$21="계산불가",1,0)+IF($C$22="계산불가",1,0))>0,"Error",IF((IF(NOT(ISNUMBER($C$16)),1,0)+IF(NOT(ISNUMBER($C$18)),1,0)+IF(NOT(ISNUMBER($C$19)),1,0)+IF(NOT(ISNUMBER($C$20)),1,0)+IF(NOT(ISNUMBER($C$21)),1,0)+IF(NOT(ISNUMBER($C$22)),1,0))>0,"Incomplete","Complete"))
B26: Missing Inputs | C26: =IF($J$26="","없음",SUBSTITUTE(LEFT($J$26,LEN($J$26)-1),"|",", ")) | J26: =IF(ISBLANK($C$6),"판매가격|","")&IF(ISBLANK($C$7),"VAT포함여부|","")&IF(AND(NOT(ISBLANK($C$7)),ISBLANK($C$8),OR($C$7=TRUE,AND($C$7=FALSE,NOT(ISBLANK($C$11))))),"VAT율|","")&IF(ISBLANK($C$9),"직접원가|","")&IF(ISBLANK($C$10),"채널수수료율|","")&IF(ISBLANK($C$11),"PG수수료율|","")&IF(ISBLANK($C$12),"배송/설치비|","")&IF(ISBLANK($C$13),"기타변동비|","")
B27: Blocking Warning | C27: =IF(AND(ISNUMBER($C$18),ISNUMBER($C$21)),"없음 — 핵심 지표 계산 완료","Gross Profit: "&IF(ISNUMBER($C$18),"OK","UNKNOWN")&" | Contribution Margin: "&IF(ISNUMBER($C$21),"OK","UNKNOWN"))
B29: DASHBOARD CARD
B30: Current Price | E30: Net Sales | H30: Gross Profit
B31: =$C$6 | E31: =$C$16 | H31: =$C$18
B33: GP Rate | E33: Contribution Margin | H33: CM Rate
B34: =$C$19 | E34: =$C$21 | H34: =$C$22

Sheet 02_CALCULATION
B2: 02. Calculation Flow — 교육/QA용 (01_SIMULATOR 값을 그대로 참조)
B4: Step | C4: Live Value (from 01_SIMULATOR) | D4: Formula / Rule
B5: ① Actual Price | C5: ='01_SIMULATOR'!$C$6 | D5: 입력된 판매가격 그대로
B6: ↓
B7: ② VAT 처리 | C7: (VAT 포함여부에 따라 분기 — 결과는 다음 행 ③에 반영됨) | D7: price_includes_vat=FALSE → 그대로 사용 / TRUE → ÷(1+vat_rate)
B8: ↓
B9: ③ Net Sales (ex VAT) | C9: ='01_SIMULATOR'!$C$16 | D9: ①을 VAT 규칙대로 변환한 값
B10: ↓
B11: ④ Direct Cost | C11: ='01_SIMULATOR'!$C$9 | D11: product_service_direct_cost
B12: ↓
B13: ⑤ Gross Profit | C13: ='01_SIMULATOR'!$C$18 | D13: ③ − ④
B14: ↓
B15: ⑥ Variable Selling Cost | C15: ='01_SIMULATOR'!$C$20 | D15: channel/PG/배송/기타 변동비 합
B16: ↓
B17: ⑦ Contribution Margin | C17: ='01_SIMULATOR'!$C$21 | D17: ⑤ − ⑥ (고정비 제외)

Sheet 03_PARITY_TEST
B2: 03. Python Engine vs Excel Formula — Parity Test
B3: 각 케이스는 Excel에 동일 입력값을 리터럴로 심어 01_SIMULATOR와 같은 수식 패턴으로 독립 재계산하고, Python 참조값(core/engine/modes/mode_a.py 실행 결과, 빌드 시점에 고정)과 비교합니다. 허용오차 0.01(금액) / 0.0001(비율).
B5: Case 1 — Simple one-time product
B6: Metric | C6: Excel Result | D6: Python Reference | E6: Difference | F6: PASS / FAIL
B7: Actual Price ex VAT | C7: =I8 | D7: 31818.182 | E7: =IF(ISNUMBER(D7),IF(ISNUMBER(I8),ABS(I8-D7),"N/A"),"N/A") | F7: =IF(ISNUMBER(D7),IF(AND(ISNUMBER(I8),ABS(I8-D7)<=0.01),"PASS","FAIL"),IF(NOT(ISNUMBER(I8)),"PASS","FAIL")) | H7: (local inputs) | I7: 35000 | J7: TRUE | K7: 0.1 | L7: 13500 | M7: 0 | N7: 0.025 | O7: 3000 | P7: 0
B8: Direct Cost Total | C8: =J8 | D8: 13500 | E8: =IF(ISNUMBER(D8),IF(ISNUMBER(J8),ABS(J8-D8),"N/A"),"N/A") | F8: =IF(ISNUMBER(D8),IF(AND(ISNUMBER(J8),ABS(J8-D8)<=0.01),"PASS","FAIL"),IF(NOT(ISNUMBER(J8)),"PASS","FAIL")) | I8: =IFERROR(IF(ISBLANK($I$7),"미입력",IF(ISBLANK($J$7),"미입력",IF($J$7=FALSE,$I$7,IF(ISBLANK($K$7),"미입력",$I$7/(1+$K$7))))),"계산불가") | J8: =IFERROR(IF(ISBLANK($L$7),"미입력",$L$7),"계산불가") | K8: =IFERROR(IF(AND(ISNUMBER(I8),ISNUMBER(J8)),I8-J8,"미입력"),"계산불가") | L8: =IFERROR(IF(OR(NOT(ISNUMBER(K8)),NOT(ISNUMBER(I8))),"미입력",IF(I8=0,"계산불가",K8/I8)),"계산불가") | M8: =IFERROR(IF(OR(ISBLANK($M$7),ISBLANK($N$7),ISBLANK($O$7),ISBLANK($P$7),NOT(ISNUMBER(I8)),NOT(ISNUMBER(P8))),"미입력",I8*$M$7+P8*$N$7+$O$7+$P$7),"계산불가") | N8: =IFERROR(IF(AND(ISNUMBER(K8),ISNUMBER(M8)),K8-M8,"미입력"),"계산불가") | O8: =IFERROR(IF(OR(NOT(ISNUMBER(N8)),NOT(ISNUMBER(I8))),"미입력",IF(I8=0,"계산불가",N8/I8)),"계산불가") | P8: =IFERROR(IF(ISBLANK($I$7),"미입력",IF(ISBLANK($J$7),"미입력",IF($J$7=TRUE,$I$7,IF(ISBLANK($K$7),"미입력",$I$7*(1+$K$7))))),"계산불가")
B9: Gross Profit | C9: =K8 | D9: 18318.182 | E9: =IF(ISNUMBER(D9),IF(ISNUMBER(K8),ABS(K8-D9),"N/A"),"N/A") | F9: =IF(ISNUMBER(D9),IF(AND(ISNUMBER(K8),ABS(K8-D9)<=0.01),"PASS","FAIL"),IF(NOT(ISNUMBER(K8)),"PASS","FAIL"))
B10: Gross Profit Rate | C10: =L8 | D10: 0.57571429 | E10: =IF(ISNUMBER(D10),IF(ISNUMBER(L8),ABS(L8-D10),"N/A"),"N/A") | F10: =IF(ISNUMBER(D10),IF(AND(ISNUMBER(L8),ABS(L8-D10)<=0.0001),"PASS","FAIL"),IF(NOT(ISNUMBER(L8)),"PASS","FAIL"))
B11: Variable Cost Total | C11: =M8 | D11: 3875 | E11: =IF(ISNUMBER(D11),IF(ISNUMBER(M8),ABS(M8-D11),"N/A"),"N/A") | F11: =IF(ISNUMBER(D11),IF(AND(ISNUMBER(M8),ABS(M8-D11)<=0.01),"PASS","FAIL"),IF(NOT(ISNUMBER(M8)),"PASS","FAIL"))
B12: Contribution Margin | C12: =N8 | D12: 14443.182 | E12: =IF(ISNUMBER(D12),IF(ISNUMBER(N8),ABS(N8-D12),"N/A"),"N/A") | F12: =IF(ISNUMBER(D12),IF(AND(ISNUMBER(N8),ABS(N8-D12)<=0.01),"PASS","FAIL"),IF(NOT(ISNUMBER(N8)),"PASS","FAIL"))
B13: Contribution Margin Rate | C13: =O8 | D13: 0.45392857 | E13: =IF(ISNUMBER(D13),IF(ISNUMBER(O8),ABS(O8-D13),"N/A"),"N/A") | F13: =IF(ISNUMBER(D13),IF(AND(ISNUMBER(O8),ABS(O8-D13)<=0.0001),"PASS","FAIL"),IF(NOT(ISNUMBER(O8)),"PASS","FAIL"))
B15: Case 2 — VAT-inclusive, clean numbers
B16: Metric | C16: Excel Result | D16: Python Reference | E16: Difference | F16: PASS / FAIL
B17: Actual Price ex VAT | C17: =I18 | D17: 10000 | E17: =IF(ISNUMBER(D17),IF(ISNUMBER(I18),ABS(I18-D17),"N/A"),"N/A") | F17: =IF(ISNUMBER(D17),IF(AND(ISNUMBER(I18),ABS(I18-D17)<=0.01),"PASS","FAIL"),IF(NOT(ISNUMBER(I18)),"PASS","FAIL")) | H17: (local inputs) | I17: 11000 | J17: TRUE | K17: 0.1 | L17: 4000 | M17: 0 | N17: 0 | O17: 0 | P17: 0
B18: Direct Cost Total | C18: =J18 | D18: 4000 | E18: =IF(ISNUMBER(D18),IF(ISNUMBER(J18),ABS(J18-D18),"N/A"),"N/A") | F18: =IF(ISNUMBER(D18),IF(AND(ISNUMBER(J18),ABS(J18-D18)<=0.01),"PASS","FAIL"),IF(NOT(ISNUMBER(J18)),"PASS","FAIL")) | I18: =IFERROR(IF(ISBLANK($I$17),"미입력",IF(ISBLANK($J$17),"미입력",IF($J$17=FALSE,$I$17,IF(ISBLANK($K$17),"미입력",$I$17/(1+$K$17))))),"계산불가") | J18: =IFERROR(IF(ISBLANK($L$17),"미입력",$L$17),"계산불가") | K18: =IFERROR(IF(AND(ISNUMBER(I18),ISNUMBER(J18)),I18-J18,"미입력"),"계산불가") | L18: =IFERROR(IF(OR(NOT(ISNUMBER(K18)),NOT(ISNUMBER(I18))),"미입력",IF(I18=0,"계산불가",K18/I18)),"계산불가") | M18: =IFERROR(IF(OR(ISBLANK($M$17),ISBLANK($N$17),ISBLANK($O$17),ISBLANK($P$17),NOT(ISNUMBER(I18)),NOT(ISNUMBER(P18))),"미입력",I18*$M$17+P18*$N$17+$O$17+$P$17),"계산불가") | N18: =IFERROR(IF(AND(ISNUMBER(K18),ISNUMBER(M18)),K18-M18,"미입력"),"계산불가") | O18: =IFERROR(IF(OR(NOT(ISNUMBER(N18)),NOT(ISNUMBER(I18))),"미입력",IF(I18=0,"계산불가",N18/I18)),"계산불가") | P18: =IFERROR(IF(ISBLANK($I$17),"미입력",IF(ISBLANK($J$17),"미입력",IF($J$17=TRUE,$I$17,IF(ISBLANK($K$17),"미입력",$I$17*(1+$K$17))))),"계산불가")
B19: Gross Profit | C19: =K18 | D19: 6000 | E19: =IF(ISNUMBER(D19),IF(ISNUMBER(K18),ABS(K18-D19),"N/A"),"N/A") | F19: =IF(ISNUMBER(D19),IF(AND(ISNUMBER(K18),ABS(K18-D19)<=0.01),"PASS","FAIL"),IF(NOT(ISNUMBER(K18)),"PASS","FAIL"))
B20: Gross Profit Rate | C20: =L18 | D20: 0.6 | E20: =IF(ISNUMBER(D20),IF(ISNUMBER(L18),ABS(L18-D20),"N/A"),"N/A") | F20: =IF(ISNUMBER(D20),IF(AND(ISNUMBER(L18),ABS(L18-D20)<=0.0001),"PASS","FAIL"),IF(NOT(ISNUMBER(L18)),"PASS","FAIL"))
B21: Variable Cost Total | C21: =M18 | D21: 0 | E21: =IF(ISNUMBER(D21),IF(ISNUMBER(M18),ABS(M18-D21),"N/A"),"N/A") | F21: =IF(ISNUMBER(D21),IF(AND(ISNUMBER(M18),ABS(M18-D21)<=0.01),"PASS","FAIL"),IF(NOT(ISNUMBER(M18)),"PASS","FAIL"))
B22: Contribution Margin | C22: =N18 | D22: 6000 | E22: =IF(ISNUMBER(D22),IF(ISNUMBER(N18),ABS(N18-D22),"N/A"),"N/A") | F22: =IF(ISNUMBER(D22),IF(AND(ISNUMBER(N18),ABS(N18-D22)<=0.01),"PASS","FAIL"),IF(NOT(ISNUMBER(N18)),"PASS","FAIL"))
B23: Contribution Margin Rate | C23: =O18 | D23: 0.6 | E23: =IF(ISNUMBER(D23),IF(ISNUMBER(O18),ABS(O18-D23),"N/A"),"N/A") | F23: =IF(ISNUMBER(D23),IF(AND(ISNUMBER(O18),ABS(O18-D23)<=0.0001),"PASS","FAIL"),IF(NOT(ISNUMBER(O18)),"PASS","FAIL"))
B25: Case 3 — Ecommerce (channel fee + PG fee)
B26: Metric | C26: Excel Result | D26: Python Reference | E26: Difference | F26: PASS / FAIL
B27: Actual Price ex VAT | C27: =I28 | D27: 53636.364 | E27: =IF(ISNUMBER(D27),IF(ISNUMBER(I28),ABS(I28-D27),"N/A"),"N/A") | F27: =IF(ISNUMBER(D27),IF(AND(ISNUMBER(I28),ABS(I28-D27)<=0.01),"PASS","FAIL"),IF(NOT(ISNUMBER(I28)),"PASS","FAIL")) | H27: (local inputs) | I27: 59000 | J27: TRUE | K27: 0.1 | L27: 17000 | M27: 0.13 | N27: 0.028 | O27: 2500 | P27: 0
B28: Direct Cost Total | C28: =J28 | D28: 17000 | E28: =IF(ISNUMBER(D28),IF(ISNUMBER(J28),ABS(J28-D28),"N/A"),"N/A") | F28: =IF(ISNUMBER(D28),IF(AND(ISNUMBER(J28),ABS(J28-D28)<=0.01),"PASS","FAIL"),IF(NOT(ISNUMBER(J28)),"PASS","FAIL")) | I28: =IFERROR(IF(ISBLANK($I$27),"미입력",IF(ISBLANK($J$27),"미입력",IF($J$27=FALSE,$I$27,IF(ISBLANK($K$27),"미입력",$I$27/(1+$K$27))))),"계산불가") | J28: =IFERROR(IF(ISBLANK($L$27),"미입력",$L$27),"계산불가") | K28: =IFERROR(IF(AND(ISNUMBER(I28),ISNUMBER(J28)),I28-J28,"미입력"),"계산불가") | L28: =IFERROR(IF(OR(NOT(ISNUMBER(K28)),NOT(ISNUMBER(I28))),"미입력",IF(I28=0,"계산불가",K28/I28)),"계산불가") | M28: =IFERROR(IF(OR(ISBLANK($M$27),ISBLANK($N$27),ISBLANK($O$27),ISBLANK($P$27),NOT(ISNUMBER(I28)),NOT(ISNUMBER(P28))),"미입력",I28*$M$27+P28*$N$27+$O$27+$P$27),"계산불가") | N28: =IFERROR(IF(AND(ISNUMBER(K28),ISNUMBER(M28)),K28-M28,"미입력"),"계산불가") | O28: =IFERROR(IF(OR(NOT(ISNUMBER(N28)),NOT(ISNUMBER(I28))),"미입력",IF(I28=0,"계산불가",N28/I28)),"계산불가") | P28: =IFERROR(IF(ISBLANK($I$27),"미입력",IF(ISBLANK($J$27),"미입력",IF($J$27=TRUE,$I$27,IF(ISBLANK($K$27),"미입력",$I$27*(1+$K$27))))),"계산불가")
B29: Gross Profit | C29: =K28 | D29: 36636.364 | E29: =IF(ISNUMBER(D29),IF(ISNUMBER(K28),ABS(K28-D29),"N/A"),"N/A") | F29: =IF(ISNUMBER(D29),IF(AND(ISNUMBER(K28),ABS(K28-D29)<=0.01),"PASS","FAIL"),IF(NOT(ISNUMBER(K28)),"PASS","FAIL"))
B30: Gross Profit Rate | C30: =L28 | D30: 0.68305085 | E30: =IF(ISNUMBER(D30),IF(ISNUMBER(L28),ABS(L28-D30),"N/A"),"N/A") | F30: =IF(ISNUMBER(D30),IF(AND(ISNUMBER(L28),ABS(L28-D30)<=0.0001),"PASS","FAIL"),IF(NOT(ISNUMBER(L28)),"PASS","FAIL"))
B31: Variable Cost Total | C31: =M28 | D31: 11124.727 | E31: =IF(ISNUMBER(D31),IF(ISNUMBER(M28),ABS(M28-D31),"N/A"),"N/A") | F31: =IF(ISNUMBER(D31),IF(AND(ISNUMBER(M28),ABS(M28-D31)<=0.01),"PASS","FAIL"),IF(NOT(ISNUMBER(M28)),"PASS","FAIL"))
B32: Contribution Margin | C32: =N28 | D32: 25511.636 | E32: =IF(ISNUMBER(D32),IF(ISNUMBER(N28),ABS(N28-D32),"N/A"),"N/A") | F32: =IF(ISNUMBER(D32),IF(AND(ISNUMBER(N28),ABS(N28-D32)<=0.01),"PASS","FAIL"),IF(NOT(ISNUMBER(N28)),"PASS","FAIL"))
B33: Contribution Margin Rate | C33: =O28 | D33: 0.47564068 | E33: =IF(ISNUMBER(D33),IF(ISNUMBER(O28),ABS(O28-D33),"N/A"),"N/A") | F33: =IF(ISNUMBER(D33),IF(AND(ISNUMBER(O28),ABS(O28-D33)<=0.0001),"PASS","FAIL"),IF(NOT(ISNUMBER(O28)),"PASS","FAIL"))
B35: Case 4 — Incomplete input (UNKNOWN propagation)
B36: Metric | C36: Excel Result | D36: Python Reference | E36: Difference | F36: PASS / FAIL
B37: Actual Price ex VAT | C37: =I38 | D37: UNKNOWN | E37: =IF(ISNUMBER(D37),IF(ISNUMBER(I38),ABS(I38-D37),"N/A"),"N/A") | F37: =IF(ISNUMBER(D37),IF(AND(ISNUMBER(I38),ABS(I38-D37)<=0.01),"PASS","FAIL"),IF(NOT(ISNUMBER(I38)),"PASS","FAIL")) | H37: (local inputs) | I37: 35000
B38: Direct Cost Total | C38: =J38 | D38: UNKNOWN | E38: =IF(ISNUMBER(D38),IF(ISNUMBER(J38),ABS(J38-D38),"N/A"),"N/A") | F38: =IF(ISNUMBER(D38),IF(AND(ISNUMBER(J38),ABS(J38-D38)<=0.01),"PASS","FAIL"),IF(NOT(ISNUMBER(J38)),"PASS","FAIL")) | I38: =IFERROR(IF(ISBLANK($I$37),"미입력",IF(ISBLANK($J$37),"미입력",IF($J$37=FALSE,$I$37,IF(ISBLANK($K$37),"미입력",$I$37/(1+$K$37))))),"계산불가") | J38: =IFERROR(IF(ISBLANK($L$37),"미입력",$L$37),"계산불가") | K38: =IFERROR(IF(AND(ISNUMBER(I38),ISNUMBER(J38)),I38-J38,"미입력"),"계산불가") | L38: =IFERROR(IF(OR(NOT(ISNUMBER(K38)),NOT(ISNUMBER(I38))),"미입력",IF(I38=0,"계산불가",K38/I38)),"계산불가") | M38: =IFERROR(IF(OR(ISBLANK($M$37),ISBLANK($N$37),ISBLANK($O$37),ISBLANK($P$37),NOT(ISNUMBER(I38)),NOT(ISNUMBER(P38))),"미입력",I38*$M$37+P38*$N$37+$O$37+$P$37),"계산불가") | N38: =IFERROR(IF(AND(ISNUMBER(K38),ISNUMBER(M38)),K38-M38,"미입력"),"계산불가") | O38: =IFERROR(IF(OR(NOT(ISNUMBER(N38)),NOT(ISNUMBER(I38))),"미입력",IF(I38=0,"계산불가",N38/I38)),"계산불가") | P38: =IFERROR(IF(ISBLANK($I$37),"미입력",IF(ISBLANK($J$37),"미입력",IF($J$37=TRUE,$I$37,IF(ISBLANK($K$37),"미입력",$I$37*(1+$K$37))))),"계산불가")
B39: Gross Profit | C39: =K38 | D39: UNKNOWN | E39: =IF(ISNUMBER(D39),IF(ISNUMBER(K38),ABS(K38-D39),"N/A"),"N/A") | F39: =IF(ISNUMBER(D39),IF(AND(ISNUMBER(K38),ABS(K38-D39)<=0.01),"PASS","FAIL"),IF(NOT(ISNUMBER(K38)),"PASS","FAIL"))
B40: Gross Profit Rate | C40: =L38 | D40: UNKNOWN | E40: =IF(ISNUMBER(D40),IF(ISNUMBER(L38),ABS(L38-D40),"N/A"),"N/A") | F40: =IF(ISNUMBER(D40),IF(AND(ISNUMBER(L38),ABS(L38-D40)<=0.0001),"PASS","FAIL"),IF(NOT(ISNUMBER(L38)),"PASS","FAIL"))
B41: Variable Cost Total | C41: =M38 | D41: UNKNOWN | E41: =IF(ISNUMBER(D41),IF(ISNUMBER(M38),ABS(M38-D41),"N/A"),"N/A") | F41: =IF(ISNUMBER(D41),IF(AND(ISNUMBER(M38),ABS(M38-D41)<=0.01),"PASS","FAIL"),IF(NOT(ISNUMBER(M38)),"PASS","FAIL"))
B42: Contribution Margin | C42: =N38 | D42: UNKNOWN | E42: =IF(ISNUMBER(D42),IF(ISNUMBER(N38),ABS(N38-D42),"N/A"),"N/A") | F42: =IF(ISNUMBER(D42),IF(AND(ISNUMBER(N38),ABS(N38-D42)<=0.01),"PASS","FAIL"),IF(NOT(ISNUMBER(N38)),"PASS","FAIL"))
B43: Contribution Margin Rate | C43: =O38 | D43: UNKNOWN | E43: =IF(ISNUMBER(D43),IF(ISNUMBER(O38),ABS(O38-D43),"N/A"),"N/A") | F43: =IF(ISNUMBER(D43),IF(AND(ISNUMBER(O38),ABS(O38-D43)<=0.0001),"PASS","FAIL"),IF(NOT(ISNUMBER(O38)),"PASS","FAIL"))
B45: Case 5 — VAT-exclusive display + known VAT rate + gross-payment fee
B46: Metric | C46: Excel Result | D46: Python Reference | E46: Difference | F46: PASS / FAIL
B47: Actual Price ex VAT | C47: =I48 | D47: 8800 | E47: =IF(ISNUMBER(D47),IF(ISNUMBER(I48),ABS(I48-D47),"N/A"),"N/A") | F47: =IF(ISNUMBER(D47),IF(AND(ISNUMBER(I48),ABS(I48-D47)<=0.01),"PASS","FAIL"),IF(NOT(ISNUMBER(I48)),"PASS","FAIL")) | H47: (local inputs) | I47: 8800 | J47: FALSE | K47: 0.1 | L47: 3000 | M47: 0 | N47: 0.04 | O47: 200 | P47: 0
B48: Direct Cost Total | C48: =J48 | D48: 3000 | E48: =IF(ISNUMBER(D48),IF(ISNUMBER(J48),ABS(J48-D48),"N/A"),"N/A") | F48: =IF(ISNUMBER(D48),IF(AND(ISNUMBER(J48),ABS(J48-D48)<=0.01),"PASS","FAIL"),IF(NOT(ISNUMBER(J48)),"PASS","FAIL")) | I48: =IFERROR(IF(ISBLANK($I$47),"미입력",IF(ISBLANK($J$47),"미입력",IF($J$47=FALSE,$I$47,IF(ISBLANK($K$47),"미입력",$I$47/(1+$K$47))))),"계산불가") | J48: =IFERROR(IF(ISBLANK($L$47),"미입력",$L$47),"계산불가") | K48: =IFERROR(IF(AND(ISNUMBER(I48),ISNUMBER(J48)),I48-J48,"미입력"),"계산불가") | L48: =IFERROR(IF(OR(NOT(ISNUMBER(K48)),NOT(ISNUMBER(I48))),"미입력",IF(I48=0,"계산불가",K48/I48)),"계산불가") | M48: =IFERROR(IF(OR(ISBLANK($M$47),ISBLANK($N$47),ISBLANK($O$47),ISBLANK($P$47),NOT(ISNUMBER(I48)),NOT(ISNUMBER(P48))),"미입력",I48*$M$47+P48*$N$47+$O$47+$P$47),"계산불가") | N48: =IFERROR(IF(AND(ISNUMBER(K48),ISNUMBER(M48)),K48-M48,"미입력"),"계산불가") | O48: =IFERROR(IF(OR(NOT(ISNUMBER(N48)),NOT(ISNUMBER(I48))),"미입력",IF(I48=0,"계산불가",N48/I48)),"계산불가") | P48: =IFERROR(IF(ISBLANK($I$47),"미입력",IF(ISBLANK($J$47),"미입력",IF($J$47=TRUE,$I$47,IF(ISBLANK($K$47),"미입력",$I$47*(1+$K$47))))),"계산불가")
B49: Gross Profit | C49: =K48 | D49: 5800 | E49: =IF(ISNUMBER(D49),IF(ISNUMBER(K48),ABS(K48-D49),"N/A"),"N/A") | F49: =IF(ISNUMBER(D49),IF(AND(ISNUMBER(K48),ABS(K48-D49)<=0.01),"PASS","FAIL"),IF(NOT(ISNUMBER(K48)),"PASS","FAIL"))
B50: Gross Profit Rate | C50: =L48 | D50: 0.65909091 | E50: =IF(ISNUMBER(D50),IF(ISNUMBER(L48),ABS(L48-D50),"N/A"),"N/A") | F50: =IF(ISNUMBER(D50),IF(AND(ISNUMBER(L48),ABS(L48-D50)<=0.0001),"PASS","FAIL"),IF(NOT(ISNUMBER(L48)),"PASS","FAIL"))
B51: Variable Cost Total | C51: =M48 | D51: 587.2 | E51: =IF(ISNUMBER(D51),IF(ISNUMBER(M48),ABS(M48-D51),"N/A"),"N/A") | F51: =IF(ISNUMBER(D51),IF(AND(ISNUMBER(M48),ABS(M48-D51)<=0.01),"PASS","FAIL"),IF(NOT(ISNUMBER(M48)),"PASS","FAIL"))
B52: Contribution Margin | C52: =N48 | D52: 5212.8 | E52: =IF(ISNUMBER(D52),IF(ISNUMBER(N48),ABS(N48-D52),"N/A"),"N/A") | F52: =IF(ISNUMBER(D52),IF(AND(ISNUMBER(N48),ABS(N48-D52)<=0.01),"PASS","FAIL"),IF(NOT(ISNUMBER(N48)),"PASS","FAIL"))
B53: Contribution Margin Rate | C53: =O48 | D53: 0.59236364 | E53: =IF(ISNUMBER(D53),IF(ISNUMBER(O48),ABS(O48-D53),"N/A"),"N/A") | F53: =IF(ISNUMBER(D53),IF(AND(ISNUMBER(O48),ABS(O48-D53)<=0.0001),"PASS","FAIL"),IF(NOT(ISNUMBER(O48)),"PASS","FAIL"))
B55: Case 6 — VAT-exclusive display + VAT rate UNKNOWN + gross-payment fee
B56: Metric | C56: Excel Result | D56: Python Reference | E56: Difference | F56: PASS / FAIL
B57: Actual Price ex VAT | C57: =I58 | D57: 8800 | E57: =IF(ISNUMBER(D57),IF(ISNUMBER(I58),ABS(I58-D57),"N/A"),"N/A") | F57: =IF(ISNUMBER(D57),IF(AND(ISNUMBER(I58),ABS(I58-D57)<=0.01),"PASS","FAIL"),IF(NOT(ISNUMBER(I58)),"PASS","FAIL")) | H57: (local inputs) | I57: 8800 | J57: FALSE | L57: 3000 | M57: 0 | N57: 0.04 | O57: 200 | P57: 0
B58: Direct Cost Total | C58: =J58 | D58: 3000 | E58: =IF(ISNUMBER(D58),IF(ISNUMBER(J58),ABS(J58-D58),"N/A"),"N/A") | F58: =IF(ISNUMBER(D58),IF(AND(ISNUMBER(J58),ABS(J58-D58)<=0.01),"PASS","FAIL"),IF(NOT(ISNUMBER(J58)),"PASS","FAIL")) | I58: =IFERROR(IF(ISBLANK($I$57),"미입력",IF(ISBLANK($J$57),"미입력",IF($J$57=FALSE,$I$57,IF(ISBLANK($K$57),"미입력",$I$57/(1+$K$57))))),"계산불가") | J58: =IFERROR(IF(ISBLANK($L$57),"미입력",$L$57),"계산불가") | K58: =IFERROR(IF(AND(ISNUMBER(I58),ISNUMBER(J58)),I58-J58,"미입력"),"계산불가") | L58: =IFERROR(IF(OR(NOT(ISNUMBER(K58)),NOT(ISNUMBER(I58))),"미입력",IF(I58=0,"계산불가",K58/I58)),"계산불가") | M58: =IFERROR(IF(OR(ISBLANK($M$57),ISBLANK($N$57),ISBLANK($O$57),ISBLANK($P$57),NOT(ISNUMBER(I58)),NOT(ISNUMBER(P58))),"미입력",I58*$M$57+P58*$N$57+$O$57+$P$57),"계산불가") | N58: =IFERROR(IF(AND(ISNUMBER(K58),ISNUMBER(M58)),K58-M58,"미입력"),"계산불가") | O58: =IFERROR(IF(OR(NOT(ISNUMBER(N58)),NOT(ISNUMBER(I58))),"미입력",IF(I58=0,"계산불가",N58/I58)),"계산불가") | P58: =IFERROR(IF(ISBLANK($I$57),"미입력",IF(ISBLANK($J$57),"미입력",IF($J$57=TRUE,$I$57,IF(ISBLANK($K$57),"미입력",$I$57*(1+$K$57))))),"계산불가")
B59: Gross Profit | C59: =K58 | D59: 5800 | E59: =IF(ISNUMBER(D59),IF(ISNUMBER(K58),ABS(K58-D59),"N/A"),"N/A") | F59: =IF(ISNUMBER(D59),IF(AND(ISNUMBER(K58),ABS(K58-D59)<=0.01),"PASS","FAIL"),IF(NOT(ISNUMBER(K58)),"PASS","FAIL"))
B60: Gross Profit Rate | C60: =L58 | D60: 0.65909091 | E60: =IF(ISNUMBER(D60),IF(ISNUMBER(L58),ABS(L58-D60),"N/A"),"N/A") | F60: =IF(ISNUMBER(D60),IF(AND(ISNUMBER(L58),ABS(L58-D60)<=0.0001),"PASS","FAIL"),IF(NOT(ISNUMBER(L58)),"PASS","FAIL"))
B61: Variable Cost Total | C61: =M58 | D61: UNKNOWN | E61: =IF(ISNUMBER(D61),IF(ISNUMBER(M58),ABS(M58-D61),"N/A"),"N/A") | F61: =IF(ISNUMBER(D61),IF(AND(ISNUMBER(M58),ABS(M58-D61)<=0.01),"PASS","FAIL"),IF(NOT(ISNUMBER(M58)),"PASS","FAIL"))
B62: Contribution Margin | C62: =N58 | D62: UNKNOWN | E62: =IF(ISNUMBER(D62),IF(ISNUMBER(N58),ABS(N58-D62),"N/A"),"N/A") | F62: =IF(ISNUMBER(D62),IF(AND(ISNUMBER(N58),ABS(N58-D62)<=0.01),"PASS","FAIL"),IF(NOT(ISNUMBER(N58)),"PASS","FAIL"))
B63: Contribution Margin Rate | C63: =O58 | D63: UNKNOWN | E63: =IF(ISNUMBER(D63),IF(ISNUMBER(O58),ABS(O58-D63),"N/A"),"N/A") | F63: =IF(ISNUMBER(D63),IF(AND(ISNUMBER(O58),ABS(O58-D63)<=0.0001),"PASS","FAIL"),IF(NOT(ISNUMBER(O58)),"PASS","FAIL"))
B65: Overall
B66: All metrics PASS? | C66: =IF(COUNTIF(F7:F63,"FAIL")=0,"ALL PASS","SOME FAILED")

Sheet 04_MODE_B_SIMULATOR
B2: 04. MODE B Simulator — Target Price (Interactive)
B4: INPUT (노란 셀만 입력, 단일 컴포넌트 / shared cost 없음 기준)
B5: Target Contribution Margin Rate (t) | C5: 0.3 | D5: 0 이상 1 미만이어야 함 (>=1 또는 <0은 ERROR)
B6: Fixed-Amount Direct + Variable Cost (C) | C6: 10000 | D6: 직접원가 + 금액형 변동비 합계 (rate 기반 항목 제외)
B7: Net-Sales Fee Rate (b) | C7: 0 | D7: rate_of_net_sales 합계 — Net Sales(N)에 곱함. 없으면 0
B8: Gross-Payment Fee Rate (a) | C8: 0.05 | D8: rate_of_gross_payment 합계 — Gross Payment(G)에 곱함. 없으면 0
B9: Price Includes VAT | C9: FALSE | D9: TRUE→표시가=G / FALSE→표시가=N / 빈칸=모름(UNKNOWN)
B10: VAT Rate (v) | C10: 0.1 | D10: a=0이면 N 계산에 불필요. G는 a와 무관하게 항상 필요 (SPEC.md §3)
B11: Discount Rate | D11: 0 이상 1 미만이어야 함. 빈칸=UNKNOWN → 정가 계산 불가
B12: Shared Cost Status (Excel simulation control — not a schema field) | C12: none | D12: Excel-only simulation control. NOT a field in client_input.schema.json — the production Python engine (core/engine/modes/mode_b.py) derives this state from actual cost item / applies_to_component / allocation_rule data, never from a flag like this. none=shared 비용 없음(정상 계산) / unresolved=by_component_revenue·fixed_share 등 배부 미구현(모든 결과 UNKNOWN) / invalid=shared+direct 모순 설정(모든 결과 ERROR). 실제 배부 엔진은 구현하지 않음 — 미지원 상태를 조용히 숫자로 만들지 않는지만 검증
B14: RESULT (계산값 — 직접 입력 금지)
B15: Denominator | C15: =IFERROR(IF($C$12="invalid","ERROR",IF($C$12="unresolved","UNKNOWN",IF(OR(AND(NOT(ISBLANK($C$5)),OR($C$5<0,$C$5>=1)),AND(NOT(ISBLANK($C$7)),$C$7<0),AND(NOT(ISBLANK($C$8)),$C$8<0),AND(NOT(ISBLANK($C$6)),$C$6<0)),"ERROR",IF(OR(ISBLANK($C$5),ISBLANK($C$7),ISBLANK($C$8)),"UNKNOWN",IF($C$8=0,IF(1-$C$5-$C$7<=0,"ERROR",1-$C$5-$C$7),IF(ISBLANK($C$10),"UNKNOWN",IF(1-$C$5-$C$7-$C$8*(1+$C$10)<=0,"ERROR",1-$C$5-$C$7-$C$8*(1+$C$10)))))))),"ERROR") | D15: D = 1 - t - b - a(1+v). D<=0 → ERROR (목표 불가능)
B16: Required Net Sales ex VAT | C16: =IFERROR(IF(ISBLANK($C$6),"UNKNOWN",IF(NOT(ISNUMBER(C15)),C15,$C$6/C15)),"ERROR") | D16: N = C / D
B17: Required Gross Payment incl VAT | C17: =IFERROR(IF(NOT(ISNUMBER(C16)),C16,IF(ISBLANK($C$10),"UNKNOWN",C16*(1+$C$10))),"ERROR") | D17: G = N × (1+v) — 항상 v 필요
B18: Required Selling Price | C18: =IFERROR(IF(ISBLANK($C$9),"UNKNOWN",IF($C$9=FALSE,C16,C17)),"ERROR") | D18: price_includes_vat=FALSE→N / TRUE→G / 빈칸→UNKNOWN
B19: Required List Price | C19: =IFERROR(IF(NOT(ISNUMBER(C18)),C18,IF(ISBLANK($C$11),"UNKNOWN",IF(OR($C$11<0,$C$11>=1),"ERROR",IF($C$11=0,C18,C18/(1-$C$11))))),"ERROR") | D19: = 판매가 / (1 - discount_rate)
B20: Expected Contribution Margin | C20: =IFERROR(IF(NOT(ISNUMBER(C16)),C16,IF($C$8=0,C16-$C$6-$C$7*C16,IF(NOT(ISNUMBER(C17)),C17,C16-$C$6-$C$7*C16-$C$8*C17))),"ERROR") | D20: = N - C - b×N - a×G (역산식과 독립적인 비용구조 재계산)
B21: Expected CM Rate | C21: =IFERROR(IF(NOT(ISNUMBER(C20)),C20,IF(C16=0,"ERROR",C20/C16)),"ERROR") | D21: = CM / N — 아래 Self-Check에서 목표 t와 별도 대조
B23: Self-Check: |CMR − t| ≤ 0.0001? | C23: =IF(NOT(ISNUMBER(C21)),"N/A",IF(ABS(C21-$C$5)<=0.0001,"PASS","FAIL")) | D23: 역산식(N=C/D)과 독립적으로 재계산한 CMR(=CM/N)이 목표 t와 tolerance 내에서 일치하는지 진단. MODE B의 공식 출력 metric은 아님 — 산술 오류를 잡기 위한 진단용.
B24: STATUS
B25: Overall Status | C25: =IF((IF(C15="ERROR",1,0)+IF(C16="ERROR",1,0)+IF(C17="ERROR",1,0)+IF(C18="ERROR",1,0)+IF(C19="ERROR",1,0)+IF(C20="ERROR",1,0)+IF(C21="ERROR",1,0))>0,"ERROR — 목표 불가능 또는 입력값 모순",IF((IF(C15="UNKNOWN",1,0)+IF(C16="UNKNOWN",1,0)+IF(C17="UNKNOWN",1,0)+IF(C18="UNKNOWN",1,0)+IF(C19="UNKNOWN",1,0)+IF(C20="UNKNOWN",1,0)+IF(C21="UNKNOWN",1,0))>0,"INCOMPLETE — 일부 지표 UNKNOWN","OK — 전체 계산 완료"))
B26: blank = UNKNOWN / 0 = explicit zero
B28: DASHBOARD CARD
B29: Required Net Sales ex VAT | E29: Required Gross Payment | H29: Required Selling Price
B30: =C16 | E30: =C17 | H30: =C18
B32: Required List Price | E32: Expected CM | H32: Expected CM Rate
B33: =C19 | E33: =C20 | H33: =C21

Sheet 05_MODE_B_PARITY_TEST
B2: 05. Python Engine vs Excel Formula — MODE B Parity Test
B3: 각 케이스는 Excel에 동일 입력값을 리터럴로 심어 04_MODE_B_SIMULATOR와 같은 수식(build_mode_b_formulas)으로 독립 재계산하고, Python 참조값(core/engine/modes/mode_b.py 실행 결과, 빌드 시점에 고정)과 비교합니다. 허용오차 0.01(금액) / 0.0001(비율). #14/#15는 shared-cost 시나리오로, 실제 배부(allocation) 금액을 계산하지는 않지만 Shared Cost Status 플래그를 통해 Excel이 '미지원 상태를 UNKNOWN/ERROR로 정확히 표시하는지'를 실시간으로 평가합니다 — 다른 13개 케이스와 동일하게 15/15 전부 live parity입니다.
B5: 1. Simple — no rate cost at all (TC1)
B6: Metric | C6: Excel Result | D6: Python Reference | E6: Difference | F6: PASS / FAIL
B7: Denominator | C7: =Q7 | D7: 0.6 | E7: =IF(ISNUMBER(D7),IF(ISNUMBER(Q7),ABS(Q7-D7),"N/A"),"N/A") | F7: =IF(ISNUMBER(D7),IF(AND(ISNUMBER(Q7),ABS(Q7-D7)<=0.01),"PASS","FAIL"),IF(AND(NOT(ISNUMBER(Q7)),Q7=D7),"PASS","FAIL")) | I7: 0.4 | J7: 10000 | K7: 0 | L7: 0 | M7: 0.1 | N7: FALSE | P7: none | Q7: =IFERROR(IF($P$7="invalid","ERROR",IF($P$7="unresolved","UNKNOWN",IF(OR(AND(NOT(ISBLANK($I$7)),OR($I$7<0,$I$7>=1)),AND(NOT(ISBLANK($K$7)),$K$7<0),AND(NOT(ISBLANK($L$7)),$L$7<0),AND(NOT(ISBLANK($J$7)),$J$7<0)),"ERROR",IF(OR(ISBLANK($I$7),ISBLANK($K$7),ISBLANK($L$7)),"UNKNOWN",IF($L$7=0,IF(1-$I$7-$K$7<=0,"ERROR",1-$I$7-$K$7),IF(ISBLANK($M$7),"UNKNOWN",IF(1-$I$7-$K$7-$L$7*(1+$M$7)<=0,"ERROR",1-$I$7-$K$7-$L$7*(1+$M$7)))))))),"ERROR") | R7: =IFERROR(IF(ISBLANK($J$7),"UNKNOWN",IF(NOT(ISNUMBER(Q7)),Q7,$J$7/Q7)),"ERROR") | S7: =IFERROR(IF(NOT(ISNUMBER(R7)),R7,IF(ISBLANK($M$7),"UNKNOWN",R7*(1+$M$7))),"ERROR") | T7: =IFERROR(IF(ISBLANK($N$7),"UNKNOWN",IF($N$7=FALSE,R7,S7)),"ERROR") | U7: =IFERROR(IF(NOT(ISNUMBER(T7)),T7,IF(ISBLANK($O$7),"UNKNOWN",IF(OR($O$7<0,$O$7>=1),"ERROR",IF($O$7=0,T7,T7/(1-$O$7))))),"ERROR") | V7: =IFERROR(IF(NOT(ISNUMBER(R7)),R7,IF($L$7=0,R7-$J$7-$K$7*R7,IF(NOT(ISNUMBER(S7)),S7,R7-$J$7-$K$7*R7-$L$7*S7))),"ERROR") | W7: =IFERROR(IF(NOT(ISNUMBER(V7)),V7,IF(R7=0,"ERROR",V7/R7)),"ERROR")
B8: Required Net Sales ex VAT | C8: =R7 | D8: 16666.667 | E8: =IF(ISNUMBER(D8),IF(ISNUMBER(R7),ABS(R7-D8),"N/A"),"N/A") | F8: =IF(ISNUMBER(D8),IF(AND(ISNUMBER(R7),ABS(R7-D8)<=0.01),"PASS","FAIL"),IF(AND(NOT(ISNUMBER(R7)),R7=D8),"PASS","FAIL"))
B9: Required Gross Payment incl VAT | C9: =S7 | D9: 18333.333 | E9: =IF(ISNUMBER(D9),IF(ISNUMBER(S7),ABS(S7-D9),"N/A"),"N/A") | F9: =IF(ISNUMBER(D9),IF(AND(ISNUMBER(S7),ABS(S7-D9)<=0.01),"PASS","FAIL"),IF(AND(NOT(ISNUMBER(S7)),S7=D9),"PASS","FAIL"))
B10: Required Selling Price | C10: =T7 | D10: 16666.667 | E10: =IF(ISNUMBER(D10),IF(ISNUMBER(T7),ABS(T7-D10),"N/A"),"N/A") | F10: =IF(ISNUMBER(D10),IF(AND(ISNUMBER(T7),ABS(T7-D10)<=0.01),"PASS","FAIL"),IF(AND(NOT(ISNUMBER(T7)),T7=D10),"PASS","FAIL"))
B11: Required List Price | C11: =U7 | D11: UNKNOWN | E11: =IF(ISNUMBER(D11),IF(ISNUMBER(U7),ABS(U7-D11),"N/A"),"N/A") | F11: =IF(ISNUMBER(D11),IF(AND(ISNUMBER(U7),ABS(U7-D11)<=0.01),"PASS","FAIL"),IF(AND(NOT(ISNUMBER(U7)),U7=D11),"PASS","FAIL"))
B12: Expected Contribution Margin | C12: =V7 | D12: 6666.6667 | E12: =IF(ISNUMBER(D12),IF(ISNUMBER(V7),ABS(V7-D12),"N/A"),"N/A") | F12: =IF(ISNUMBER(D12),IF(AND(ISNUMBER(V7),ABS(V7-D12)<=0.01),"PASS","FAIL"),IF(AND(NOT(ISNUMBER(V7)),V7=D12),"PASS","FAIL"))
B13: Expected CM Rate | C13: =W7 | D13: 0.4 | E13: =IF(ISNUMBER(D13),IF(ISNUMBER(W7),ABS(W7-D13),"N/A"),"N/A") | F13: =IF(ISNUMBER(D13),IF(AND(ISNUMBER(W7),ABS(W7-D13)<=0.0001),"PASS","FAIL"),IF(AND(NOT(ISNUMBER(W7)),W7=D13),"PASS","FAIL"))
B15: 2. Net-sales fee only (TC2)
B16: Metric | C16: Excel Result | D16: Python Reference | E16: Difference | F16: PASS / FAIL
B17: Denominator | C17: =Q17 | D17: 0.6 | E17: =IF(ISNUMBER(D17),IF(ISNUMBER(Q17),ABS(Q17-D17),"N/A"),"N/A") | F17: =IF(ISNUMBER(D17),IF(AND(ISNUMBER(Q17),ABS(Q17-D17)<=0.01),"PASS","FAIL"),IF(AND(NOT(ISNUMBER(Q17)),Q17=D17),"PASS","FAIL")) | I17: 0.3 | J17: 10000 | K17: 0.1 | L17: 0 | M17: 0.1 | N17: FALSE | P17: none | Q17: =IFERROR(IF($P$17="invalid","ERROR",IF($P$17="unresolved","UNKNOWN",IF(OR(AND(NOT(ISBLANK($I$17)),OR($I$17<0,$I$17>=1)),AND(NOT(ISBLANK($K$17)),$K$17<0),AND(NOT(ISBLANK($L$17)),$L$17<0),AND(NOT(ISBLANK($J$17)),$J$17<0)),"ERROR",IF(OR(ISBLANK($I$17),ISBLANK($K$17),ISBLANK($L$17)),"UNKNOWN",IF($L$17=0,IF(1-$I$17-$K$17<=0,"ERROR",1-$I$17-$K$17),IF(ISBLANK($M$17),"UNKNOWN",IF(1-$I$17-$K$17-$L$17*(1+$M$17)<=0,"ERROR",1-$I$17-$K$17-$L$17*(1+$M$17)))))))),"ERROR") | R17: =IFERROR(IF(ISBLANK($J$17),"UNKNOWN",IF(NOT(ISNUMBER(Q17)),Q17,$J$17/Q17)),"ERROR") | S17: =IFERROR(IF(NOT(ISNUMBER(R17)),R17,IF(ISBLANK($M$17),"UNKNOWN",R17*(1+$M$17))),"ERROR") | T17: =IFERROR(IF(ISBLANK($N$17),"UNKNOWN",IF($N$17=FALSE,R17,S17)),"ERROR") | U17: =IFERROR(IF(NOT(ISNUMBER(T17)),T17,IF(ISBLANK($O$17),"UNKNOWN",IF(OR($O$17<0,$O$17>=1),"ERROR",IF($O$17=0,T17,T17/(1-$O$17))))),"ERROR") | V17: =IFERROR(IF(NOT(ISNUMBER(R17)),R17,IF($L$17=0,R17-$J$17-$K$17*R17,IF(NOT(ISNUMBER(S17)),S17,R17-$J$17-$K$17*R17-$L$17*S17))),"ERROR") | W17: =IFERROR(IF(NOT(ISNUMBER(V17)),V17,IF(R17=0,"ERROR",V17/R17)),"ERROR")
B18: Required Net Sales ex VAT | C18: =R17 | D18: 16666.667 | E18: =IF(ISNUMBER(D18),IF(ISNUMBER(R17),ABS(R17-D18),"N/A"),"N/A") | F18: =IF(ISNUMBER(D18),IF(AND(ISNUMBER(R17),ABS(R17-D18)<=0.01),"PASS","FAIL"),IF(AND(NOT(ISNUMBER(R17)),R17=D18),"PASS","FAIL"))
B19: Required Gross Payment incl VAT | C19: =S17 | D19: 18333.333 | E19: =IF(ISNUMBER(D19),IF(ISNUMBER(S17),ABS(S17-D19),"N/A"),"N/A") | F19: =IF(ISNUMBER(D19),IF(AND(ISNUMBER(S17),ABS(S17-D19)<=0.01),"PASS","FAIL"),IF(AND(NOT(ISNUMBER(S17)),S17=D19),"PASS","FAIL"))
B20: Required Selling Price | C20: =T17 | D20: 16666.667 | E20: =IF(ISNUMBER(D20),IF(ISNUMBER(T17),ABS(T17-D20),"N/A"),"N/A") | F20: =IF(ISNUMBER(D20),IF(AND(ISNUMBER(T17),ABS(T17-D20)<=0.01),"PASS","FAIL"),IF(AND(NOT(ISNUMBER(T17)),T17=D20),"PASS","FAIL"))
B21: Required List Price | C21: =U17 | D21: UNKNOWN | E21: =IF(ISNUMBER(D21),IF(ISNUMBER(U17),ABS(U17-D21),"N/A"),"N/A") | F21: =IF(ISNUMBER(D21),IF(AND(ISNUMBER(U17),ABS(U17-D21)<=0.01),"PASS","FAIL"),IF(AND(NOT(ISNUMBER(U17)),U17=D21),"PASS","FAIL"))
B22: Expected Contribution Margin | C22: =V17 | D22: 5000 | E22: =IF(ISNUMBER(D22),IF(ISNUMBER(V17),ABS(V17-D22),"N/A"),"N/A") | F22: =IF(ISNUMBER(D22),IF(AND(ISNUMBER(V17),ABS(V17-D22)<=0.01),"PASS","FAIL"),IF(AND(NOT(ISNUMBER(V17)),V17=D22),"PASS","FAIL"))
B23: Expected CM Rate | C23: =W17 | D23: 0.3 | E23: =IF(ISNUMBER(D23),IF(ISNUMBER(W17),ABS(W17-D23),"N/A"),"N/A") | F23: =IF(ISNUMBER(D23),IF(AND(ISNUMBER(W17),ABS(W17-D23)<=0.0001),"PASS","FAIL"),IF(AND(NOT(ISNUMBER(W17)),W17=D23),"PASS","FAIL"))
B25: 3. Gross-payment fee only, VAT-exclusive display (TC3)
B26: Metric | C26: Excel Result | D26: Python Reference | E26: Difference | F26: PASS / FAIL
B27: Denominator | C27: =Q27 | D27: 0.645 | E27: =IF(ISNUMBER(D27),IF(ISNUMBER(Q27),ABS(Q27-D27),"N/A"),"N/A") | F27: =IF(ISNUMBER(D27),IF(AND(ISNUMBER(Q27),ABS(Q27-D27)<=0.01),"PASS","FAIL"),IF(AND(NOT(ISNUMBER(Q27)),Q27=D27),"PASS","FAIL")) | I27: 0.3 | J27: 10000 | K27: 0 | L27: 0.05 | M27: 0.1 | N27: FALSE | P27: none | Q27: =IFERROR(IF($P$27="invalid","ERROR",IF($P$27="unresolved","UNKNOWN",IF(OR(AND(NOT(ISBLANK($I$27)),OR($I$27<0,$I$27>=1)),AND(NOT(ISBLANK($K$27)),$K$27<0),AND(NOT(ISBLANK($L$27)),$L$27<0),AND(NOT(ISBLANK($J$27)),$J$27<0)),"ERROR",IF(OR(ISBLANK($I$27),ISBLANK($K$27),ISBLANK($L$27)),"UNKNOWN",IF($L$27=0,IF(1-$I$27-$K$27<=0,"ERROR",1-$I$27-$K$27),IF(ISBLANK($M$27),"UNKNOWN",IF(1-$I$27-$K$27-$L$27*(1+$M$27)<=0,"ERROR",1-$I$27-$K$27-$L$27*(1+$M$27)))))))),"ERROR") | R27: =IFERROR(IF(ISBLANK($J$27),"UNKNOWN",IF(NOT(ISNUMBER(Q27)),Q27,$J$27/Q27)),"ERROR") | S27: =IFERROR(IF(NOT(ISNUMBER(R27)),R27,IF(ISBLANK($M$27),"UNKNOWN",R27*(1+$M$27))),"ERROR") | T27: =IFERROR(IF(ISBLANK($N$27),"UNKNOWN",IF($N$27=FALSE,R27,S27)),"ERROR") | U27: =IFERROR(IF(NOT(ISNUMBER(T27)),T27,IF(ISBLANK($O$27),"UNKNOWN",IF(OR($O$27<0,$O$27>=1),"ERROR",IF($O$27=0,T27,T27/(1-$O$27))))),"ERROR") | V27: =IFERROR(IF(NOT(ISNUMBER(R27)),R27,IF($L$27=0,R27-$J$27-$K$27*R27,IF(NOT(ISNUMBER(S27)),S27,R27-$J$27-$K$27*R27-$L$27*S27))),"ERROR") | W27: =IFERROR(IF(NOT(ISNUMBER(V27)),V27,IF(R27=0,"ERROR",V27/R27)),"ERROR")
B28: Required Net Sales ex VAT | C28: =R27 | D28: 15503.876 | E28: =IF(ISNUMBER(D28),IF(ISNUMBER(R27),ABS(R27-D28),"N/A"),"N/A") | F28: =IF(ISNUMBER(D28),IF(AND(ISNUMBER(R27),ABS(R27-D28)<=0.01),"PASS","FAIL"),IF(AND(NOT(ISNUMBER(R27)),R27=D28),"PASS","FAIL"))
B29: Required Gross Payment incl VAT | C29: =S27 | D29: 17054.264 | E29: =IF(ISNUMBER(D29),IF(ISNUMBER(S27),ABS(S27-D29),"N/A"),"N/A") | F29: =IF(ISNUMBER(D29),IF(AND(ISNUMBER(S27),ABS(S27-D29)<=0.01),"PASS","FAIL"),IF(AND(NOT(ISNUMBER(S27)),S27=D29),"PASS","FAIL"))
B30: Required Selling Price | C30: =T27 | D30: 15503.876 | E30: =IF(ISNUMBER(D30),IF(ISNUMBER(T27),ABS(T27-D30),"N/A"),"N/A") | F30: =IF(ISNUMBER(D30),IF(AND(ISNUMBER(T27),ABS(T27-D30)<=0.01),"PASS","FAIL"),IF(AND(NOT(ISNUMBER(T27)),T27=D30),"PASS","FAIL"))
B31: Required List Price | C31: =U27 | D31: UNKNOWN | E31: =IF(ISNUMBER(D31),IF(ISNUMBER(U27),ABS(U27-D31),"N/A"),"N/A") | F31: =IF(ISNUMBER(D31),IF(AND(ISNUMBER(U27),ABS(U27-D31)<=0.01),"PASS","FAIL"),IF(AND(NOT(ISNUMBER(U27)),U27=D31),"PASS","FAIL"))
B32: Expected Contribution Margin | C32: =V27 | D32: 4651.1628 | E32: =IF(ISNUMBER(D32),IF(ISNUMBER(V27),ABS(V27-D32),"N/A"),"N/A") | F32: =IF(ISNUMBER(D32),IF(AND(ISNUMBER(V27),ABS(V27-D32)<=0.01),"PASS","FAIL"),IF(AND(NOT(ISNUMBER(V27)),V27=D32),"PASS","FAIL"))
B33: Expected CM Rate | C33: =W27 | D33: 0.3 | E33: =IF(ISNUMBER(D33),IF(ISNUMBER(W27),ABS(W27-D33),"N/A"),"N/A") | F33: =IF(ISNUMBER(D33),IF(AND(ISNUMBER(W27),ABS(W27-D33)<=0.0001),"PASS","FAIL"),IF(AND(NOT(ISNUMBER(W27)),W27=D33),"PASS","FAIL"))
B35: 4. VAT-inclusive display, both fee types (TC4)
B36: Metric | C36: Excel Result | D36: Python Reference | E36: Difference | F36: PASS / FAIL
B37: Denominator | C37: =Q37 | D37: 0.567 | E37: =IF(ISNUMBER(D37),IF(ISNUMBER(Q37),ABS(Q37-D37),"N/A"),"N/A") | F37: =IF(ISNUMBER(D37),IF(AND(ISNUMBER(Q37),ABS(Q37-D37)<=0.01),"PASS","FAIL"),IF(AND(NOT(ISNUMBER(Q37)),Q37=D37),"PASS","FAIL")) | I37: 0.3 | J37: 10000 | K37: 0.1 | L37: 0.03 | M37: 0.1 | N37: TRUE | P37: none | Q37: =IFERROR(IF($P$37="invalid","ERROR",IF($P$37="unresolved","UNKNOWN",IF(OR(AND(NOT(ISBLANK($I$37)),OR($I$37<0,$I$37>=1)),AND(NOT(ISBLANK($K$37)),$K$37<0),AND(NOT(ISBLANK($L$37)),$L$37<0),AND(NOT(ISBLANK($J$37)),$J$37<0)),"ERROR",IF(OR(ISBLANK($I$37),ISBLANK($K$37),ISBLANK($L$37)),"UNKNOWN",IF($L$37=0,IF(1-$I$37-$K$37<=0,"ERROR",1-$I$37-$K$37),IF(ISBLANK($M$37),"UNKNOWN",IF(1-$I$37-$K$37-$L$37*(1+$M$37)<=0,"ERROR",1-$I$37-$K$37-$L$37*(1+$M$37)))))))),"ERROR") | R37: =IFERROR(IF(ISBLANK($J$37),"UNKNOWN",IF(NOT(ISNUMBER(Q37)),Q37,$J$37/Q37)),"ERROR") | S37: =IFERROR(IF(NOT(ISNUMBER(R37)),R37,IF(ISBLANK($M$37),"UNKNOWN",R37*(1+$M$37))),"ERROR") | T37: =IFERROR(IF(ISBLANK($N$37),"UNKNOWN",IF($N$37=FALSE,R37,S37)),"ERROR") | U37: =IFERROR(IF(NOT(ISNUMBER(T37)),T37,IF(ISBLANK($O$37),"UNKNOWN",IF(OR($O$37<0,$O$37>=1),"ERROR",IF($O$37=0,T37,T37/(1-$O$37))))),"ERROR") | V37: =IFERROR(IF(NOT(ISNUMBER(R37)),R37,IF($L$37=0,R37-$J$37-$K$37*R37,IF(NOT(ISNUMBER(S37)),S37,R37-$J$37-$K$37*R37-$L$37*S37))),"ERROR") | W37: =IFERROR(IF(NOT(ISNUMBER(V37)),V37,IF(R37=0,"ERROR",V37/R37)),"ERROR")
B38: Required Net Sales ex VAT | C38: =R37 | D38: 17636.684 | E38: =IF(ISNUMBER(D38),IF(ISNUMBER(R37),ABS(R37-D38),"N/A"),"N/A") | F38: =IF(ISNUMBER(D38),IF(AND(ISNUMBER(R37),ABS(R37-D38)<=0.01),"PASS","FAIL"),IF(AND(NOT(ISNUMBER(R37)),R37=D38),"PASS","FAIL"))
B39: Required Gross Payment incl VAT | C39: =S37 | D39: 19400.353 | E39: =IF(ISNUMBER(D39),IF(ISNUMBER(S37),ABS(S37-D39),"N/A"),"N/A") | F39: =IF(ISNUMBER(D39),IF(AND(ISNUMBER(S37),ABS(S37-D39)<=0.01),"PASS","FAIL"),IF(AND(NOT(ISNUMBER(S37)),S37=D39),"PASS","FAIL"))
B40: Required Selling Price | C40: =T37 | D40: 19400.353 | E40: =IF(ISNUMBER(D40),IF(ISNUMBER(T37),ABS(T37-D40),"N/A"),"N/A") | F40: =IF(ISNUMBER(D40),IF(AND(ISNUMBER(T37),ABS(T37-D40)<=0.01),"PASS","FAIL"),IF(AND(NOT(ISNUMBER(T37)),T37=D40),"PASS","FAIL"))
B41: Required List Price | C41: =U37 | D41: UNKNOWN | E41: =IF(ISNUMBER(D41),IF(ISNUMBER(U37),ABS(U37-D41),"N/A"),"N/A") | F41: =IF(ISNUMBER(D41),IF(AND(ISNUMBER(U37),ABS(U37-D41)<=0.01),"PASS","FAIL"),IF(AND(NOT(ISNUMBER(U37)),U37=D41),"PASS","FAIL"))
B42: Expected Contribution Margin | C42: =V37 | D42: 5291.0053 | E42: =IF(ISNUMBER(D42),IF(ISNUMBER(V37),ABS(V37-D42),"N/A"),"N/A") | F42: =IF(ISNUMBER(D42),IF(AND(ISNUMBER(V37),ABS(V37-D42)<=0.01),"PASS","FAIL"),IF(AND(NOT(ISNUMBER(V37)),V37=D42),"PASS","FAIL"))
B43: Expected CM Rate | C43: =W37 | D43: 0.3 | E43: =IF(ISNUMBER(D43),IF(ISNUMBER(W37),ABS(W37-D43),"N/A"),"N/A") | F43: =IF(ISNUMBER(D43),IF(AND(ISNUMBER(W37),ABS(W37-D43)<=0.0001),"PASS","FAIL"),IF(AND(NOT(ISNUMBER(W37)),W37=D43),"PASS","FAIL"))
B45: 5. VAT-exclusive display, both fee types (TC5)
B46: Metric | C46: Excel Result | D46: Python Reference | E46: Difference | F46: PASS / FAIL
B47: Denominator | C47: =Q47 | D47: 0.678 | E47: =IF(ISNUMBER(D47),IF(ISNUMBER(Q47),ABS(Q47-D47),"N/A"),"N/A") | F47: =IF(ISNUMBER(D47),IF(AND(ISNUMBER(Q47),ABS(Q47-D47)<=0.01),"PASS","FAIL"),IF(AND(NOT(ISNUMBER(Q47)),Q47=D47),"PASS","FAIL")) | I47: 0.25 | J47: 8000 | K47: 0.05 | L47: 0.02 | M47: 0.1 | N47: FALSE | P47: none | Q47: =IFERROR(IF($P$47="invalid","ERROR",IF($P$47="unresolved","UNKNOWN",IF(OR(AND(NOT(ISBLANK($I$47)),OR($I$47<0,$I$47>=1)),AND(NOT(ISBLANK($K$47)),$K$47<0),AND(NOT(ISBLANK($L$47)),$L$47<0),AND(NOT(ISBLANK($J$47)),$J$47<0)),"ERROR",IF(OR(ISBLANK($I$47),ISBLANK($K$47),ISBLANK($L$47)),"UNKNOWN",IF($L$47=0,IF(1-$I$47-$K$47<=0,"ERROR",1-$I$47-$K$47),IF(ISBLANK($M$47),"UNKNOWN",IF(1-$I$47-$K$47-$L$47*(1+$M$47)<=0,"ERROR",1-$I$47-$K$47-$L$47*(1+$M$47)))))))),"ERROR") | R47: =IFERROR(IF(ISBLANK($J$47),"UNKNOWN",IF(NOT(ISNUMBER(Q47)),Q47,$J$47/Q47)),"ERROR") | S47: =IFERROR(IF(NOT(ISNUMBER(R47)),R47,IF(ISBLANK($M$47),"UNKNOWN",R47*(1+$M$47))),"ERROR") | T47: =IFERROR(IF(ISBLANK($N$47),"UNKNOWN",IF($N$47=FALSE,R47,S47)),"ERROR") | U47: =IFERROR(IF(NOT(ISNUMBER(T47)),T47,IF(ISBLANK($O$47),"UNKNOWN",IF(OR($O$47<0,$O$47>=1),"ERROR",IF($O$47=0,T47,T47/(1-$O$47))))),"ERROR") | V47: =IFERROR(IF(NOT(ISNUMBER(R47)),R47,IF($L$47=0,R47-$J$47-$K$47*R47,IF(NOT(ISNUMBER(S47)),S47,R47-$J$47-$K$47*R47-$L$47*S47))),"ERROR") | W47: =IFERROR(IF(NOT(ISNUMBER(V47)),V47,IF(R47=0,"ERROR",V47/R47)),"ERROR")
B48: Required Net Sales ex VAT | C48: =R47 | D48: 11799.41 | E48: =IF(ISNUMBER(D48),IF(ISNUMBER(R47),ABS(R47-D48),"N/A"),"N/A") | F48: =IF(ISNUMBER(D48),IF(AND(ISNUMBER(R47),ABS(R47-D48)<=0.01),"PASS","FAIL"),IF(AND(NOT(ISNUMBER(R47)),R47=D48),"PASS","FAIL"))
B49: Required Gross Payment incl VAT | C49: =S47 | D49: 12979.351 | E49: =IF(ISNUMBER(D49),IF(ISNUMBER(S47),ABS(S47-D49),"N/A"),"N/A") | F49: =IF(ISNUMBER(D49),IF(AND(ISNUMBER(S47),ABS(S47-D49)<=0.01),"PASS","FAIL"),IF(AND(NOT(ISNUMBER(S47)),S47=D49),"PASS","FAIL"))
B50: Required Selling Price | C50: =T47 | D50: 11799.41 | E50: =IF(ISNUMBER(D50),IF(ISNUMBER(T47),ABS(T47-D50),"N/A"),"N/A") | F50: =IF(ISNUMBER(D50),IF(AND(ISNUMBER(T47),ABS(T47-D50)<=0.01),"PASS","FAIL"),IF(AND(NOT(ISNUMBER(T47)),T47=D50),"PASS","FAIL"))
B51: Required List Price | C51: =U47 | D51: UNKNOWN | E51: =IF(ISNUMBER(D51),IF(ISNUMBER(U47),ABS(U47-D51),"N/A"),"N/A") | F51: =IF(ISNUMBER(D51),IF(AND(ISNUMBER(U47),ABS(U47-D51)<=0.01),"PASS","FAIL"),IF(AND(NOT(ISNUMBER(U47)),U47=D51),"PASS","FAIL"))
B52: Expected Contribution Margin | C52: =V47 | D52: 2949.8525 | E52: =IF(ISNUMBER(D52),IF(ISNUMBER(V47),ABS(V47-D52),"N/A"),"N/A") | F52: =IF(ISNUMBER(D52),IF(AND(ISNUMBER(V47),ABS(V47-D52)<=0.01),"PASS","FAIL"),IF(AND(NOT(ISNUMBER(V47)),V47=D52),"PASS","FAIL"))
B53: Expected CM Rate | C53: =W47 | D53: 0.25 | E53: =IF(ISNUMBER(D53),IF(ISNUMBER(W47),ABS(W47-D53),"N/A"),"N/A") | F53: =IF(ISNUMBER(D53),IF(AND(ISNUMBER(W47),ABS(W47-D53)<=0.0001),"PASS","FAIL"),IF(AND(NOT(ISNUMBER(W47)),W47=D53),"PASS","FAIL"))
B55: 6. VAT-exclusive, VAT UNKNOWN, gross-payment fee (TC11)
B56: Metric | C56: Excel Result | D56: Python Reference | E56: Difference | F56: PASS / FAIL
B57: Denominator | C57: =Q57 | D57: UNKNOWN | E57: =IF(ISNUMBER(D57),IF(ISNUMBER(Q57),ABS(Q57-D57),"N/A"),"N/A") | F57: =IF(ISNUMBER(D57),IF(AND(ISNUMBER(Q57),ABS(Q57-D57)<=0.01),"PASS","FAIL"),IF(AND(NOT(ISNUMBER(Q57)),Q57=D57),"PASS","FAIL")) | I57: 0.3 | J57: 10000 | K57: 0 | L57: 0.05 | N57: FALSE | P57: none | Q57: =IFERROR(IF($P$57="invalid","ERROR",IF($P$57="unresolved","UNKNOWN",IF(OR(AND(NOT(ISBLANK($I$57)),OR($I$57<0,$I$57>=1)),AND(NOT(ISBLANK($K$57)),$K$57<0),AND(NOT(ISBLANK($L$57)),$L$57<0),AND(NOT(ISBLANK($J$57)),$J$57<0)),"ERROR",IF(OR(ISBLANK($I$57),ISBLANK($K$57),ISBLANK($L$57)),"UNKNOWN",IF($L$57=0,IF(1-$I$57-$K$57<=0,"ERROR",1-$I$57-$K$57),IF(ISBLANK($M$57),"UNKNOWN",IF(1-$I$57-$K$57-$L$57*(1+$M$57)<=0,"ERROR",1-$I$57-$K$57-$L$57*(1+$M$57)))))))),"ERROR") | R57: =IFERROR(IF(ISBLANK($J$57),"UNKNOWN",IF(NOT(ISNUMBER(Q57)),Q57,$J$57/Q57)),"ERROR") | S57: =IFERROR(IF(NOT(ISNUMBER(R57)),R57,IF(ISBLANK($M$57),"UNKNOWN",R57*(1+$M$57))),"ERROR") | T57: =IFERROR(IF(ISBLANK($N$57),"UNKNOWN",IF($N$57=FALSE,R57,S57)),"ERROR") | U57: =IFERROR(IF(NOT(ISNUMBER(T57)),T57,IF(ISBLANK($O$57),"UNKNOWN",IF(OR($O$57<0,$O$57>=1),"ERROR",IF($O$57=0,T57,T57/(1-$O$57))))),"ERROR") | V57: =IFERROR(IF(NOT(ISNUMBER(R57)),R57,IF($L$57=0,R57-$J$57-$K$57*R57,IF(NOT(ISNUMBER(S57)),S57,R57-$J$57-$K$57*R57-$L$57*S57))),"ERROR") | W57: =IFERROR(IF(NOT(ISNUMBER(V57)),V57,IF(R57=0,"ERROR",V57/R57)),"ERROR")
B58: Required Net Sales ex VAT | C58: =R57 | D58: UNKNOWN | E58: =IF(ISNUMBER(D58),IF(ISNUMBER(R57),ABS(R57-D58),"N/A"),"N/A") | F58: =IF(ISNUMBER(D58),IF(AND(ISNUMBER(R57),ABS(R57-D58)<=0.01),"PASS","FAIL"),IF(AND(NOT(ISNUMBER(R57)),R57=D58),"PASS","FAIL"))
B59: Required Gross Payment incl VAT | C59: =S57 | D59: UNKNOWN | E59: =IF(ISNUMBER(D59),IF(ISNUMBER(S57),ABS(S57-D59),"N/A"),"N/A") | F59: =IF(ISNUMBER(D59),IF(AND(ISNUMBER(S57),ABS(S57-D59)<=0.01),"PASS","FAIL"),IF(AND(NOT(ISNUMBER(S57)),S57=D59),"PASS","FAIL"))
B60: Required Selling Price | C60: =T57 | D60: UNKNOWN | E60: =IF(ISNUMBER(D60),IF(ISNUMBER(T57),ABS(T57-D60),"N/A"),"N/A") | F60: =IF(ISNUMBER(D60),IF(AND(ISNUMBER(T57),ABS(T57-D60)<=0.01),"PASS","FAIL"),IF(AND(NOT(ISNUMBER(T57)),T57=D60),"PASS","FAIL"))
B61: Required List Price | C61: =U57 | D61: UNKNOWN | E61: =IF(ISNUMBER(D61),IF(ISNUMBER(U57),ABS(U57-D61),"N/A"),"N/A") | F61: =IF(ISNUMBER(D61),IF(AND(ISNUMBER(U57),ABS(U57-D61)<=0.01),"PASS","FAIL"),IF(AND(NOT(ISNUMBER(U57)),U57=D61),"PASS","FAIL"))
B62: Expected Contribution Margin | C62: =V57 | D62: UNKNOWN | E62: =IF(ISNUMBER(D62),IF(ISNUMBER(V57),ABS(V57-D62),"N/A"),"N/A") | F62: =IF(ISNUMBER(D62),IF(AND(ISNUMBER(V57),ABS(V57-D62)<=0.01),"PASS","FAIL"),IF(AND(NOT(ISNUMBER(V57)),V57=D62),"PASS","FAIL"))
B63: Expected CM Rate | C63: =W57 | D63: UNKNOWN | E63: =IF(ISNUMBER(D63),IF(ISNUMBER(W57),ABS(W57-D63),"N/A"),"N/A") | F63: =IF(ISNUMBER(D63),IF(AND(ISNUMBER(W57),ABS(W57-D63)<=0.0001),"PASS","FAIL"),IF(AND(NOT(ISNUMBER(W57)),W57=D63),"PASS","FAIL"))
B65: 7. VAT-exclusive, VAT UNKNOWN, net-sales fee only (TC12)
B66: Metric | C66: Excel Result | D66: Python Reference | E66: Difference | F66: PASS / FAIL
B67: Denominator | C67: =Q67 | D67: 0.6 | E67: =IF(ISNUMBER(D67),IF(ISNUMBER(Q67),ABS(Q67-D67),"N/A"),"N/A") | F67: =IF(ISNUMBER(D67),IF(AND(ISNUMBER(Q67),ABS(Q67-D67)<=0.01),"PASS","FAIL"),IF(AND(NOT(ISNUMBER(Q67)),Q67=D67),"PASS","FAIL")) | I67: 0.3 | J67: 10000 | K67: 0.1 | L67: 0 | N67: FALSE | P67: none | Q67: =IFERROR(IF($P$67="invalid","ERROR",IF($P$67="unresolved","UNKNOWN",IF(OR(AND(NOT(ISBLANK($I$67)),OR($I$67<0,$I$67>=1)),AND(NOT(ISBLANK($K$67)),$K$67<0),AND(NOT(ISBLANK($L$67)),$L$67<0),AND(NOT(ISBLANK($J$67)),$J$67<0)),"ERROR",IF(OR(ISBLANK($I$67),ISBLANK($K$67),ISBLANK($L$67)),"UNKNOWN",IF($L$67=0,IF(1-$I$67-$K$67<=0,"ERROR",1-$I$67-$K$67),IF(ISBLANK($M$67),"UNKNOWN",IF(1-$I$67-$K$67-$L$67*(1+$M$67)<=0,"ERROR",1-$I$67-$K$67-$L$67*(1+$M$67)))))))),"ERROR") | R67: =IFERROR(IF(ISBLANK($J$67),"UNKNOWN",IF(NOT(ISNUMBER(Q67)),Q67,$J$67/Q67)),"ERROR") | S67: =IFERROR(IF(NOT(ISNUMBER(R67)),R67,IF(ISBLANK($M$67),"UNKNOWN",R67*(1+$M$67))),"ERROR") | T67: =IFERROR(IF(ISBLANK($N$67),"UNKNOWN",IF($N$67=FALSE,R67,S67)),"ERROR") | U67: =IFERROR(IF(NOT(ISNUMBER(T67)),T67,IF(ISBLANK($O$67),"UNKNOWN",IF(OR($O$67<0,$O$67>=1),"ERROR",IF($O$67=0,T67,T67/(1-$O$67))))),"ERROR") | V67: =IFERROR(IF(NOT(ISNUMBER(R67)),R67,IF($L$67=0,R67-$J$67-$K$67*R67,IF(NOT(ISNUMBER(S67)),S67,R67-$J$67-$K$67*R67-$L$67*S67))),"ERROR") | W67: =IFERROR(IF(NOT(ISNUMBER(V67)),V67,IF(R67=0,"ERROR",V67/R67)),"ERROR")
B68: Required Net Sales ex VAT | C68: =R67 | D68: 16666.667 | E68: =IF(ISNUMBER(D68),IF(ISNUMBER(R67),ABS(R67-D68),"N/A"),"N/A") | F68: =IF(ISNUMBER(D68),IF(AND(ISNUMBER(R67),ABS(R67-D68)<=0.01),"PASS","FAIL"),IF(AND(NOT(ISNUMBER(R67)),R67=D68),"PASS","FAIL"))
B69: Required Gross Payment incl VAT | C69: =S67 | D69: UNKNOWN | E69: =IF(ISNUMBER(D69),IF(ISNUMBER(S67),ABS(S67-D69),"N/A"),"N/A") | F69: =IF(ISNUMBER(D69),IF(AND(ISNUMBER(S67),ABS(S67-D69)<=0.01),"PASS","FAIL"),IF(AND(NOT(ISNUMBER(S67)),S67=D69),"PASS","FAIL"))
B70: Required Selling Price | C70: =T67 | D70: 16666.667 | E70: =IF(ISNUMBER(D70),IF(ISNUMBER(T67),ABS(T67-D70),"N/A"),"N/A") | F70: =IF(ISNUMBER(D70),IF(AND(ISNUMBER(T67),ABS(T67-D70)<=0.01),"PASS","FAIL"),IF(AND(NOT(ISNUMBER(T67)),T67=D70),"PASS","FAIL"))
B71: Required List Price | C71: =U67 | D71: UNKNOWN | E71: =IF(ISNUMBER(D71),IF(ISNUMBER(U67),ABS(U67-D71),"N/A"),"N/A") | F71: =IF(ISNUMBER(D71),IF(AND(ISNUMBER(U67),ABS(U67-D71)<=0.01),"PASS","FAIL"),IF(AND(NOT(ISNUMBER(U67)),U67=D71),"PASS","FAIL"))
B72: Expected Contribution Margin | C72: =V67 | D72: 5000 | E72: =IF(ISNUMBER(D72),IF(ISNUMBER(V67),ABS(V67-D72),"N/A"),"N/A") | F72: =IF(ISNUMBER(D72),IF(AND(ISNUMBER(V67),ABS(V67-D72)<=0.01),"PASS","FAIL"),IF(AND(NOT(ISNUMBER(V67)),V67=D72),"PASS","FAIL"))
B73: Expected CM Rate | C73: =W67 | D73: 0.3 | E73: =IF(ISNUMBER(D73),IF(ISNUMBER(W67),ABS(W67-D73),"N/A"),"N/A") | F73: =IF(ISNUMBER(D73),IF(AND(ISNUMBER(W67),ABS(W67-D73)<=0.0001),"PASS","FAIL"),IF(AND(NOT(ISNUMBER(W67)),W67=D73),"PASS","FAIL"))
B75: 8. VAT-inclusive display, VAT UNKNOWN
B76: Metric | C76: Excel Result | D76: Python Reference | E76: Difference | F76: PASS / FAIL
B77: Denominator | C77: =Q77 | D77: 0.6 | E77: =IF(ISNUMBER(D77),IF(ISNUMBER(Q77),ABS(Q77-D77),"N/A"),"N/A") | F77: =IF(ISNUMBER(D77),IF(AND(ISNUMBER(Q77),ABS(Q77-D77)<=0.01),"PASS","FAIL"),IF(AND(NOT(ISNUMBER(Q77)),Q77=D77),"PASS","FAIL")) | I77: 0.3 | J77: 10000 | K77: 0.1 | L77: 0 | N77: TRUE | P77: none | Q77: =IFERROR(IF($P$77="invalid","ERROR",IF($P$77="unresolved","UNKNOWN",IF(OR(AND(NOT(ISBLANK($I$77)),OR($I$77<0,$I$77>=1)),AND(NOT(ISBLANK($K$77)),$K$77<0),AND(NOT(ISBLANK($L$77)),$L$77<0),AND(NOT(ISBLANK($J$77)),$J$77<0)),"ERROR",IF(OR(ISBLANK($I$77),ISBLANK($K$77),ISBLANK($L$77)),"UNKNOWN",IF($L$77=0,IF(1-$I$77-$K$77<=0,"ERROR",1-$I$77-$K$77),IF(ISBLANK($M$77),"UNKNOWN",IF(1-$I$77-$K$77-$L$77*(1+$M$77)<=0,"ERROR",1-$I$77-$K$77-$L$77*(1+$M$77)))))))),"ERROR") | R77: =IFERROR(IF(ISBLANK($J$77),"UNKNOWN",IF(NOT(ISNUMBER(Q77)),Q77,$J$77/Q77)),"ERROR") | S77: =IFERROR(IF(NOT(ISNUMBER(R77)),R77,IF(ISBLANK($M$77),"UNKNOWN",R77*(1+$M$77))),"ERROR") | T77: =IFERROR(IF(ISBLANK($N$77),"UNKNOWN",IF($N$77=FALSE,R77,S77)),"ERROR") | U77: =IFERROR(IF(NOT(ISNUMBER(T77)),T77,IF(ISBLANK($O$77),"UNKNOWN",IF(OR($O$77<0,$O$77>=1),"ERROR",IF($O$77=0,T77,T77/(1-$O$77))))),"ERROR") | V77: =IFERROR(IF(NOT(ISNUMBER(R77)),R77,IF($L$77=0,R77-$J$77-$K$77*R77,IF(NOT(ISNUMBER(S77)),S77,R77-$J$77-$K$77*R77-$L$77*S77))),"ERROR") | W77: =IFERROR(IF(NOT(ISNUMBER(V77)),V77,IF(R77=0,"ERROR",V77/R77)),"ERROR")
B78: Required Net Sales ex VAT | C78: =R77 | D78: 16666.667 | E78: =IF(ISNUMBER(D78),IF(ISNUMBER(R77),ABS(R77-D78),"N/A"),"N/A") | F78: =IF(ISNUMBER(D78),IF(AND(ISNUMBER(R77),ABS(R77-D78)<=0.01),"PASS","FAIL"),IF(AND(NOT(ISNUMBER(R77)),R77=D78),"PASS","FAIL"))
B79: Required Gross Payment incl VAT | C79: =S77 | D79: UNKNOWN | E79: =IF(ISNUMBER(D79),IF(ISNUMBER(S77),ABS(S77-D79),"N/A"),"N/A") | F79: =IF(ISNUMBER(D79),IF(AND(ISNUMBER(S77),ABS(S77-D79)<=0.01),"PASS","FAIL"),IF(AND(NOT(ISNUMBER(S77)),S77=D79),"PASS","FAIL"))
B80: Required Selling Price | C80: =T77 | D80: UNKNOWN | E80: =IF(ISNUMBER(D80),IF(ISNUMBER(T77),ABS(T77-D80),"N/A"),"N/A") | F80: =IF(ISNUMBER(D80),IF(AND(ISNUMBER(T77),ABS(T77-D80)<=0.01),"PASS","FAIL"),IF(AND(NOT(ISNUMBER(T77)),T77=D80),"PASS","FAIL"))
B81: Required List Price | C81: =U77 | D81: UNKNOWN | E81: =IF(ISNUMBER(D81),IF(ISNUMBER(U77),ABS(U77-D81),"N/A"),"N/A") | F81: =IF(ISNUMBER(D81),IF(AND(ISNUMBER(U77),ABS(U77-D81)<=0.01),"PASS","FAIL"),IF(AND(NOT(ISNUMBER(U77)),U77=D81),"PASS","FAIL"))
B82: Expected Contribution Margin | C82: =V77 | D82: 5000 | E82: =IF(ISNUMBER(D82),IF(ISNUMBER(V77),ABS(V77-D82),"N/A"),"N/A") | F82: =IF(ISNUMBER(D82),IF(AND(ISNUMBER(V77),ABS(V77-D82)<=0.01),"PASS","FAIL"),IF(AND(NOT(ISNUMBER(V77)),V77=D82),"PASS","FAIL"))
B83: Expected CM Rate | C83: =W77 | D83: 0.3 | E83: =IF(ISNUMBER(D83),IF(ISNUMBER(W77),ABS(W77-D83),"N/A"),"N/A") | F83: =IF(ISNUMBER(D83),IF(AND(ISNUMBER(W77),ABS(W77-D83)<=0.0001),"PASS","FAIL"),IF(AND(NOT(ISNUMBER(W77)),W77=D83),"PASS","FAIL"))
B85: 9. Discount rate = 0
B86: Metric | C86: Excel Result | D86: Python Reference | E86: Difference | F86: PASS / FAIL
B87: Denominator | C87: =Q87 | D87: 0.6 | E87: =IF(ISNUMBER(D87),IF(ISNUMBER(Q87),ABS(Q87-D87),"N/A"),"N/A") | F87: =IF(ISNUMBER(D87),IF(AND(ISNUMBER(Q87),ABS(Q87-D87)<=0.01),"PASS","FAIL"),IF(AND(NOT(ISNUMBER(Q87)),Q87=D87),"PASS","FAIL")) | I87: 0.4 | J87: 10000 | K87: 0 | L87: 0 | M87: 0.1 | N87: FALSE | O87: 0 | P87: none | Q87: =IFERROR(IF($P$87="invalid","ERROR",IF($P$87="unresolved","UNKNOWN",IF(OR(AND(NOT(ISBLANK($I$87)),OR($I$87<0,$I$87>=1)),AND(NOT(ISBLANK($K$87)),$K$87<0),AND(NOT(ISBLANK($L$87)),$L$87<0),AND(NOT(ISBLANK($J$87)),$J$87<0)),"ERROR",IF(OR(ISBLANK($I$87),ISBLANK($K$87),ISBLANK($L$87)),"UNKNOWN",IF($L$87=0,IF(1-$I$87-$K$87<=0,"ERROR",1-$I$87-$K$87),IF(ISBLANK($M$87),"UNKNOWN",IF(1-$I$87-$K$87-$L$87*(1+$M$87)<=0,"ERROR",1-$I$87-$K$87-$L$87*(1+$M$87)))))))),"ERROR") | R87: =IFERROR(IF(ISBLANK($J$87),"UNKNOWN",IF(NOT(ISNUMBER(Q87)),Q87,$J$87/Q87)),"ERROR") | S87: =IFERROR(IF(NOT(ISNUMBER(R87)),R87,IF(ISBLANK($M$87),"UNKNOWN",R87*(1+$M$87))),"ERROR") | T87: =IFERROR(IF(ISBLANK($N$87),"UNKNOWN",IF($N$87=FALSE,R87,S87)),"ERROR") | U87: =IFERROR(IF(NOT(ISNUMBER(T87)),T87,IF(ISBLANK($O$87),"UNKNOWN",IF(OR($O$87<0,$O$87>=1),"ERROR",IF($O$87=0,T87,T87/(1-$O$87))))),"ERROR") | V87: =IFERROR(IF(NOT(ISNUMBER(R87)),R87,IF($L$87=0,R87-$J$87-$K$87*R87,IF(NOT(ISNUMBER(S87)),S87,R87-$J$87-$K$87*R87-$L$87*S87))),"ERROR") | W87: =IFERROR(IF(NOT(ISNUMBER(V87)),V87,IF(R87=0,"ERROR",V87/R87)),"ERROR")
B88: Required Net Sales ex VAT | C88: =R87 | D88: 16666.667 | E88: =IF(ISNUMBER(D88),IF(ISNUMBER(R87),ABS(R87-D88),"N/A"),"N/A") | F88: =IF(ISNUMBER(D88),IF(AND(ISNUMBER(R87),ABS(R87-D88)<=0.01),"PASS","FAIL"),IF(AND(NOT(ISNUMBER(R87)),R87=D88),"PASS","FAIL"))
B89: Required Gross Payment incl VAT | C89: =S87 | D89: 18333.333 | E89: =IF(ISNUMBER(D89),IF(ISNUMBER(S87),ABS(S87-D89),"N/A"),"N/A") | F89: =IF(ISNUMBER(D89),IF(AND(ISNUMBER(S87),ABS(S87-D89)<=0.01),"PASS","FAIL"),IF(AND(NOT(ISNUMBER(S87)),S87=D89),"PASS","FAIL"))
B90: Required Selling Price | C90: =T87 | D90: 16666.667 | E90: =IF(ISNUMBER(D90),IF(ISNUMBER(T87),ABS(T87-D90),"N/A"),"N/A") | F90: =IF(ISNUMBER(D90),IF(AND(ISNUMBER(T87),ABS(T87-D90)<=0.01),"PASS","FAIL"),IF(AND(NOT(ISNUMBER(T87)),T87=D90),"PASS","FAIL"))
B91: Required List Price | C91: =U87 | D91: 16666.667 | E91: =IF(ISNUMBER(D91),IF(ISNUMBER(U87),ABS(U87-D91),"N/A"),"N/A") | F91: =IF(ISNUMBER(D91),IF(AND(ISNUMBER(U87),ABS(U87-D91)<=0.01),"PASS","FAIL"),IF(AND(NOT(ISNUMBER(U87)),U87=D91),"PASS","FAIL"))
B92: Expected Contribution Margin | C92: =V87 | D92: 6666.6667 | E92: =IF(ISNUMBER(D92),IF(ISNUMBER(V87),ABS(V87-D92),"N/A"),"N/A") | F92: =IF(ISNUMBER(D92),IF(AND(ISNUMBER(V87),ABS(V87-D92)<=0.01),"PASS","FAIL"),IF(AND(NOT(ISNUMBER(V87)),V87=D92),"PASS","FAIL"))
B93: Expected CM Rate | C93: =W87 | D93: 0.4 | E93: =IF(ISNUMBER(D93),IF(ISNUMBER(W87),ABS(W87-D93),"N/A"),"N/A") | F93: =IF(ISNUMBER(D93),IF(AND(ISNUMBER(W87),ABS(W87-D93)<=0.0001),"PASS","FAIL"),IF(AND(NOT(ISNUMBER(W87)),W87=D93),"PASS","FAIL"))
B95: 10. Discount rate normal value (TC6, on top of TC4)
B96: Metric | C96: Excel Result | D96: Python Reference | E96: Difference | F96: PASS / FAIL
B97: Denominator | C97: =Q97 | D97: 0.567 | E97: =IF(ISNUMBER(D97),IF(ISNUMBER(Q97),ABS(Q97-D97),"N/A"),"N/A") | F97: =IF(ISNUMBER(D97),IF(AND(ISNUMBER(Q97),ABS(Q97-D97)<=0.01),"PASS","FAIL"),IF(AND(NOT(ISNUMBER(Q97)),Q97=D97),"PASS","FAIL")) | I97: 0.3 | J97: 10000 | K97: 0.1 | L97: 0.03 | M97: 0.1 | N97: TRUE | O97: 0.1 | P97: none | Q97: =IFERROR(IF($P$97="invalid","ERROR",IF($P$97="unresolved","UNKNOWN",IF(OR(AND(NOT(ISBLANK($I$97)),OR($I$97<0,$I$97>=1)),AND(NOT(ISBLANK($K$97)),$K$97<0),AND(NOT(ISBLANK($L$97)),$L$97<0),AND(NOT(ISBLANK($J$97)),$J$97<0)),"ERROR",IF(OR(ISBLANK($I$97),ISBLANK($K$97),ISBLANK($L$97)),"UNKNOWN",IF($L$97=0,IF(1-$I$97-$K$97<=0,"ERROR",1-$I$97-$K$97),IF(ISBLANK($M$97),"UNKNOWN",IF(1-$I$97-$K$97-$L$97*(1+$M$97)<=0,"ERROR",1-$I$97-$K$97-$L$97*(1+$M$97)))))))),"ERROR") | R97: =IFERROR(IF(ISBLANK($J$97),"UNKNOWN",IF(NOT(ISNUMBER(Q97)),Q97,$J$97/Q97)),"ERROR") | S97: =IFERROR(IF(NOT(ISNUMBER(R97)),R97,IF(ISBLANK($M$97),"UNKNOWN",R97*(1+$M$97))),"ERROR") | T97: =IFERROR(IF(ISBLANK($N$97),"UNKNOWN",IF($N$97=FALSE,R97,S97)),"ERROR") | U97: =IFERROR(IF(NOT(ISNUMBER(T97)),T97,IF(ISBLANK($O$97),"UNKNOWN",IF(OR($O$97<0,$O$97>=1),"ERROR",IF($O$97=0,T97,T97/(1-$O$97))))),"ERROR") | V97: =IFERROR(IF(NOT(ISNUMBER(R97)),R97,IF($L$97=0,R97-$J$97-$K$97*R97,IF(NOT(ISNUMBER(S97)),S97,R97-$J$97-$K$97*R97-$L$97*S97))),"ERROR") | W97: =IFERROR(IF(NOT(ISNUMBER(V97)),V97,IF(R97=0,"ERROR",V97/R97)),"ERROR")
B98: Required Net Sales ex VAT | C98: =R97 | D98: 17636.684 | E98: =IF(ISNUMBER(D98),IF(ISNUMBER(R97),ABS(R97-D98),"N/A"),"N/A") | F98: =IF(ISNUMBER(D98),IF(AND(ISNUMBER(R97),ABS(R97-D98)<=0.01),"PASS","FAIL"),IF(AND(NOT(ISNUMBER(R97)),R97=D98),"PASS","FAIL"))
B99: Required Gross Payment incl VAT | C99: =S97 | D99: 19400.353 | E99: =IF(ISNUMBER(D99),IF(ISNUMBER(S97),ABS(S97-D99),"N/A"),"N/A") | F99: =IF(ISNUMBER(D99),IF(AND(ISNUMBER(S97),ABS(S97-D99)<=0.01),"PASS","FAIL"),IF(AND(NOT(ISNUMBER(S97)),S97=D99),"PASS","FAIL"))
B100: Required Selling Price | C100: =T97 | D100: 19400.353 | E100: =IF(ISNUMBER(D100),IF(ISNUMBER(T97),ABS(T97-D100),"N/A"),"N/A") | F100: =IF(ISNUMBER(D100),IF(AND(ISNUMBER(T97),ABS(T97-D100)<=0.01),"PASS","FAIL"),IF(AND(NOT(ISNUMBER(T97)),T97=D100),"PASS","FAIL"))
B101: Required List Price | C101: =U97 | D101: 21555.947 | E101: =IF(ISNUMBER(D101),IF(ISNUMBER(U97),ABS(U97-D101),"N/A"),"N/A") | F101: =IF(ISNUMBER(D101),IF(AND(ISNUMBER(U97),ABS(U97-D101)<=0.01),"PASS","FAIL"),IF(AND(NOT(ISNUMBER(U97)),U97=D101),"PASS","FAIL"))
B102: Expected Contribution Margin | C102: =V97 | D102: 5291.0053 | E102: =IF(ISNUMBER(D102),IF(ISNUMBER(V97),ABS(V97-D102),"N/A"),"N/A") | F102: =IF(ISNUMBER(D102),IF(AND(ISNUMBER(V97),ABS(V97-D102)<=0.01),"PASS","FAIL"),IF(AND(NOT(ISNUMBER(V97)),V97=D102),"PASS","FAIL"))
B103: Expected CM Rate | C103: =W97 | D103: 0.3 | E103: =IF(ISNUMBER(D103),IF(ISNUMBER(W97),ABS(W97-D103),"N/A"),"N/A") | F103: =IF(ISNUMBER(D103),IF(AND(ISNUMBER(W97),ABS(W97-D103)<=0.0001),"PASS","FAIL"),IF(AND(NOT(ISNUMBER(W97)),W97=D103),"PASS","FAIL"))
B105: 11. Denominator <= 0 (TC7)
B106: Metric | C106: Excel Result | D106: Python Reference | E106: Difference | F106: PASS / FAIL
B107: Denominator | C107: =Q107 | D107: ERROR | E107: =IF(ISNUMBER(D107),IF(ISNUMBER(Q107),ABS(Q107-D107),"N/A"),"N/A") | F107: =IF(ISNUMBER(D107),IF(AND(ISNUMBER(Q107),ABS(Q107-D107)<=0.01),"PASS","FAIL"),IF(AND(NOT(ISNUMBER(Q107)),Q107=D107),"PASS","FAIL")) | I107: 0.5 | J107: 10000 | K107: 0.3 | L107: 0.3 | M107: 0.1 | N107: FALSE | P107: none | Q107: =IFERROR(IF($P$107="invalid","ERROR",IF($P$107="unresolved","UNKNOWN",IF(OR(AND(NOT(ISBLANK($I$107)),OR($I$107<0,$I$107>=1)),AND(NOT(ISBLANK($K$107)),$K$107<0),AND(NOT(ISBLANK($L$107)),$L$107<0),AND(NOT(ISBLANK($J$107)),$J$107<0)),"ERROR",IF(OR(ISBLANK($I$107),ISBLANK($K$107),ISBLANK($L$107)),"UNKNOWN",IF($L$107=0,IF(1-$I$107-$K$107<=0,"ERROR",1-$I$107-$K$107),IF(ISBLANK($M$107),"UNKNOWN",IF(1-$I$107-$K$107-$L$107*(1+$M$107)<=0,"ERROR",1-$I$107-$K$107-$L$107*(1+$M$107)))))))),"ERROR") | R107: =IFERROR(IF(ISBLANK($J$107),"UNKNOWN",IF(NOT(ISNUMBER(Q107)),Q107,$J$107/Q107)),"ERROR") | S107: =IFERROR(IF(NOT(ISNUMBER(R107)),R107,IF(ISBLANK($M$107),"UNKNOWN",R107*(1+$M$107))),"ERROR") | T107: =IFERROR(IF(ISBLANK($N$107),"UNKNOWN",IF($N$107=FALSE,R107,S107)),"ERROR") | U107: =IFERROR(IF(NOT(ISNUMBER(T107)),T107,IF(ISBLANK($O$107),"UNKNOWN",IF(OR($O$107<0,$O$107>=1),"ERROR",IF($O$107=0,T107,T107/(1-$O$107))))),"ERROR") | V107: =IFERROR(IF(NOT(ISNUMBER(R107)),R107,IF($L$107=0,R107-$J$107-$K$107*R107,IF(NOT(ISNUMBER(S107)),S107,R107-$J$107-$K$107*R107-$L$107*S107))),"ERROR") | W107: =IFERROR(IF(NOT(ISNUMBER(V107)),V107,IF(R107=0,"ERROR",V107/R107)),"ERROR")
B108: Required Net Sales ex VAT | C108: =R107 | D108: ERROR | E108: =IF(ISNUMBER(D108),IF(ISNUMBER(R107),ABS(R107-D108),"N/A"),"N/A") | F108: =IF(ISNUMBER(D108),IF(AND(ISNUMBER(R107),ABS(R107-D108)<=0.01),"PASS","FAIL"),IF(AND(NOT(ISNUMBER(R107)),R107=D108),"PASS","FAIL"))
B109: Required Gross Payment incl VAT | C109: =S107 | D109: ERROR | E109: =IF(ISNUMBER(D109),IF(ISNUMBER(S107),ABS(S107-D109),"N/A"),"N/A") | F109: =IF(ISNUMBER(D109),IF(AND(ISNUMBER(S107),ABS(S107-D109)<=0.01),"PASS","FAIL"),IF(AND(NOT(ISNUMBER(S107)),S107=D109),"PASS","FAIL"))
B110: Required Selling Price | C110: =T107 | D110: ERROR | E110: =IF(ISNUMBER(D110),IF(ISNUMBER(T107),ABS(T107-D110),"N/A"),"N/A") | F110: =IF(ISNUMBER(D110),IF(AND(ISNUMBER(T107),ABS(T107-D110)<=0.01),"PASS","FAIL"),IF(AND(NOT(ISNUMBER(T107)),T107=D110),"PASS","FAIL"))
B111: Required List Price | C111: =U107 | D111: ERROR | E111: =IF(ISNUMBER(D111),IF(ISNUMBER(U107),ABS(U107-D111),"N/A"),"N/A") | F111: =IF(ISNUMBER(D111),IF(AND(ISNUMBER(U107),ABS(U107-D111)<=0.01),"PASS","FAIL"),IF(AND(NOT(ISNUMBER(U107)),U107=D111),"PASS","FAIL"))
B112: Expected Contribution Margin | C112: =V107 | D112: ERROR | E112: =IF(ISNUMBER(D112),IF(ISNUMBER(V107),ABS(V107-D112),"N/A"),"N/A") | F112: =IF(ISNUMBER(D112),IF(AND(ISNUMBER(V107),ABS(V107-D112)<=0.01),"PASS","FAIL"),IF(AND(NOT(ISNUMBER(V107)),V107=D112),"PASS","FAIL"))
...

Sheet 06_MODE_C_SIMULATOR
B2: 06. MODE C Simulator — Allowable Direct Cost (Interactive)
B4: INPUT (노란 셀만 입력, 단일 컴포넌트 기준)
B5: Target Market Price | C5: 110000 | D5: product.price_components[].target_market_price — effective(할인 반영 후) 거래가격
B6: Price Includes VAT | C6: TRUE | D6: TRUE=시장가에 VAT 포함 / FALSE=별도 / 빈칸=모름
B7: VAT Rate (v) | C7: 0.1 | D7: a=0이면 ADC 계산에 불필요. N/G는 각자의 조건에서만 필요 (SPEC.md §6)
B8: Target Contribution Margin Rate (t) | C8: 0.3 | D8: 0 이상 1 미만이어야 함 (>=1 또는 <0은 ERROR)
B9: Fixed-Amount Variable Cost (F) | C9: 1000 | D9: variable_selling_delivery 중 금액형 항목 합계 (product_service_direct_cost 제외)
B10: Net-Sales Fee Rate (b) | C10: 0.1 | D10: rate_of_net_sales 합계 — N에 곱함. 없으면 0
B11: Gross-Payment Fee Rate (a) | C11: 0.03 | D11: rate_of_gross_payment 합계 — G에 곱함. 없으면 0
B12: Actual Direct Cost | C12: 50000 | D12: 실제 product_service_direct_cost 합계 — ADC 계산에 절대 사용되지 않음(dependency isolation)
B13: Variable Cost Allocation Status (Excel simulation control — not a schema field) | C13: none | D13: Excel-only. F/b/a(변동비)의 공유비용 배부 상태 시뮬레이션. none=정상 계산 / unresolved=배부 미구현(ADC/gap/CM/CMR까지 전부 UNKNOWN) / invalid=shared+direct 모순(전부 ERROR).
B14: Direct Cost Allocation Status (Excel simulation control — not a schema field) | C14: none | D14: Excel-only. actual_direct_cost만의 공유비용 배부 상태 시뮬레이션 — F/b/a와 완전히 분리된 컨트롤. none=정상 / unresolved=배부 미구현(actual_direct_cost·gap만 UNKNOWN) / invalid=모순(둘 다 ERROR). ADC·expected_contribution_margin(_rate)은 이 값과 무관하게 절대 변하지 않아야 함(가장 중요한 dependency-isolation 테스트, SPEC.md §9).
B16: RESULT (계산값 — 직접 입력 금지)
B17: Market Net Sales ex VAT (N) | C17: =IFERROR(IF(ISBLANK($C$5),"UNKNOWN",IF(ISBLANK($C$6),"UNKNOWN",IF($C$6=FALSE,$C$5,IF(ISBLANK($C$7),"UNKNOWN",$C$5/(1+$C$7))))),"ERROR") | D17: N — price_includes_vat=FALSE→시장가 그대로 / TRUE→÷(1+v)
B18: Market Gross Payment incl VAT (G) | C18: =IFERROR(IF(ISBLANK($C$5),"UNKNOWN",IF(ISBLANK($C$6),"UNKNOWN",IF($C$6=TRUE,$C$5,IF(ISBLANK($C$7),"UNKNOWN",$C$5*(1+$C$7))))),"ERROR") | D18: G — price_includes_vat=TRUE→시장가 그대로 / FALSE→×(1+v)
B19: Allowable Direct Cost (ADC) | C19: =IFERROR(IF(OR(C17="ERROR",J24="ERROR",K24="ERROR",L24="ERROR",M24="ERROR"),"ERROR",IF(OR(NOT(ISNUMBER(C17)),NOT(ISNUMBER(J24)),NOT(ISNUMBER(K24)),NOT(ISNUMBER(L24)),NOT(ISNUMBER(M24))),"UNKNOWN",IF(M24>0,IF(C18="ERROR","ERROR",IF(NOT(ISNUMBER(C18)),"UNKNOWN",C17*(1-J24-L24)-M24*C18-K24)),C17*(1-J24-L24)-K24))),"ERROR") | D19: ADC = N×(1−t−b) − a×G − F (a=0이면 G 참조 안 함)
B20: Actual Direct Cost | C20: =IFERROR(IF($C$14="invalid","ERROR",IF($C$14="unresolved","UNKNOWN",IF(ISBLANK($C$12),"UNKNOWN",$C$12))),"ERROR") | D20: 실제 직접원가 — ADC와 완전히 독립 (Direct Cost Allocation Status만 영향)
B21: Direct Cost Gap (ADC − Actual) | C21: =IFERROR(IF(OR(C19="ERROR",C20="ERROR"),"ERROR",IF(OR(NOT(ISNUMBER(C19)),NOT(ISNUMBER(C20))),"UNKNOWN",C19-C20)),"ERROR") | D21: = ADC − Actual Direct Cost. 양수=여유, 음수=초과
B22: Expected Contribution Margin | C22: =IFERROR(IF(C19="ERROR","ERROR",IF(NOT(ISNUMBER(C19)),"UNKNOWN",IF(M24>0,C17-C19-K24-L24*C17-M24*C18,C17-C19-K24-L24*C17))),"ERROR") | D22: = N − ADC − F − b×N − a×G (역산식과 독립적인 비용구조 재계산)
B23: Expected CM Rate | C23: =IFERROR(IF(C22="ERROR","ERROR",IF(NOT(ISNUMBER(C22)),"UNKNOWN",IF(C17=0,"ERROR",C22/C17))),"ERROR") | D23: = CM / N. N=0이면 ERROR(미입력이 아니라 계산불가)
J24: =IFERROR(IF(ISBLANK($C$8),"UNKNOWN",IF(OR($C$8<0,$C$8>=1),"ERROR",$C$8)),"ERROR") | K24: =IFERROR(IF($C$13="invalid","ERROR",IF($C$13="unresolved","UNKNOWN",IF(ISBLANK($C$9),"UNKNOWN",$C$9))),"ERROR") | L24: =IFERROR(IF($C$13="invalid","ERROR",IF($C$13="unresolved","UNKNOWN",IF(ISBLANK($C$10),"UNKNOWN",$C$10))),"ERROR") | M24: =IFERROR(IF($C$13="invalid","ERROR",IF($C$13="unresolved","UNKNOWN",IF(ISBLANK($C$11),"UNKNOWN",$C$11))),"ERROR")
B26: Negative ADC? | C26: =IF(ISNUMBER(C19),IF(C19<0,"YES — NEGATIVE_ALLOWABLE_COST (경고, ERROR 아님)","NO"),"N/A")
B27: Self-Check: |CMR − t| ≤ 0.0001? | C27: =IF(NOT(ISNUMBER(C23)),"N/A",IF(ABS(C23-$C$8)<=0.0001,"PASS","FAIL")) | D27: expected_contribution_margin은 t×N이 아니라 비용구조(N-ADC-F-bN-aG)로 독립 재계산됩니다. 그 결과로 얻은 CMR(=CM/N)이 목표 t와 tolerance 내에서 일치하는지 진단하는 별도 셀. MODE C의 공식 출력 metric은 아님 — 산술 오류를 잡기 위한 진단용.
B28: STATUS
B29: Overall Status | C29: =IF((IF(C17="ERROR",1,0)+IF(C18="ERROR",1,0)+IF(C19="ERROR",1,0)+IF(C20="ERROR",1,0)+IF(C21="ERROR",1,0)+IF(C22="ERROR",1,0)+IF(C23="ERROR",1,0))>0,"ERROR — 목표 불가능 또는 입력값 모순",IF((IF(C17="UNKNOWN",1,0)+IF(C18="UNKNOWN",1,0)+IF(C19="UNKNOWN",1,0)+IF(C20="UNKNOWN",1,0)+IF(C21="UNKNOWN",1,0)+IF(C22="UNKNOWN",1,0)+IF(C23="UNKNOWN",1,0))>0,"INCOMPLETE — 일부 지표 UNKNOWN","OK — 전체 계산 완료"))
B30: blank = UNKNOWN / 0 = explicit zero
B32: DASHBOARD CARD
B33: Market Net Sales (N) | E33: Allowable Direct Cost | H33: Actual Direct Cost
B34: =C17 | E34: =C19 | H34: =C20
B36: Direct Cost Gap | E36: Expected CM | H36: Expected CM Rate
B37: =C21 | E37: =C22 | H37: =C23

Sheet 07_MODE_C_PARITY_TEST
B2: 07. Python Engine vs Excel Formula — MODE C Parity Test
B3: 각 케이스는 docs/features/mode_c_allowable_cost/CASE.md의 TC1-20에 대응하며, Excel에 동일 입력값을 리터럴로 심어 06_MODE_C_SIMULATOR와 같은 수식(build_mode_c_formulas)으로 독립 재계산하고, Python 참조값(core/engine/modes/mode_c.py 실행 결과, 빌드 시점에 고정)과 비교합니다. 허용오차 0.01(금액) / 0.0001(비율). TC14/TC15/TC18은 Variable Cost Allocation Status로, TC20은 Direct Cost Allocation Status로 공유비용 배부 미구현/모순 상태를 시뮬레이션합니다 — TC19/TC20은 특히 Direct Cost Allocation Status를 바꿔도 allowable_direct_cost/expected_contribution_margin(_rate)이 전혀 영향받지 않는지를 실시간으로 검증하는, 가장 중요한 dependency-isolation 케이스입니다. 20개 전부 live Excel evaluation.
B5: TC1. Simple, no fee at all
B6: Metric | C6: Excel Result | D6: Python Reference | E6: Difference | F6: PASS / FAIL
B7: Market Net Sales ex VAT (N) | C7: =S7 | D7: 100000 | E7: =IF(ISNUMBER(D7),IF(ISNUMBER(S7),ABS(S7-D7),"N/A"),"N/A") | F7: =IFERROR(IF(ISNUMBER(D7),IF(ISNUMBER(S7),IF(ABS(S7-D7)<=0.01,"PASS","FAIL"),"FAIL"),IF(NOT(ISNUMBER(S7)),IF(S7=D7,"PASS","FAIL"),"FAIL")),"FAIL") | I7: 100000 | J7: FALSE | L7: 0.3 | M7: 0 | N7: 0 | O7: 0 | P7: 0 | Q7: none | R7: none | S7: =IFERROR(IF(ISBLANK($I$7),"UNKNOWN",IF(ISBLANK($J$7),"UNKNOWN",IF($J$7=FALSE,$I$7,IF(ISBLANK($K$7),"UNKNOWN",$I$7/(1+$K$7))))),"ERROR") | T7: =IFERROR(IF(ISBLANK($I$7),"UNKNOWN",IF(ISBLANK($J$7),"UNKNOWN",IF($J$7=TRUE,$I$7,IF(ISBLANK($K$7),"UNKNOWN",$I$7*(1+$K$7))))),"ERROR") | U7: =IFERROR(IF(OR(S7="ERROR",Z7="ERROR",AA7="ERROR",AB7="ERROR",AC7="ERROR"),"ERROR",IF(OR(NOT(ISNUMBER(S7)),NOT(ISNUMBER(Z7)),NOT(ISNUMBER(AA7)),NOT(ISNUMBER(AB7)),NOT(ISNUMBER(AC7))),"UNKNOWN",IF(AC7>0,IF(T7="ERROR","ERROR",IF(NOT(ISNUMBER(T7)),"UNKNOWN",S7*(1-Z7-AB7)-AC7*T7-AA7)),S7*(1-Z7-AB7)-AA7))),"ERROR") | V7: =IFERROR(IF($R$7="invalid","ERROR",IF($R$7="unresolved","UNKNOWN",IF(ISBLANK($P$7),"UNKNOWN",$P$7))),"ERROR") | W7: =IFERROR(IF(OR(U7="ERROR",V7="ERROR"),"ERROR",IF(OR(NOT(ISNUMBER(U7)),NOT(ISNUMBER(V7))),"UNKNOWN",U7-V7)),"ERROR") | X7: =IFERROR(IF(U7="ERROR","ERROR",IF(NOT(ISNUMBER(U7)),"UNKNOWN",IF(AC7>0,S7-U7-AA7-AB7*S7-AC7*T7,S7-U7-AA7-AB7*S7))),"ERROR") | Y7: =IFERROR(IF(X7="ERROR","ERROR",IF(NOT(ISNUMBER(X7)),"UNKNOWN",IF(S7=0,"ERROR",X7/S7))),"ERROR") | Z7: =IFERROR(IF(ISBLANK($L$7),"UNKNOWN",IF(OR($L$7<0,$L$7>=1),"ERROR",$L$7)),"ERROR") | AA7: =IFERROR(IF($Q$7="invalid","ERROR",IF($Q$7="unresolved","UNKNOWN",IF(ISBLANK($M$7),"UNKNOWN",$M$7))),"ERROR") | AB7: =IFERROR(IF($Q$7="invalid","ERROR",IF($Q$7="unresolved","UNKNOWN",IF(ISBLANK($N$7),"UNKNOWN",$N$7))),"ERROR") | AC7: =IFERROR(IF($Q$7="invalid","ERROR",IF($Q$7="unresolved","UNKNOWN",IF(ISBLANK($O$7),"UNKNOWN",$O$7))),"ERROR")
B8: Market Gross Payment incl VAT (G) | C8: =T7 | D8: UNKNOWN | E8: =IF(ISNUMBER(D8),IF(ISNUMBER(T7),ABS(T7-D8),"N/A"),"N/A") | F8: =IFERROR(IF(ISNUMBER(D8),IF(ISNUMBER(T7),IF(ABS(T7-D8)<=0.01,"PASS","FAIL"),"FAIL"),IF(NOT(ISNUMBER(T7)),IF(T7=D8,"PASS","FAIL"),"FAIL")),"FAIL")
B9: Allowable Direct Cost (ADC) | C9: =U7 | D9: 70000 | E9: =IF(ISNUMBER(D9),IF(ISNUMBER(U7),ABS(U7-D9),"N/A"),"N/A") | F9: =IFERROR(IF(ISNUMBER(D9),IF(ISNUMBER(U7),IF(ABS(U7-D9)<=0.01,"PASS","FAIL"),"FAIL"),IF(NOT(ISNUMBER(U7)),IF(U7=D9,"PASS","FAIL"),"FAIL")),"FAIL")
B10: Actual Direct Cost | C10: =V7 | D10: 0 | E10: =IF(ISNUMBER(D10),IF(ISNUMBER(V7),ABS(V7-D10),"N/A"),"N/A") | F10: =IFERROR(IF(ISNUMBER(D10),IF(ISNUMBER(V7),IF(ABS(V7-D10)<=0.01,"PASS","FAIL"),"FAIL"),IF(NOT(ISNUMBER(V7)),IF(V7=D10,"PASS","FAIL"),"FAIL")),"FAIL")
B11: Direct Cost Gap (ADC − Actual) | C11: =W7 | D11: 70000 | E11: =IF(ISNUMBER(D11),IF(ISNUMBER(W7),ABS(W7-D11),"N/A"),"N/A") | F11: =IFERROR(IF(ISNUMBER(D11),IF(ISNUMBER(W7),IF(ABS(W7-D11)<=0.01,"PASS","FAIL"),"FAIL"),IF(NOT(ISNUMBER(W7)),IF(W7=D11,"PASS","FAIL"),"FAIL")),"FAIL")
B12: Expected Contribution Margin | C12: =X7 | D12: 30000 | E12: =IF(ISNUMBER(D12),IF(ISNUMBER(X7),ABS(X7-D12),"N/A"),"N/A") | F12: =IFERROR(IF(ISNUMBER(D12),IF(ISNUMBER(X7),IF(ABS(X7-D12)<=0.01,"PASS","FAIL"),"FAIL"),IF(NOT(ISNUMBER(X7)),IF(X7=D12,"PASS","FAIL"),"FAIL")),"FAIL")
B13: Expected CM Rate | C13: =Y7 | D13: 0.3 | E13: =IF(ISNUMBER(D13),IF(ISNUMBER(Y7),ABS(Y7-D13),"N/A"),"N/A") | F13: =IFERROR(IF(ISNUMBER(D13),IF(ISNUMBER(Y7),IF(ABS(Y7-D13)<=0.0001,"PASS","FAIL"),"FAIL"),IF(NOT(ISNUMBER(Y7)),IF(Y7=D13,"PASS","FAIL"),"FAIL")),"FAIL")
B15: TC2. Fixed-amount variable cost (F>0)
B16: Metric | C16: Excel Result | D16: Python Reference | E16: Difference | F16: PASS / FAIL
B17: Market Net Sales ex VAT (N) | C17: =S17 | D17: 100000 | E17: =IF(ISNUMBER(D17),IF(ISNUMBER(S17),ABS(S17-D17),"N/A"),"N/A") | F17: =IFERROR(IF(ISNUMBER(D17),IF(ISNUMBER(S17),IF(ABS(S17-D17)<=0.01,"PASS","FAIL"),"FAIL"),IF(NOT(ISNUMBER(S17)),IF(S17=D17,"PASS","FAIL"),"FAIL")),"FAIL") | I17: 100000 | J17: FALSE | L17: 0.3 | M17: 5000 | N17: 0 | O17: 0 | P17: 0 | Q17: none | R17: none | S17: =IFERROR(IF(ISBLANK($I$17),"UNKNOWN",IF(ISBLANK($J$17),"UNKNOWN",IF($J$17=FALSE,$I$17,IF(ISBLANK($K$17),"UNKNOWN",$I$17/(1+$K$17))))),"ERROR") | T17: =IFERROR(IF(ISBLANK($I$17),"UNKNOWN",IF(ISBLANK($J$17),"UNKNOWN",IF($J$17=TRUE,$I$17,IF(ISBLANK($K$17),"UNKNOWN",$I$17*(1+$K$17))))),"ERROR") | U17: =IFERROR(IF(OR(S17="ERROR",Z17="ERROR",AA17="ERROR",AB17="ERROR",AC17="ERROR"),"ERROR",IF(OR(NOT(ISNUMBER(S17)),NOT(ISNUMBER(Z17)),NOT(ISNUMBER(AA17)),NOT(ISNUMBER(AB17)),NOT(ISNUMBER(AC17))),"UNKNOWN",IF(AC17>0,IF(T17="ERROR","ERROR",IF(NOT(ISNUMBER(T17)),"UNKNOWN",S17*(1-Z17-AB17)-AC17*T17-AA17)),S17*(1-Z17-AB17)-AA17))),"ERROR") | V17: =IFERROR(IF($R$17="invalid","ERROR",IF($R$17="unresolved","UNKNOWN",IF(ISBLANK($P$17),"UNKNOWN",$P$17))),"ERROR") | W17: =IFERROR(IF(OR(U17="ERROR",V17="ERROR"),"ERROR",IF(OR(NOT(ISNUMBER(U17)),NOT(ISNUMBER(V17))),"UNKNOWN",U17-V17)),"ERROR") | X17: =IFERROR(IF(U17="ERROR","ERROR",IF(NOT(ISNUMBER(U17)),"UNKNOWN",IF(AC17>0,S17-U17-AA17-AB17*S17-AC17*T17,S17-U17-AA17-AB17*S17))),"ERROR") | Y17: =IFERROR(IF(X17="ERROR","ERROR",IF(NOT(ISNUMBER(X17)),"UNKNOWN",IF(S17=0,"ERROR",X17/S17))),"ERROR") | Z17: =IFERROR(IF(ISBLANK($L$17),"UNKNOWN",IF(OR($L$17<0,$L$17>=1),"ERROR",$L$17)),"ERROR") | AA17: =IFERROR(IF($Q$17="invalid","ERROR",IF($Q$17="unresolved","UNKNOWN",IF(ISBLANK($M$17),"UNKNOWN",$M$17))),"ERROR") | AB17: =IFERROR(IF($Q$17="invalid","ERROR",IF($Q$17="unresolved","UNKNOWN",IF(ISBLANK($N$17),"UNKNOWN",$N$17))),"ERROR") | AC17: =IFERROR(IF($Q$17="invalid","ERROR",IF($Q$17="unresolved","UNKNOWN",IF(ISBLANK($O$17),"UNKNOWN",$O$17))),"ERROR")
B18: Market Gross Payment incl VAT (G) | C18: =T17 | D18: UNKNOWN | E18: =IF(ISNUMBER(D18),IF(ISNUMBER(T17),ABS(T17-D18),"N/A"),"N/A") | F18: =IFERROR(IF(ISNUMBER(D18),IF(ISNUMBER(T17),IF(ABS(T17-D18)<=0.01,"PASS","FAIL"),"FAIL"),IF(NOT(ISNUMBER(T17)),IF(T17=D18,"PASS","FAIL"),"FAIL")),"FAIL")
B19: Allowable Direct Cost (ADC) | C19: =U17 | D19: 65000 | E19: =IF(ISNUMBER(D19),IF(ISNUMBER(U17),ABS(U17-D19),"N/A"),"N/A") | F19: =IFERROR(IF(ISNUMBER(D19),IF(ISNUMBER(U17),IF(ABS(U17-D19)<=0.01,"PASS","FAIL"),"FAIL"),IF(NOT(ISNUMBER(U17)),IF(U17=D19,"PASS","FAIL"),"FAIL")),"FAIL")
B20: Actual Direct Cost | C20: =V17 | D20: 0 | E20: =IF(ISNUMBER(D20),IF(ISNUMBER(V17),ABS(V17-D20),"N/A"),"N/A") | F20: =IFERROR(IF(ISNUMBER(D20),IF(ISNUMBER(V17),IF(ABS(V17-D20)<=0.01,"PASS","FAIL"),"FAIL"),IF(NOT(ISNUMBER(V17)),IF(V17=D20,"PASS","FAIL"),"FAIL")),"FAIL")
B21: Direct Cost Gap (ADC − Actual) | C21: =W17 | D21: 65000 | E21: =IF(ISNUMBER(D21),IF(ISNUMBER(W17),ABS(W17-D21),"N/A"),"N/A") | F21: =IFERROR(IF(ISNUMBER(D21),IF(ISNUMBER(W17),IF(ABS(W17-D21)<=0.01,"PASS","FAIL"),"FAIL"),IF(NOT(ISNUMBER(W17)),IF(W17=D21,"PASS","FAIL"),"FAIL")),"FAIL")
B22: Expected Contribution Margin | C22: =X17 | D22: 30000 | E22: =IF(ISNUMBER(D22),IF(ISNUMBER(X17),ABS(X17-D22),"N/A"),"N/A") | F22: =IFERROR(IF(ISNUMBER(D22),IF(ISNUMBER(X17),IF(ABS(X17-D22)<=0.01,"PASS","FAIL"),"FAIL"),IF(NOT(ISNUMBER(X17)),IF(X17=D22,"PASS","FAIL"),"FAIL")),"FAIL")
B23: Expected CM Rate | C23: =Y17 | D23: 0.3 | E23: =IF(ISNUMBER(D23),IF(ISNUMBER(Y17),ABS(Y17-D23),"N/A"),"N/A") | F23: =IFERROR(IF(ISNUMBER(D23),IF(ISNUMBER(Y17),IF(ABS(Y17-D23)<=0.0001,"PASS","FAIL"),"FAIL"),IF(NOT(ISNUMBER(Y17)),IF(Y17=D23,"PASS","FAIL"),"FAIL")),"FAIL")
B25: TC3. Net-sales fee only (b>0)
B26: Metric | C26: Excel Result | D26: Python Reference | E26: Difference | F26: PASS / FAIL
B27: Market Net Sales ex VAT (N) | C27: =S27 | D27: 100000 | E27: =IF(ISNUMBER(D27),IF(ISNUMBER(S27),ABS(S27-D27),"N/A"),"N/A") | F27: =IFERROR(IF(ISNUMBER(D27),IF(ISNUMBER(S27),IF(ABS(S27-D27)<=0.01,"PASS","FAIL"),"FAIL"),IF(NOT(ISNUMBER(S27)),IF(S27=D27,"PASS","FAIL"),"FAIL")),"FAIL") | I27: 100000 | J27: FALSE | L27: 0.3 | M27: 0 | N27: 0.1 | O27: 0 | P27: 0 | Q27: none | R27: none | S27: =IFERROR(IF(ISBLANK($I$27),"UNKNOWN",IF(ISBLANK($J$27),"UNKNOWN",IF($J$27=FALSE,$I$27,IF(ISBLANK($K$27),"UNKNOWN",$I$27/(1+$K$27))))),"ERROR") | T27: =IFERROR(IF(ISBLANK($I$27),"UNKNOWN",IF(ISBLANK($J$27),"UNKNOWN",IF($J$27=TRUE,$I$27,IF(ISBLANK($K$27),"UNKNOWN",$I$27*(1+$K$27))))),"ERROR") | U27: =IFERROR(IF(OR(S27="ERROR",Z27="ERROR",AA27="ERROR",AB27="ERROR",AC27="ERROR"),"ERROR",IF(OR(NOT(ISNUMBER(S27)),NOT(ISNUMBER(Z27)),NOT(ISNUMBER(AA27)),NOT(ISNUMBER(AB27)),NOT(ISNUMBER(AC27))),"UNKNOWN",IF(AC27>0,IF(T27="ERROR","ERROR",IF(NOT(ISNUMBER(T27)),"UNKNOWN",S27*(1-Z27-AB27)-AC27*T27-AA27)),S27*(1-Z27-AB27)-AA27))),"ERROR") | V27: =IFERROR(IF($R$27="invalid","ERROR",IF($R$27="unresolved","UNKNOWN",IF(ISBLANK($P$27),"UNKNOWN",$P$27))),"ERROR") | W27: =IFERROR(IF(OR(U27="ERROR",V27="ERROR"),"ERROR",IF(OR(NOT(ISNUMBER(U27)),NOT(ISNUMBER(V27))),"UNKNOWN",U27-V27)),"ERROR") | X27: =IFERROR(IF(U27="ERROR","ERROR",IF(NOT(ISNUMBER(U27)),"UNKNOWN",IF(AC27>0,S27-U27-AA27-AB27*S27-AC27*T27,S27-U27-AA27-AB27*S27))),"ERROR") | Y27: =IFERROR(IF(X27="ERROR","ERROR",IF(NOT(ISNUMBER(X27)),"UNKNOWN",IF(S27=0,"ERROR",X27/S27))),"ERROR") | Z27: =IFERROR(IF(ISBLANK($L$27),"UNKNOWN",IF(OR($L$27<0,$L$27>=1),"ERROR",$L$27)),"ERROR") | AA27: =IFERROR(IF($Q$27="invalid","ERROR",IF($Q$27="unresolved","UNKNOWN",IF(ISBLANK($M$27),"UNKNOWN",$M$27))),"ERROR") | AB27: =IFERROR(IF($Q$27="invalid","ERROR",IF($Q$27="unresolved","UNKNOWN",IF(ISBLANK($N$27),"UNKNOWN",$N$27))),"ERROR") | AC27: =IFERROR(IF($Q$27="invalid","ERROR",IF($Q$27="unresolved","UNKNOWN",IF(ISBLANK($O$27),"UNKNOWN",$O$27))),"ERROR")
B28: Market Gross Payment incl VAT (G) | C28: =T27 | D28: UNKNOWN | E28: =IF(ISNUMBER(D28),IF(ISNUMBER(T27),ABS(T27-D28),"N/A"),"N/A") | F28: =IFERROR(IF(ISNUMBER(D28),IF(ISNUMBER(T27),IF(ABS(T27-D28)<=0.01,"PASS","FAIL"),"FAIL"),IF(NOT(ISNUMBER(T27)),IF(T27=D28,"PASS","FAIL"),"FAIL")),"FAIL")
B29: Allowable Direct Cost (ADC) | C29: =U27 | D29: 60000 | E29: =IF(ISNUMBER(D29),IF(ISNUMBER(U27),ABS(U27-D29),"N/A"),"N/A") | F29: =IFERROR(IF(ISNUMBER(D29),IF(ISNUMBER(U27),IF(ABS(U27-D29)<=0.01,"PASS","FAIL"),"FAIL"),IF(NOT(ISNUMBER(U27)),IF(U27=D29,"PASS","FAIL"),"FAIL")),"FAIL")
B30: Actual Direct Cost | C30: =V27 | D30: 0 | E30: =IF(ISNUMBER(D30),IF(ISNUMBER(V27),ABS(V27-D30),"N/A"),"N/A") | F30: =IFERROR(IF(ISNUMBER(D30),IF(ISNUMBER(V27),IF(ABS(V27-D30)<=0.01,"PASS","FAIL"),"FAIL"),IF(NOT(ISNUMBER(V27)),IF(V27=D30,"PASS","FAIL"),"FAIL")),"FAIL")
B31: Direct Cost Gap (ADC − Actual) | C31: =W27 | D31: 60000 | E31: =IF(ISNUMBER(D31),IF(ISNUMBER(W27),ABS(W27-D31),"N/A"),"N/A") | F31: =IFERROR(IF(ISNUMBER(D31),IF(ISNUMBER(W27),IF(ABS(W27-D31)<=0.01,"PASS","FAIL"),"FAIL"),IF(NOT(ISNUMBER(W27)),IF(W27=D31,"PASS","FAIL"),"FAIL")),"FAIL")
B32: Expected Contribution Margin | C32: =X27 | D32: 30000 | E32: =IF(ISNUMBER(D32),IF(ISNUMBER(X27),ABS(X27-D32),"N/A"),"N/A") | F32: =IFERROR(IF(ISNUMBER(D32),IF(ISNUMBER(X27),IF(ABS(X27-D32)<=0.01,"PASS","FAIL"),"FAIL"),IF(NOT(ISNUMBER(X27)),IF(X27=D32,"PASS","FAIL"),"FAIL")),"FAIL")
B33: Expected CM Rate | C33: =Y27 | D33: 0.3 | E33: =IF(ISNUMBER(D33),IF(ISNUMBER(Y27),ABS(Y27-D33),"N/A"),"N/A") | F33: =IFERROR(IF(ISNUMBER(D33),IF(ISNUMBER(Y27),IF(ABS(Y27-D33)<=0.0001,"PASS","FAIL"),"FAIL"),IF(NOT(ISNUMBER(Y27)),IF(Y27=D33,"PASS","FAIL"),"FAIL")),"FAIL")
B35: TC4. Gross-payment fee, VAT-exclusive display, v known
B36: Metric | C36: Excel Result | D36: Python Reference | E36: Difference | F36: PASS / FAIL
B37: Market Net Sales ex VAT (N) | C37: =S37 | D37: 100000 | E37: =IF(ISNUMBER(D37),IF(ISNUMBER(S37),ABS(S37-D37),"N/A"),"N/A") | F37: =IFERROR(IF(ISNUMBER(D37),IF(ISNUMBER(S37),IF(ABS(S37-D37)<=0.01,"PASS","FAIL"),"FAIL"),IF(NOT(ISNUMBER(S37)),IF(S37=D37,"PASS","FAIL"),"FAIL")),"FAIL") | I37: 100000 | J37: FALSE | K37: 0.1 | L37: 0.3 | M37: 0 | N37: 0 | O37: 0.05 | P37: 0 | Q37: none | R37: none | S37: =IFERROR(IF(ISBLANK($I$37),"UNKNOWN",IF(ISBLANK($J$37),"UNKNOWN",IF($J$37=FALSE,$I$37,IF(ISBLANK($K$37),"UNKNOWN",$I$37/(1+$K$37))))),"ERROR") | T37: =IFERROR(IF(ISBLANK($I$37),"UNKNOWN",IF(ISBLANK($J$37),"UNKNOWN",IF($J$37=TRUE,$I$37,IF(ISBLANK($K$37),"UNKNOWN",$I$37*(1+$K$37))))),"ERROR") | U37: =IFERROR(IF(OR(S37="ERROR",Z37="ERROR",AA37="ERROR",AB37="ERROR",AC37="ERROR"),"ERROR",IF(OR(NOT(ISNUMBER(S37)),NOT(ISNUMBER(Z37)),NOT(ISNUMBER(AA37)),NOT(ISNUMBER(AB37)),NOT(ISNUMBER(AC37))),"UNKNOWN",IF(AC37>0,IF(T37="ERROR","ERROR",IF(NOT(ISNUMBER(T37)),"UNKNOWN",S37*(1-Z37-AB37)-AC37*T37-AA37)),S37*(1-Z37-AB37)-AA37))),"ERROR") | V37: =IFERROR(IF($R$37="invalid","ERROR",IF($R$37="unresolved","UNKNOWN",IF(ISBLANK($P$37),"UNKNOWN",$P$37))),"ERROR") | W37: =IFERROR(IF(OR(U37="ERROR",V37="ERROR"),"ERROR",IF(OR(NOT(ISNUMBER(U37)),NOT(ISNUMBER(V37))),"UNKNOWN",U37-V37)),"ERROR") | X37: =IFERROR(IF(U37="ERROR","ERROR",IF(NOT(ISNUMBER(U37)),"UNKNOWN",IF(AC37>0,S37-U37-AA37-AB37*S37-AC37*T37,S37-U37-AA37-AB37*S37))),"ERROR") | Y37: =IFERROR(IF(X37="ERROR","ERROR",IF(NOT(ISNUMBER(X37)),"UNKNOWN",IF(S37=0,"ERROR",X37/S37))),"ERROR") | Z37: =IFERROR(IF(ISBLANK($L$37),"UNKNOWN",IF(OR($L$37<0,$L$37>=1),"ERROR",$L$37)),"ERROR") | AA37: =IFERROR(IF($Q$37="invalid","ERROR",IF($Q$37="unresolved","UNKNOWN",IF(ISBLANK($M$37),"UNKNOWN",$M$37))),"ERROR") | AB37: =IFERROR(IF($Q$37="invalid","ERROR",IF($Q$37="unresolved","UNKNOWN",IF(ISBLANK($N$37),"UNKNOWN",$N$37))),"ERROR") | AC37: =IFERROR(IF($Q$37="invalid","ERROR",IF($Q$37="unresolved","UNKNOWN",IF(ISBLANK($O$37),"UNKNOWN",$O$37))),"ERROR")
B38: Market Gross Payment incl VAT (G) | C38: =T37 | D38: 110000 | E38: =IF(ISNUMBER(D38),IF(ISNUMBER(T37),ABS(T37-D38),"N/A"),"N/A") | F38: =IFERROR(IF(ISNUMBER(D38),IF(ISNUMBER(T37),IF(ABS(T37-D38)<=0.01,"PASS","FAIL"),"FAIL"),IF(NOT(ISNUMBER(T37)),IF(T37=D38,"PASS","FAIL"),"FAIL")),"FAIL")
B39: Allowable Direct Cost (ADC) | C39: =U37 | D39: 64500 | E39: =IF(ISNUMBER(D39),IF(ISNUMBER(U37),ABS(U37-D39),"N/A"),"N/A") | F39: =IFERROR(IF(ISNUMBER(D39),IF(ISNUMBER(U37),IF(ABS(U37-D39)<=0.01,"PASS","FAIL"),"FAIL"),IF(NOT(ISNUMBER(U37)),IF(U37=D39,"PASS","FAIL"),"FAIL")),"FAIL")
B40: Actual Direct Cost | C40: =V37 | D40: 0 | E40: =IF(ISNUMBER(D40),IF(ISNUMBER(V37),ABS(V37-D40),"N/A"),"N/A") | F40: =IFERROR(IF(ISNUMBER(D40),IF(ISNUMBER(V37),IF(ABS(V37-D40)<=0.01,"PASS","FAIL"),"FAIL"),IF(NOT(ISNUMBER(V37)),IF(V37=D40,"PASS","FAIL"),"FAIL")),"FAIL")
B41: Direct Cost Gap (ADC − Actual) | C41: =W37 | D41: 64500 | E41: =IF(ISNUMBER(D41),IF(ISNUMBER(W37),ABS(W37-D41),"N/A"),"N/A") | F41: =IFERROR(IF(ISNUMBER(D41),IF(ISNUMBER(W37),IF(ABS(W37-D41)<=0.01,"PASS","FAIL"),"FAIL"),IF(NOT(ISNUMBER(W37)),IF(W37=D41,"PASS","FAIL"),"FAIL")),"FAIL")
B42: Expected Contribution Margin | C42: =X37 | D42: 30000 | E42: =IF(ISNUMBER(D42),IF(ISNUMBER(X37),ABS(X37-D42),"N/A"),"N/A") | F42: =IFERROR(IF(ISNUMBER(D42),IF(ISNUMBER(X37),IF(ABS(X37-D42)<=0.01,"PASS","FAIL"),"FAIL"),IF(NOT(ISNUMBER(X37)),IF(X37=D42,"PASS","FAIL"),"FAIL")),"FAIL")
B43: Expected CM Rate | C43: =Y37 | D43: 0.3 | E43: =IF(ISNUMBER(D43),IF(ISNUMBER(Y37),ABS(Y37-D43),"N/A"),"N/A") | F43: =IFERROR(IF(ISNUMBER(D43),IF(ISNUMBER(Y37),IF(ABS(Y37-D43)<=0.0001,"PASS","FAIL"),"FAIL"),IF(NOT(ISNUMBER(Y37)),IF(Y37=D43,"PASS","FAIL"),"FAIL")),"FAIL")
B45: TC5. VAT-inclusive display, both fee types
B46: Metric | C46: Excel Result | D46: Python Reference | E46: Difference | F46: PASS / FAIL
B47: Market Net Sales ex VAT (N) | C47: =S47 | D47: 100000 | E47: =IF(ISNUMBER(D47),IF(ISNUMBER(S47),ABS(S47-D47),"N/A"),"N/A") | F47: =IFERROR(IF(ISNUMBER(D47),IF(ISNUMBER(S47),IF(ABS(S47-D47)<=0.01,"PASS","FAIL"),"FAIL"),IF(NOT(ISNUMBER(S47)),IF(S47=D47,"PASS","FAIL"),"FAIL")),"FAIL") | I47: 110000 | J47: TRUE | K47: 0.1 | L47: 0.3 | M47: 1000 | N47: 0.1 | O47: 0.03 | P47: 0 | Q47: none | R47: none | S47: =IFERROR(IF(ISBLANK($I$47),"UNKNOWN",IF(ISBLANK($J$47),"UNKNOWN",IF($J$47=FALSE,$I$47,IF(ISBLANK($K$47),"UNKNOWN",$I$47/(1+$K$47))))),"ERROR") | T47: =IFERROR(IF(ISBLANK($I$47),"UNKNOWN",IF(ISBLANK($J$47),"UNKNOWN",IF($J$47=TRUE,$I$47,IF(ISBLANK($K$47),"UNKNOWN",$I$47*(1+$K$47))))),"ERROR") | U47: =IFERROR(IF(OR(S47="ERROR",Z47="ERROR",AA47="ERROR",AB47="ERROR",AC47="ERROR"),"ERROR",IF(OR(NOT(ISNUMBER(S47)),NOT(ISNUMBER(Z47)),NOT(ISNUMBER(AA47)),NOT(ISNUMBER(AB47)),NOT(ISNUMBER(AC47))),"UNKNOWN",IF(AC47>0,IF(T47="ERROR","ERROR",IF(NOT(ISNUMBER(T47)),"UNKNOWN",S47*(1-Z47-AB47)-AC47*T47-AA47)),S47*(1-Z47-AB47)-AA47))),"ERROR") | V47: =IFERROR(IF($R$47="invalid","ERROR",IF($R$47="unresolved","UNKNOWN",IF(ISBLANK($P$47),"UNKNOWN",$P$47))),"ERROR") | W47: =IFERROR(IF(OR(U47="ERROR",V47="ERROR"),"ERROR",IF(OR(NOT(ISNUMBER(U47)),NOT(ISNUMBER(V47))),"UNKNOWN",U47-V47)),"ERROR") | X47: =IFERROR(IF(U47="ERROR","ERROR",IF(NOT(ISNUMBER(U47)),"UNKNOWN",IF(AC47>0,S47-U47-AA47-AB47*S47-AC47*T47,S47-U47-AA47-AB47*S47))),"ERROR") | Y47: =IFERROR(IF(X47="ERROR","ERROR",IF(NOT(ISNUMBER(X47)),"UNKNOWN",IF(S47=0,"ERROR",X47/S47))),"ERROR") | Z47: =IFERROR(IF(ISBLANK($L$47),"UNKNOWN",IF(OR($L$47<0,$L$47>=1),"ERROR",$L$47)),"ERROR") | AA47: =IFERROR(IF($Q$47="invalid","ERROR",IF($Q$47="unresolved","UNKNOWN",IF(ISBLANK($M$47),"UNKNOWN",$M$47))),"ERROR") | AB47: =IFERROR(IF($Q$47="invalid","ERROR",IF($Q$47="unresolved","UNKNOWN",IF(ISBLANK($N$47),"UNKNOWN",$N$47))),"ERROR") | AC47: =IFERROR(IF($Q$47="invalid","ERROR",IF($Q$47="unresolved","UNKNOWN",IF(ISBLANK($O$47),"UNKNOWN",$O$47))),"ERROR")
B48: Market Gross Payment incl VAT (G) | C48: =T47 | D48: 110000 | E48: =IF(ISNUMBER(D48),IF(ISNUMBER(T47),ABS(T47-D48),"N/A"),"N/A") | F48: =IFERROR(IF(ISNUMBER(D48),IF(ISNUMBER(T47),IF(ABS(T47-D48)<=0.01,"PASS","FAIL"),"FAIL"),IF(NOT(ISNUMBER(T47)),IF(T47=D48,"PASS","FAIL"),"FAIL")),"FAIL")
B49: Allowable Direct Cost (ADC) | C49: =U47 | D49: 55700 | E49: =IF(ISNUMBER(D49),IF(ISNUMBER(U47),ABS(U47-D49),"N/A"),"N/A") | F49: =IFERROR(IF(ISNUMBER(D49),IF(ISNUMBER(U47),IF(ABS(U47-D49)<=0.01,"PASS","FAIL"),"FAIL"),IF(NOT(ISNUMBER(U47)),IF(U47=D49,"PASS","FAIL"),"FAIL")),"FAIL")
B50: Actual Direct Cost | C50: =V47 | D50: 0 | E50: =IF(ISNUMBER(D50),IF(ISNUMBER(V47),ABS(V47-D50),"N/A"),"N/A") | F50: =IFERROR(IF(ISNUMBER(D50),IF(ISNUMBER(V47),IF(ABS(V47-D50)<=0.01,"PASS","FAIL"),"FAIL"),IF(NOT(ISNUMBER(V47)),IF(V47=D50,"PASS","FAIL"),"FAIL")),"FAIL")
B51: Direct Cost Gap (ADC − Actual) | C51: =W47 | D51: 55700 | E51: =IF(ISNUMBER(D51),IF(ISNUMBER(W47),ABS(W47-D51),"N/A"),"N/A") | F51: =IFERROR(IF(ISNUMBER(D51),IF(ISNUMBER(W47),IF(ABS(W47-D51)<=0.01,"PASS","FAIL"),"FAIL"),IF(NOT(ISNUMBER(W47)),IF(W47=D51,"PASS","FAIL"),"FAIL")),"FAIL")
B52: Expected Contribution Margin | C52: =X47 | D52: 30000 | E52: =IF(ISNUMBER(D52),IF(ISNUMBER(X47),ABS(X47-D52),"N/A"),"N/A") | F52: =IFERROR(IF(ISNUMBER(D52),IF(ISNUMBER(X47),IF(ABS(X47-D52)<=0.01,"PASS","FAIL"),"FAIL"),IF(NOT(ISNUMBER(X47)),IF(X47=D52,"PASS","FAIL"),"FAIL")),"FAIL")
B53: Expected CM Rate | C53: =Y47 | D53: 0.3 | E53: =IF(ISNUMBER(D53),IF(ISNUMBER(Y47),ABS(Y47-D53),"N/A"),"N/A") | F53: =IFERROR(IF(ISNUMBER(D53),IF(ISNUMBER(Y47),IF(ABS(Y47-D53)<=0.0001,"PASS","FAIL"),"FAIL"),IF(NOT(ISNUMBER(Y47)),IF(Y47=D53,"PASS","FAIL"),"FAIL")),"FAIL")
B55: TC6. VAT-exclusive display, same economics as TC5
B56: Metric | C56: Excel Result | D56: Python Reference | E56: Difference | F56: PASS / FAIL
B57: Market Net Sales ex VAT (N) | C57: =S57 | D57: 100000 | E57: =IF(ISNUMBER(D57),IF(ISNUMBER(S57),ABS(S57-D57),"N/A"),"N/A") | F57: =IFERROR(IF(ISNUMBER(D57),IF(ISNUMBER(S57),IF(ABS(S57-D57)<=0.01,"PASS","FAIL"),"FAIL"),IF(NOT(ISNUMBER(S57)),IF(S57=D57,"PASS","FAIL"),"FAIL")),"FAIL") | I57: 100000 | J57: FALSE | K57: 0.1 | L57: 0.3 | M57: 1000 | N57: 0.1 | O57: 0.03 | P57: 0 | Q57: none | R57: none | S57: =IFERROR(IF(ISBLANK($I$57),"UNKNOWN",IF(ISBLANK($J$57),"UNKNOWN",IF($J$57=FALSE,$I$57,IF(ISBLANK($K$57),"UNKNOWN",$I$57/(1+$K$57))))),"ERROR") | T57: =IFERROR(IF(ISBLANK($I$57),"UNKNOWN",IF(ISBLANK($J$57),"UNKNOWN",IF($J$57=TRUE,$I$57,IF(ISBLANK($K$57),"UNKNOWN",$I$57*(1+$K$57))))),"ERROR") | U57: =IFERROR(IF(OR(S57="ERROR",Z57="ERROR",AA57="ERROR",AB57="ERROR",AC57="ERROR"),"ERROR",IF(OR(NOT(ISNUMBER(S57)),NOT(ISNUMBER(Z57)),NOT(ISNUMBER(AA57)),NOT(ISNUMBER(AB57)),NOT(ISNUMBER(AC57))),"UNKNOWN",IF(AC57>0,IF(T57="ERROR","ERROR",IF(NOT(ISNUMBER(T57)),"UNKNOWN",S57*(1-Z57-AB57)-AC57*T57-AA57)),S57*(1-Z57-AB57)-AA57))),"ERROR") | V57: =IFERROR(IF($R$57="invalid","ERROR",IF($R$57="unresolved","UNKNOWN",IF(ISBLANK($P$57),"UNKNOWN",$P$57))),"ERROR") | W57: =IFERROR(IF(OR(U57="ERROR",V57="ERROR"),"ERROR",IF(OR(NOT(ISNUMBER(U57)),NOT(ISNUMBER(V57))),"UNKNOWN",U57-V57)),"ERROR") | X57: =IFERROR(IF(U57="ERROR","ERROR",IF(NOT(ISNUMBER(U57)),"UNKNOWN",IF(AC57>0,S57-U57-AA57-AB57*S57-AC57*T57,S57-U57-AA57-AB57*S57))),"ERROR") | Y57: =IFERROR(IF(X57="ERROR","ERROR",IF(NOT(ISNUMBER(X57)),"UNKNOWN",IF(S57=0,"ERROR",X57/S57))),"ERROR") | Z57: =IFERROR(IF(ISBLANK($L$57),"UNKNOWN",IF(OR($L$57<0,$L$57>=1),"ERROR",$L$57)),"ERROR") | AA57: =IFERROR(IF($Q$57="invalid","ERROR",IF($Q$57="unresolved","UNKNOWN",IF(ISBLANK($M$57),"UNKNOWN",$M$57))),"ERROR") | AB57: =IFERROR(IF($Q$57="invalid","ERROR",IF($Q$57="unresolved","UNKNOWN",IF(ISBLANK($N$57),"UNKNOWN",$N$57))),"ERROR") | AC57: =IFERROR(IF($Q$57="invalid","ERROR",IF($Q$57="unresolved","UNKNOWN",IF(ISBLANK($O$57),"UNKNOWN",$O$57))),"ERROR")
B58: Market Gross Payment incl VAT (G) | C58: =T57 | D58: 110000 | E58: =IF(ISNUMBER(D58),IF(ISNUMBER(T57),ABS(T57-D58),"N/A"),"N/A") | F58: =IFERROR(IF(ISNUMBER(D58),IF(ISNUMBER(T57),IF(ABS(T57-D58)<=0.01,"PASS","FAIL"),"FAIL"),IF(NOT(ISNUMBER(T57)),IF(T57=D58,"PASS","FAIL"),"FAIL")),"FAIL")
B59: Allowable Direct Cost (ADC) | C59: =U57 | D59: 55700 | E59: =IF(ISNUMBER(D59),IF(ISNUMBER(U57),ABS(U57-D59),"N/A"),"N/A") | F59: =IFERROR(IF(ISNUMBER(D59),IF(ISNUMBER(U57),IF(ABS(U57-D59)<=0.01,"PASS","FAIL"),"FAIL"),IF(NOT(ISNUMBER(U57)),IF(U57=D59,"PASS","FAIL"),"FAIL")),"FAIL")
B60: Actual Direct Cost | C60: =V57 | D60: 0 | E60: =IF(ISNUMBER(D60),IF(ISNUMBER(V57),ABS(V57-D60),"N/A"),"N/A") | F60: =IFERROR(IF(ISNUMBER(D60),IF(ISNUMBER(V57),IF(ABS(V57-D60)<=0.01,"PASS","FAIL"),"FAIL"),IF(NOT(ISNUMBER(V57)),IF(V57=D60,"PASS","FAIL"),"FAIL")),"FAIL")
B61: Direct Cost Gap (ADC − Actual) | C61: =W57 | D61: 55700 | E61: =IF(ISNUMBER(D61),IF(ISNUMBER(W57),ABS(W57-D61),"N/A"),"N/A") | F61: =IFERROR(IF(ISNUMBER(D61),IF(ISNUMBER(W57),IF(ABS(W57-D61)<=0.01,"PASS","FAIL"),"FAIL"),IF(NOT(ISNUMBER(W57)),IF(W57=D61,"PASS","FAIL"),"FAIL")),"FAIL")
B62: Expected Contribution Margin | C62: =X57 | D62: 30000 | E62: =IF(ISNUMBER(D62),IF(ISNUMBER(X57),ABS(X57-D62),"N/A"),"N/A") | F62: =IFERROR(IF(ISNUMBER(D62),IF(ISNUMBER(X57),IF(ABS(X57-D62)<=0.01,"PASS","FAIL"),"FAIL"),IF(NOT(ISNUMBER(X57)),IF(X57=D62,"PASS","FAIL"),"FAIL")),"FAIL")
B63: Expected CM Rate | C63: =Y57 | D63: 0.3 | E63: =IF(ISNUMBER(D63),IF(ISNUMBER(Y57),ABS(Y57-D63),"N/A"),"N/A") | F63: =IFERROR(IF(ISNUMBER(D63),IF(ISNUMBER(Y57),IF(ABS(Y57-D63)<=0.0001,"PASS","FAIL"),"FAIL"),IF(NOT(ISNUMBER(Y57)),IF(Y57=D63,"PASS","FAIL"),"FAIL")),"FAIL")
B65: TC7. VAT-exclusive, v UNKNOWN, a=0 (ADC still OK)
B66: Metric | C66: Excel Result | D66: Python Reference | E66: Difference | F66: PASS / FAIL
B67: Market Net Sales ex VAT (N) | C67: =S67 | D67: 100000 | E67: =IF(ISNUMBER(D67),IF(ISNUMBER(S67),ABS(S67-D67),"N/A"),"N/A") | F67: =IFERROR(IF(ISNUMBER(D67),IF(ISNUMBER(S67),IF(ABS(S67-D67)<=0.01,"PASS","FAIL"),"FAIL"),IF(NOT(ISNUMBER(S67)),IF(S67=D67,"PASS","FAIL"),"FAIL")),"FAIL") | I67: 100000 | J67: FALSE | L67: 0.3 | M67: 1000 | N67: 0.1 | O67: 0 | P67: 0 | Q67: none | R67: none | S67: =IFERROR(IF(ISBLANK($I$67),"UNKNOWN",IF(ISBLANK($J$67),"UNKNOWN",IF($J$67=FALSE,$I$67,IF(ISBLANK($K$67),"UNKNOWN",$I$67/(1+$K$67))))),"ERROR") | T67: =IFERROR(IF(ISBLANK($I$67),"UNKNOWN",IF(ISBLANK($J$67),"UNKNOWN",IF($J$67=TRUE,$I$67,IF(ISBLANK($K$67),"UNKNOWN",$I$67*(1+$K$67))))),"ERROR") | U67: =IFERROR(IF(OR(S67="ERROR",Z67="ERROR",AA67="ERROR",AB67="ERROR",AC67="ERROR"),"ERROR",IF(OR(NOT(ISNUMBER(S67)),NOT(ISNUMBER(Z67)),NOT(ISNUMBER(AA67)),NOT(ISNUMBER(AB67)),NOT(ISNUMBER(AC67))),"UNKNOWN",IF(AC67>0,IF(T67="ERROR","ERROR",IF(NOT(ISNUMBER(T67)),"UNKNOWN",S67*(1-Z67-AB67)-AC67*T67-AA67)),S67*(1-Z67-AB67)-AA67))),"ERROR") | V67: =IFERROR(IF($R$67="invalid","ERROR",IF($R$67="unresolved","UNKNOWN",IF(ISBLANK($P$67),"UNKNOWN",$P$67))),"ERROR") | W67: =IFERROR(IF(OR(U67="ERROR",V67="ERROR"),"ERROR",IF(OR(NOT(ISNUMBER(U67)),NOT(ISNUMBER(V67))),"UNKNOWN",U67-V67)),"ERROR") | X67: =IFERROR(IF(U67="ERROR","ERROR",IF(NOT(ISNUMBER(U67)),"UNKNOWN",IF(AC67>0,S67-U67-AA67-AB67*S67-AC67*T67,S67-U67-AA67-AB67*S67))),"ERROR") | Y67: =IFERROR(IF(X67="ERROR","ERROR",IF(NOT(ISNUMBER(X67)),"UNKNOWN",IF(S67=0,"ERROR",X67/S67))),"ERROR") | Z67: =IFERROR(IF(ISBLANK($L$67),"UNKNOWN",IF(OR($L$67<0,$L$67>=1),"ERROR",$L$67)),"ERROR") | AA67: =IFERROR(IF($Q$67="invalid","ERROR",IF($Q$67="unresolved","UNKNOWN",IF(ISBLANK($M$67),"UNKNOWN",$M$67))),"ERROR") | AB67: =IFERROR(IF($Q$67="invalid","ERROR",IF($Q$67="unresolved","UNKNOWN",IF(ISBLANK($N$67),"UNKNOWN",$N$67))),"ERROR") | AC67: =IFERROR(IF($Q$67="invalid","ERROR",IF($Q$67="unresolved","UNKNOWN",IF(ISBLANK($O$67),"UNKNOWN",$O$67))),"ERROR")
B68: Market Gross Payment incl VAT (G) | C68: =T67 | D68: UNKNOWN | E68: =IF(ISNUMBER(D68),IF(ISNUMBER(T67),ABS(T67-D68),"N/A"),"N/A") | F68: =IFERROR(IF(ISNUMBER(D68),IF(ISNUMBER(T67),IF(ABS(T67-D68)<=0.01,"PASS","FAIL"),"FAIL"),IF(NOT(ISNUMBER(T67)),IF(T67=D68,"PASS","FAIL"),"FAIL")),"FAIL")
B69: Allowable Direct Cost (ADC) | C69: =U67 | D69: 59000 | E69: =IF(ISNUMBER(D69),IF(ISNUMBER(U67),ABS(U67-D69),"N/A"),"N/A") | F69: =IFERROR(IF(ISNUMBER(D69),IF(ISNUMBER(U67),IF(ABS(U67-D69)<=0.01,"PASS","FAIL"),"FAIL"),IF(NOT(ISNUMBER(U67)),IF(U67=D69,"PASS","FAIL"),"FAIL")),"FAIL")
B70: Actual Direct Cost | C70: =V67 | D70: 0 | E70: =IF(ISNUMBER(D70),IF(ISNUMBER(V67),ABS(V67-D70),"N/A"),"N/A") | F70: =IFERROR(IF(ISNUMBER(D70),IF(ISNUMBER(V67),IF(ABS(V67-D70)<=0.01,"PASS","FAIL"),"FAIL"),IF(NOT(ISNUMBER(V67)),IF(V67=D70,"PASS","FAIL"),"FAIL")),"FAIL")
B71: Direct Cost Gap (ADC − Actual) | C71: =W67 | D71: 59000 | E71: =IF(ISNUMBER(D71),IF(ISNUMBER(W67),ABS(W67-D71),"N/A"),"N/A") | F71: =IFERROR(IF(ISNUMBER(D71),IF(ISNUMBER(W67),IF(ABS(W67-D71)<=0.01,"PASS","FAIL"),"FAIL"),IF(NOT(ISNUMBER(W67)),IF(W67=D71,"PASS","FAIL"),"FAIL")),"FAIL")
B72: Expected Contribution Margin | C72: =X67 | D72: 30000 | E72: =IF(ISNUMBER(D72),IF(ISNUMBER(X67),ABS(X67-D72),"N/A"),"N/A") | F72: =IFERROR(IF(ISNUMBER(D72),IF(ISNUMBER(X67),IF(ABS(X67-D72)<=0.01,"PASS","FAIL"),"FAIL"),IF(NOT(ISNUMBER(X67)),IF(X67=D72,"PASS","FAIL"),"FAIL")),"FAIL")
B73: Expected CM Rate | C73: =Y67 | D73: 0.3 | E73: =IF(ISNUMBER(D73),IF(ISNUMBER(Y67),ABS(Y67-D73),"N/A"),"N/A") | F73: =IFERROR(IF(ISNUMBER(D73),IF(ISNUMBER(Y67),IF(ABS(Y67-D73)<=0.0001,"PASS","FAIL"),"FAIL"),IF(NOT(ISNUMBER(Y67)),IF(Y67=D73,"PASS","FAIL"),"FAIL")),"FAIL")
B75: TC8. VAT-exclusive, v UNKNOWN, a>0 (ADC goes UNKNOWN)
B76: Metric | C76: Excel Result | D76: Python Reference | E76: Difference | F76: PASS / FAIL
B77: Market Net Sales ex VAT (N) | C77: =S77 | D77: 100000 | E77: =IF(ISNUMBER(D77),IF(ISNUMBER(S77),ABS(S77-D77),"N/A"),"N/A") | F77: =IFERROR(IF(ISNUMBER(D77),IF(ISNUMBER(S77),IF(ABS(S77-D77)<=0.01,"PASS","FAIL"),"FAIL"),IF(NOT(ISNUMBER(S77)),IF(S77=D77,"PASS","FAIL"),"FAIL")),"FAIL") | I77: 100000 | J77: FALSE | L77: 0.3 | M77: 0 | N77: 0 | O77: 0.05 | P77: 0 | Q77: none | R77: none | S77: =IFERROR(IF(ISBLANK($I$77),"UNKNOWN",IF(ISBLANK($J$77),"UNKNOWN",IF($J$77=FALSE,$I$77,IF(ISBLANK($K$77),"UNKNOWN",$I$77/(1+$K$77))))),"ERROR") | T77: =IFERROR(IF(ISBLANK($I$77),"UNKNOWN",IF(ISBLANK($J$77),"UNKNOWN",IF($J$77=TRUE,$I$77,IF(ISBLANK($K$77),"UNKNOWN",$I$77*(1+$K$77))))),"ERROR") | U77: =IFERROR(IF(OR(S77="ERROR",Z77="ERROR",AA77="ERROR",AB77="ERROR",AC77="ERROR"),"ERROR",IF(OR(NOT(ISNUMBER(S77)),NOT(ISNUMBER(Z77)),NOT(ISNUMBER(AA77)),NOT(ISNUMBER(AB77)),NOT(ISNUMBER(AC77))),"UNKNOWN",IF(AC77>0,IF(T77="ERROR","ERROR",IF(NOT(ISNUMBER(T77)),"UNKNOWN",S77*(1-Z77-AB77)-AC77*T77-AA77)),S77*(1-Z77-AB77)-AA77))),"ERROR") | V77: =IFERROR(IF($R$77="invalid","ERROR",IF($R$77="unresolved","UNKNOWN",IF(ISBLANK($P$77),"UNKNOWN",$P$77))),"ERROR") | W77: =IFERROR(IF(OR(U77="ERROR",V77="ERROR"),"ERROR",IF(OR(NOT(ISNUMBER(U77)),NOT(ISNUMBER(V77))),"UNKNOWN",U77-V77)),"ERROR") | X77: =IFERROR(IF(U77="ERROR","ERROR",IF(NOT(ISNUMBER(U77)),"UNKNOWN",IF(AC77>0,S77-U77-AA77-AB77*S77-AC77*T77,S77-U77-AA77-AB77*S77))),"ERROR") | Y77: =IFERROR(IF(X77="ERROR","ERROR",IF(NOT(ISNUMBER(X77)),"UNKNOWN",IF(S77=0,"ERROR",X77/S77))),"ERROR") | Z77: =IFERROR(IF(ISBLANK($L$77),"UNKNOWN",IF(OR($L$77<0,$L$77>=1),"ERROR",$L$77)),"ERROR") | AA77: =IFERROR(IF($Q$77="invalid","ERROR",IF($Q$77="unresolved","UNKNOWN",IF(ISBLANK($M$77),"UNKNOWN",$M$77))),"ERROR") | AB77: =IFERROR(IF($Q$77="invalid","ERROR",IF($Q$77="unresolved","UNKNOWN",IF(ISBLANK($N$77),"UNKNOWN",$N$77))),"ERROR") | AC77: =IFERROR(IF($Q$77="invalid","ERROR",IF($Q$77="unresolved","UNKNOWN",IF(ISBLANK($O$77),"UNKNOWN",$O$77))),"ERROR")
B78: Market Gross Payment incl VAT (G) | C78: =T77 | D78: UNKNOWN | E78: =IF(ISNUMBER(D78),IF(ISNUMBER(T77),ABS(T77-D78),"N/A"),"N/A") | F78: =IFERROR(IF(ISNUMBER(D78),IF(ISNUMBER(T77),IF(ABS(T77-D78)<=0.01,"PASS","FAIL"),"FAIL"),IF(NOT(ISNUMBER(T77)),IF(T77=D78,"PASS","FAIL"),"FAIL")),"FAIL")
B79: Allowable Direct Cost (ADC) | C79: =U77 | D79: UNKNOWN | E79: =IF(ISNUMBER(D79),IF(ISNUMBER(U77),ABS(U77-D79),"N/A"),"N/A") | F79: =IFERROR(IF(ISNUMBER(D79),IF(ISNUMBER(U77),IF(ABS(U77-D79)<=0.01,"PASS","FAIL"),"FAIL"),IF(NOT(ISNUMBER(U77)),IF(U77=D79,"PASS","FAIL"),"FAIL")),"FAIL")
B80: Actual Direct Cost | C80: =V77 | D80: 0 | E80: =IF(ISNUMBER(D80),IF(ISNUMBER(V77),ABS(V77-D80),"N/A"),"N/A") | F80: =IFERROR(IF(ISNUMBER(D80),IF(ISNUMBER(V77),IF(ABS(V77-D80)<=0.01,"PASS","FAIL"),"FAIL"),IF(NOT(ISNUMBER(V77)),IF(V77=D80,"PASS","FAIL"),"FAIL")),"FAIL")
B81: Direct Cost Gap (ADC − Actual) | C81: =W77 | D81: UNKNOWN | E81: =IF(ISNUMBER(D81),IF(ISNUMBER(W77),ABS(W77-D81),"N/A"),"N/A") | F81: =IFERROR(IF(ISNUMBER(D81),IF(ISNUMBER(W77),IF(ABS(W77-D81)<=0.01,"PASS","FAIL"),"FAIL"),IF(NOT(ISNUMBER(W77)),IF(W77=D81,"PASS","FAIL"),"FAIL")),"FAIL")
B82: Expected Contribution Margin | C82: =X77 | D82: UNKNOWN | E82: =IF(ISNUMBER(D82),IF(ISNUMBER(X77),ABS(X77-D82),"N/A"),"N/A") | F82: =IFERROR(IF(ISNUMBER(D82),IF(ISNUMBER(X77),IF(ABS(X77-D82)<=0.01,"PASS","FAIL"),"FAIL"),IF(NOT(ISNUMBER(X77)),IF(X77=D82,"PASS","FAIL"),"FAIL")),"FAIL")
B83: Expected CM Rate | C83: =Y77 | D83: UNKNOWN | E83: =IF(ISNUMBER(D83),IF(ISNUMBER(Y77),ABS(Y77-D83),"N/A"),"N/A") | F83: =IFERROR(IF(ISNUMBER(D83),IF(ISNUMBER(Y77),IF(ABS(Y77-D83)<=0.0001,"PASS","FAIL"),"FAIL"),IF(NOT(ISNUMBER(Y77)),IF(Y77=D83,"PASS","FAIL"),"FAIL")),"FAIL")
B85: TC9. Target CM rate UNKNOWN
B86: Metric | C86: Excel Result | D86: Python Reference | E86: Difference | F86: PASS / FAIL
B87: Market Net Sales ex VAT (N) | C87: =S87 | D87: 100000 | E87: =IF(ISNUMBER(D87),IF(ISNUMBER(S87),ABS(S87-D87),"N/A"),"N/A") | F87: =IFERROR(IF(ISNUMBER(D87),IF(ISNUMBER(S87),IF(ABS(S87-D87)<=0.01,"PASS","FAIL"),"FAIL"),IF(NOT(ISNUMBER(S87)),IF(S87=D87,"PASS","FAIL"),"FAIL")),"FAIL") | I87: 100000 | J87: FALSE | M87: 0 | N87: 0 | O87: 0 | P87: 0 | Q87: none | R87: none | S87: =IFERROR(IF(ISBLANK($I$87),"UNKNOWN",IF(ISBLANK($J$87),"UNKNOWN",IF($J$87=FALSE,$I$87,IF(ISBLANK($K$87),"UNKNOWN",$I$87/(1+$K$87))))),"ERROR") | T87: =IFERROR(IF(ISBLANK($I$87),"UNKNOWN",IF(ISBLANK($J$87),"UNKNOWN",IF($J$87=TRUE,$I$87,IF(ISBLANK($K$87),"UNKNOWN",$I$87*(1+$K$87))))),"ERROR") | U87: =IFERROR(IF(OR(S87="ERROR",Z87="ERROR",AA87="ERROR",AB87="ERROR",AC87="ERROR"),"ERROR",IF(OR(NOT(ISNUMBER(S87)),NOT(ISNUMBER(Z87)),NOT(ISNUMBER(AA87)),NOT(ISNUMBER(AB87)),NOT(ISNUMBER(AC87))),"UNKNOWN",IF(AC87>0,IF(T87="ERROR","ERROR",IF(NOT(ISNUMBER(T87)),"UNKNOWN",S87*(1-Z87-AB87)-AC87*T87-AA87)),S87*(1-Z87-AB87)-AA87))),"ERROR") | V87: =IFERROR(IF($R$87="invalid","ERROR",IF($R$87="unresolved","UNKNOWN",IF(ISBLANK($P$87),"UNKNOWN",$P$87))),"ERROR") | W87: =IFERROR(IF(OR(U87="ERROR",V87="ERROR"),"ERROR",IF(OR(NOT(ISNUMBER(U87)),NOT(ISNUMBER(V87))),"UNKNOWN",U87-V87)),"ERROR") | X87: =IFERROR(IF(U87="ERROR","ERROR",IF(NOT(ISNUMBER(U87)),"UNKNOWN",IF(AC87>0,S87-U87-AA87-AB87*S87-AC87*T87,S87-U87-AA87-AB87*S87))),"ERROR") | Y87: =IFERROR(IF(X87="ERROR","ERROR",IF(NOT(ISNUMBER(X87)),"UNKNOWN",IF(S87=0,"ERROR",X87/S87))),"ERROR") | Z87: =IFERROR(IF(ISBLANK($L$87),"UNKNOWN",IF(OR($L$87<0,$L$87>=1),"ERROR",$L$87)),"ERROR") | AA87: =IFERROR(IF($Q$87="invalid","ERROR",IF($Q$87="unresolved","UNKNOWN",IF(ISBLANK($M$87),"UNKNOWN",$M$87))),"ERROR") | AB87: =IFERROR(IF($Q$87="invalid","ERROR",IF($Q$87="unresolved","UNKNOWN",IF(ISBLANK($N$87),"UNKNOWN",$N$87))),"ERROR") | AC87: =IFERROR(IF($Q$87="invalid","ERROR",IF($Q$87="unresolved","UNKNOWN",IF(ISBLANK($O$87),"UNKNOWN",$O$87))),"ERROR")
B88: Market Gross Payment incl VAT (G) | C88: =T87 | D88: UNKNOWN | E88: =IF(ISNUMBER(D88),IF(ISNUMBER(T87),ABS(T87-D88),"N/A"),"N/A") | F88: =IFERROR(IF(ISNUMBER(D88),IF(ISNUMBER(T87),IF(ABS(T87-D88)<=0.01,"PASS","FAIL"),"FAIL"),IF(NOT(ISNUMBER(T87)),IF(T87=D88,"PASS","FAIL"),"FAIL")),"FAIL")
B89: Allowable Direct Cost (ADC) | C89: =U87 | D89: UNKNOWN | E89: =IF(ISNUMBER(D89),IF(ISNUMBER(U87),ABS(U87-D89),"N/A"),"N/A") | F89: =IFERROR(IF(ISNUMBER(D89),IF(ISNUMBER(U87),IF(ABS(U87-D89)<=0.01,"PASS","FAIL"),"FAIL"),IF(NOT(ISNUMBER(U87)),IF(U87=D89,"PASS","FAIL"),"FAIL")),"FAIL")
B90: Actual Direct Cost | C90: =V87 | D90: 0 | E90: =IF(ISNUMBER(D90),IF(ISNUMBER(V87),ABS(V87-D90),"N/A"),"N/A") | F90: =IFERROR(IF(ISNUMBER(D90),IF(ISNUMBER(V87),IF(ABS(V87-D90)<=0.01,"PASS","FAIL"),"FAIL"),IF(NOT(ISNUMBER(V87)),IF(V87=D90,"PASS","FAIL"),"FAIL")),"FAIL")
B91: Direct Cost Gap (ADC − Actual) | C91: =W87 | D91: UNKNOWN | E91: =IF(ISNUMBER(D91),IF(ISNUMBER(W87),ABS(W87-D91),"N/A"),"N/A") | F91: =IFERROR(IF(ISNUMBER(D91),IF(ISNUMBER(W87),IF(ABS(W87-D91)<=0.01,"PASS","FAIL"),"FAIL"),IF(NOT(ISNUMBER(W87)),IF(W87=D91,"PASS","FAIL"),"FAIL")),"FAIL")
B92: Expected Contribution Margin | C92: =X87 | D92: UNKNOWN | E92: =IF(ISNUMBER(D92),IF(ISNUMBER(X87),ABS(X87-D92),"N/A"),"N/A") | F92: =IFERROR(IF(ISNUMBER(D92),IF(ISNUMBER(X87),IF(ABS(X87-D92)<=0.01,"PASS","FAIL"),"FAIL"),IF(NOT(ISNUMBER(X87)),IF(X87=D92,"PASS","FAIL"),"FAIL")),"FAIL")
B93: Expected CM Rate | C93: =Y87 | D93: UNKNOWN | E93: =IF(ISNUMBER(D93),IF(ISNUMBER(Y87),ABS(Y87-D93),"N/A"),"N/A") | F93: =IFERROR(IF(ISNUMBER(D93),IF(ISNUMBER(Y87),IF(ABS(Y87-D93)<=0.0001,"PASS","FAIL"),"FAIL"),IF(NOT(ISNUMBER(Y87)),IF(Y87=D93,"PASS","FAIL"),"FAIL")),"FAIL")
B95: TC10. Target CM rate invalid (t>=1)
B96: Metric | C96: Excel Result | D96: Python Reference | E96: Difference | F96: PASS / FAIL
B97: Market Net Sales ex VAT (N) | C97: =S97 | D97: 100000 | E97: =IF(ISNUMBER(D97),IF(ISNUMBER(S97),ABS(S97-D97),"N/A"),"N/A") | F97: =IFERROR(IF(ISNUMBER(D97),IF(ISNUMBER(S97),IF(ABS(S97-D97)<=0.01,"PASS","FAIL"),"FAIL"),IF(NOT(ISNUMBER(S97)),IF(S97=D97,"PASS","FAIL"),"FAIL")),"FAIL") | I97: 100000 | J97: FALSE | L97: 1 | M97: 0 | N97: 0 | O97: 0 | P97: 0 | Q97: none | R97: none | S97: =IFERROR(IF(ISBLANK($I$97),"UNKNOWN",IF(ISBLANK($J$97),"UNKNOWN",IF($J$97=FALSE,$I$97,IF(ISBLANK($K$97),"UNKNOWN",$I$97/(1+$K$97))))),"ERROR") | T97: =IFERROR(IF(ISBLANK($I$97),"UNKNOWN",IF(ISBLANK($J$97),"UNKNOWN",IF($J$97=TRUE,$I$97,IF(ISBLANK($K$97),"UNKNOWN",$I$97*(1+$K$97))))),"ERROR") | U97: =IFERROR(IF(OR(S97="ERROR",Z97="ERROR",AA97="ERROR",AB97="ERROR",AC97="ERROR"),"ERROR",IF(OR(NOT(ISNUMBER(S97)),NOT(ISNUMBER(Z97)),NOT(ISNUMBER(AA97)),NOT(ISNUMBER(AB97)),NOT(ISNUMBER(AC97))),"UNKNOWN",IF(AC97>0,IF(T97="ERROR","ERROR",IF(NOT(ISNUMBER(T97)),"UNKNOWN",S97*(1-Z97-AB97)-AC97*T97-AA97)),S97*(1-Z97-AB97)-AA97))),"ERROR") | V97: =IFERROR(IF($R$97="invalid","ERROR",IF($R$97="unresolved","UNKNOWN",IF(ISBLANK($P$97),"UNKNOWN",$P$97))),"ERROR") | W97: =IFERROR(IF(OR(U97="ERROR",V97="ERROR"),"ERROR",IF(OR(NOT(ISNUMBER(U97)),NOT(ISNUMBER(V97))),"UNKNOWN",U97-V97)),"ERROR") | X97: =IFERROR(IF(U97="ERROR","ERROR",IF(NOT(ISNUMBER(U97)),"UNKNOWN",IF(AC97>0,S97-U97-AA97-AB97*S97-AC97*T97,S97-U97-AA97-AB97*S97))),"ERROR") | Y97: =IFERROR(IF(X97="ERROR","ERROR",IF(NOT(ISNUMBER(X97)),"UNKNOWN",IF(S97=0,"ERROR",X97/S97))),"ERROR") | Z97: =IFERROR(IF(ISBLANK($L$97),"UNKNOWN",IF(OR($L$97<0,$L$97>=1),"ERROR",$L$97)),"ERROR") | AA97: =IFERROR(IF($Q$97="invalid","ERROR",IF($Q$97="unresolved","UNKNOWN",IF(ISBLANK($M$97),"UNKNOWN",$M$97))),"ERROR") | AB97: =IFERROR(IF($Q$97="invalid","ERROR",IF($Q$97="unresolved","UNKNOWN",IF(ISBLANK($N$97),"UNKNOWN",$N$97))),"ERROR") | AC97: =IFERROR(IF($Q$97="invalid","ERROR",IF($Q$97="unresolved","UNKNOWN",IF(ISBLANK($O$97),"UNKNOWN",$O$97))),"ERROR")
B98: Market Gross Payment incl VAT (G) | C98: =T97 | D98: UNKNOWN | E98: =IF(ISNUMBER(D98),IF(ISNUMBER(T97),ABS(T97-D98),"N/A"),"N/A") | F98: =IFERROR(IF(ISNUMBER(D98),IF(ISNUMBER(T97),IF(ABS(T97-D98)<=0.01,"PASS","FAIL"),"FAIL"),IF(NOT(ISNUMBER(T97)),IF(T97=D98,"PASS","FAIL"),"FAIL")),"FAIL")
B99: Allowable Direct Cost (ADC) | C99: =U97 | D99: ERROR | E99: =IF(ISNUMBER(D99),IF(ISNUMBER(U97),ABS(U97-D99),"N/A"),"N/A") | F99: =IFERROR(IF(ISNUMBER(D99),IF(ISNUMBER(U97),IF(ABS(U97-D99)<=0.01,"PASS","FAIL"),"FAIL"),IF(NOT(ISNUMBER(U97)),IF(U97=D99,"PASS","FAIL"),"FAIL")),"FAIL")
B100: Actual Direct Cost | C100: =V97 | D100: 0 | E100: =IF(ISNUMBER(D100),IF(ISNUMBER(V97),ABS(V97-D100),"N/A"),"N/A") | F100: =IFERROR(IF(ISNUMBER(D100),IF(ISNUMBER(V97),IF(ABS(V97-D100)<=0.01,"PASS","FAIL"),"FAIL"),IF(NOT(ISNUMBER(V97)),IF(V97=D100,"PASS","FAIL"),"FAIL")),"FAIL")
B101: Direct Cost Gap (ADC − Actual) | C101: =W97 | D101: ERROR | E101: =IF(ISNUMBER(D101),IF(ISNUMBER(W97),ABS(W97-D101),"N/A"),"N/A") | F101: =IFERROR(IF(ISNUMBER(D101),IF(ISNUMBER(W97),IF(ABS(W97-D101)<=0.01,"PASS","FAIL"),"FAIL"),IF(NOT(ISNUMBER(W97)),IF(W97=D101,"PASS","FAIL"),"FAIL")),"FAIL")
B102: Expected Contribution Margin | C102: =X97 | D102: ERROR | E102: =IF(ISNUMBER(D102),IF(ISNUMBER(X97),ABS(X97-D102),"N/A"),"N/A") | F102: =IFERROR(IF(ISNUMBER(D102),IF(ISNUMBER(X97),IF(ABS(X97-D102)<=0.01,"PASS","FAIL"),"FAIL"),IF(NOT(ISNUMBER(X97)),IF(X97=D102,"PASS","FAIL"),"FAIL")),"FAIL")
B103: Expected CM Rate | C103: =Y97 | D103: ERROR | E103: =IF(ISNUMBER(D103),IF(ISNUMBER(Y97),ABS(Y97-D103),"N/A"),"N/A") | F103: =IFERROR(IF(ISNUMBER(D103),IF(ISNUMBER(Y97),IF(ABS(Y97-D103)<=0.0001,"PASS","FAIL"),"FAIL"),IF(NOT(ISNUMBER(Y97)),IF(Y97=D103,"PASS","FAIL"),"FAIL")),"FAIL")
B105: TC11. Negative allowable direct cost (valid, warning only)
B106: Metric | C106: Excel Result | D106: Python Reference | E106: Difference | F106: PASS / FAIL
B107: Market Net Sales ex VAT (N) | C107: =S107 | D107: 10000 | E107: =IF(ISNUMBER(D107),IF(ISNUMBER(S107),ABS(S107-D107),"N/A"),"N/A") | F107: =IFERROR(IF(ISNUMBER(D107),IF(ISNUMBER(S107),IF(ABS(S107-D107)<=0.01,"PASS","FAIL"),"FAIL"),IF(NOT(ISNUMBER(S107)),IF(S107=D107,"PASS","FAIL"),"FAIL")),"FAIL") | I107: 10000 | J107: FALSE | K107: 0.1 | L107: 0.5 | M107: 0 | N107: 0.3 | O107: 0.3 | P107: 0 | Q107: none | R107: none | S107: =IFERROR(IF(ISBLANK($I$107),"UNKNOWN",IF(ISBLANK($J$107),"UNKNOWN",IF($J$107=FALSE,$I$107,IF(ISBLANK($K$107),"UNKNOWN",$I$107/(1+$K$107))))),"ERROR") | T107: =IFERROR(IF(ISBLANK($I$107),"UNKNOWN",IF(ISBLANK($J$107),"UNKNOWN",IF($J$107=TRUE,$I$107,IF(ISBLANK($K$107),"UNKNOWN",$I$107*(1+$K$107))))),"ERROR") | U107: =IFERROR(IF(OR(S107="ERROR",Z107="ERROR",AA107="ERROR",AB107="ERROR",AC107="ERROR"),"ERROR",IF(OR(NOT(ISNUMBER(S107)),NOT(ISNUMBER(Z107)),NOT(ISNUMBER(AA107)),NOT(ISNUMBER(AB107)),NOT(ISNUMBER(AC107))),"UNKNOWN",IF(AC107>0,IF(T107="ERROR","ERROR",IF(NOT(ISNUMBER(T107)),"UNKNOWN",S107*(1-Z107-AB107)-AC107*T107-AA107)),S107*(1-Z107-AB107)-AA107))),"ERROR") | V107: =IFERROR(IF($R$107="invalid","ERROR",IF($R$107="unresolved","UNKNOWN",IF(ISBLANK($P$107),"UNKNOWN",$P$107))),"ERROR") | W107: =IFERROR(IF(OR(U107="ERROR",V107="ERROR"),"ERROR",IF(OR(NOT(ISNUMBER(U107)),NOT(ISNUMBER(V107))),"UNKNOWN",U107-V107)),"ERROR") | X107: =IFERROR(IF(U107="ERROR","ERROR",IF(NOT(ISNUMBER(U107)),"UNKNOWN",IF(AC107>0,S107-U107-AA107-AB107*S107-AC107*T107,S107-U107-AA107-AB107*S107))),"ERROR") | Y107: =IFERROR(IF(X107="ERROR","ERROR",IF(NOT(ISNUMBER(X107)),"UNKNOWN",IF(S107=0,"ERROR",X107/S107))),"ERROR") | Z107: =IFERROR(IF(ISBLANK($L$107),"UNKNOWN",IF(OR($L$107<0,$L$107>=1),"ERROR",$L$107)),"ERROR") | AA107: =IFERROR(IF($Q$107="invalid","ERROR",IF($Q$107="unresolved","UNKNOWN",IF(ISBLANK($M$107),"UNKNOWN",$M$107))),"ERROR") | AB107: =IFERROR(IF($Q$107="invalid","ERROR",IF($Q$107="unresolved","UNKNOWN",IF(ISBLANK($N$107),"UNKNOWN",$N$107))),"ERROR") | AC107: =IFERROR(IF($Q$107="invalid","ERROR",IF($Q$107="unresolved","UNKNOWN",IF(ISBLANK($O$107),"UNKNOWN",$O$107))),"ERROR")
B108: Market Gross Payment incl VAT (G) | C108: =T107 | D108: 11000 | E108: =IF(ISNUMBER(D108),IF(ISNUMBER(T107),ABS(T107-D108),"N/A"),"N/A") | F108: =IFERROR(IF(ISNUMBER(D108),IF(ISNUMBER(T107),IF(ABS(T107-D108)<=0.01,"PASS","FAIL"),"FAIL"),IF(NOT(ISNUMBER(T107)),IF(T107=D108,"PASS","FAIL"),"FAIL")),"FAIL")
B109: Allowable Direct Cost (ADC) | C109: =U107 | D109: -1300 | E109: =IF(ISNUMBER(D109),IF(ISNUMBER(U107),ABS(U107-D109),"N/A"),"N/A") | F109: =IFERROR(IF(ISNUMBER(D109),IF(ISNUMBER(U107),IF(ABS(U107-D109)<=0.01,"PASS","FAIL"),"FAIL"),IF(NOT(ISNUMBER(U107)),IF(U107=D109,"PASS","FAIL"),"FAIL")),"FAIL")
B110: Actual Direct Cost | C110: =V107 | D110: 0 | E110: =IF(ISNUMBER(D110),IF(ISNUMBER(V107),ABS(V107-D110),"N/A"),"N/A") | F110: =IFERROR(IF(ISNUMBER(D110),IF(ISNUMBER(V107),IF(ABS(V107-D110)<=0.01,"PASS","FAIL"),"FAIL"),IF(NOT(ISNUMBER(V107)),IF(V107=D110,"PASS","FAIL"),"FAIL")),"FAIL")
B111: Direct Cost Gap (ADC − Actual) | C111: =W107 | D111: -1300 | E111: =IF(ISNUMBER(D111),IF(ISNUMBER(W107),ABS(W107-D111),"N/A"),"N/A") | F111: =IFERROR(IF(ISNUMBER(D111),IF(ISNUMBER(W107),IF(ABS(W107-D111)<=0.01,"PASS","FAIL"),"FAIL"),IF(NOT(ISNUMBER(W107)),IF(W107=D111,"PASS","FAIL"),"FAIL")),"FAIL")
B112: Expected Contribution Margin | C112: =X107 | D112: 5000 | E112: =IF(ISNUMBER(D112),IF(ISNUMBER(X107),ABS(X107-D112),"N/A"),"N/A") | F112: =IFERROR(IF(ISNUMBER(D112),IF(ISNUMBER(X107),IF(ABS(X107-D112)<=0.01,"PASS","FAIL"),"FAIL"),IF(NOT(ISNUMBER(X107)),IF(X107=D112,"PASS","FAIL"),"FAIL")),"FAIL")
...

Sheet 08_BEP_SIMULATOR
B2: 08. BEP Simulator — Break-Even Point (Interactive)
B4: INPUT (노란 셀만 입력, 단일 컴포넌트 기준)
B5: Actual Price | C5: 20000 | D5: 현재 실제 판매가격 — BEP는 항상 current price 기준 (MODE B/C 가격 대입 안 함)
B6: Price Includes VAT | C6: FALSE | D6: TRUE=판매가에 VAT 포함 / FALSE=별도 / 빈칸=모름
B7: VAT Rate (v) | C7: 0.1 | D7: a=0이면 CMu 계산에 불필요
B8: Product/Service Direct Cost | C8: 8000 | D8: CMu 계산에만 사용 (fixed_operating_cost와 무관)
B9: Variable Selling/Delivery Cost (Fixed Amount) | C9: 2000 | D9: variable_selling_delivery 중 금액형 항목 합계
B10: Net-Sales Fee Rate (b) | C10: 0 | D10: rate_of_net_sales 합계 — N에 곱함. 없으면 0
B11: Gross-Payment Fee Rate (a) | C11: 0 | D11: rate_of_gross_payment 합계 — G에 곱함. 없으면 0
B12: Fixed Operating Cost Amount | C12: 1000000 | D12: Fixed Cost Allocation Status=component일 때만 사용
B13: Fixed Operating Cost Basis | C13: per_month | D13: analysis period context (예: per_month) — quantity unit이 아님. break_even_quantity_exact.unit은 항상 "units"
B14: Fixed Cost Allocation Status (Excel simulation control — not a schema field) | C14: component | D14: Excel-only. none=fixed_operating_cost 항목 자체가 없음(FC 확정 0, basis 없음) / component=Fixed Operating Cost Amount/Basis 입력 사용 / unresolved=공유비용 배부 미구현(UNKNOWN) / blended_only=배부 대상 아님으로 설정(UNKNOWN, BEP만의 deviation — 다른 모드처럼 0으로 취급하지 않음) / invalid_direct=shared+direct 모순 설정(ERROR). 실제 shared-cost 배부 엔진은 구현되지 않음 — 미지원 상태를 조용히 숫자로 만들지 않는지만 검증.
B16: RESULT (계산값 — 직접 입력 금지)
B17: Contribution Margin per Unit (CMu) | C17: =IFERROR(IF(J21="ERROR","ERROR",IF(OR(NOT(ISNUMBER(J21)),ISBLANK($C$8),ISBLANK($C$9),ISBLANK($C$10),ISBLANK($C$11)),"UNKNOWN",IF($C$11>0,IF(K21="ERROR","ERROR",IF(NOT(ISNUMBER(K21)),"UNKNOWN",J21-$C$8-$C$9-$C$10*J21-$C$11*K21)),J21-$C$8-$C$9-$C$10*J21))),"ERROR") | D17: CMu = N − direct − varfixed − b×N − a×G (a=0이면 G 참조 안 함)
B18: Fixed Operating Cost (FC) | C18: =IFERROR(IF($C$14="invalid_direct","ERROR",IF(FALSE,"ERROR",IF($C$14="none",0,IF(OR($C$14="unresolved",$C$14="blended_only"),"UNKNOWN",IF(ISBLANK($C$12),"UNKNOWN",IF($C$12<0,"ERROR",$C$12)))))),"ERROR") | D18: FC — Fixed Cost Allocation Status에 따라 결정
B19: Break-Even Quantity (Q_BEP) | C19: =IFERROR(IF(OR(C17="ERROR",C18="ERROR"),"ERROR",IF(OR(NOT(ISNUMBER(C17)),NOT(ISNUMBER(C18))),"UNKNOWN",IF(C17<=0,"NOT_APPLICABLE",C18/C17))),"ERROR") | D19: Q_BEP = FC / CMu. CMu<=0이면 NOT_APPLICABLE (0/음수 출력 안 함)
B20: Analysis Period Basis | C20: =IF(OR($C$14="invalid_direct",FALSE),"",IF($C$14="none","",IF(OR($C$14="unresolved",$C$14="blended_only"),"",IF(ISBLANK($C$12),"",IF($C$12<0,"",$C$13))))) | D20: fixed_operating_cost가 정의된 기간 context — quantity unit이 아님. 빈칸=해당 항목 없음/UNKNOWN/ERROR.
J21: =IFERROR(IF(ISBLANK($C$5),"UNKNOWN",IF(ISBLANK($C$6),"UNKNOWN",IF($C$6=FALSE,$C$5,IF(ISBLANK($C$7),"UNKNOWN",$C$5/(1+$C$7))))),"ERROR") | K21: =IFERROR(IF(ISBLANK($C$5),"UNKNOWN",IF(ISBLANK($C$6),"UNKNOWN",IF($C$6=TRUE,$C$5,IF(ISBLANK($C$7),"UNKNOWN",$C$5*(1+$C$7))))),"ERROR") | L21: =IF(FALSE,"",IF($C$14="invalid_direct","INVALID_ALLOCATION_CONFIGURATION",IF(FALSE,"INCONSISTENT_FIXED_COST_BASIS",IF(AND($C$14="component",NOT(ISBLANK($C$12)),$C$12<0),"INVALID_NEGATIVE_COST",IF(C17="ERROR","CALCULATION_ERROR",IF($C$14="blended_only","FIXED_COST_BLENDED_ONLY_NOT_ALLOCATED",IF($C$14="unresolved","UNSUPPORTED_SHARED_COST_ALLOCATION",IF(NOT(ISNUMBER(C17)),"MISSING_DEPENDENCY",IF(AND($C$14="component",ISBLANK($C$12)),"MISSING_DEPENDENCY",IF(AND(C17=0,C18=0),"BREAK_EVEN_UNDEFINED_ZERO_MARGIN_ZERO_FIXED_COST",IF(C17=0,"BREAK_EVEN_UNDEFINED_ZERO_MARGIN",IF(C17<0,"BREAK_EVEN_UNDEFINED_NEGATIVE_MARGIN","NONE"))))))))))))
B23: Self-Check: |Q_BEP × CMu − FC| ≤ tolerance? | C23: =IF(NOT(ISNUMBER(C19)),"N/A — Q_BEP not numeric (UNKNOWN/ERROR/NOT_APPLICABLE)",IF(ABS(C19*C17-C18)<=0.01,"PASS","FAIL")) | D23: Python 출력을 그대로 복사하지 않고, Q_BEP×CMu가 독립적으로 FC와 tolerance 내 일치하는지 역산 검증하는 진단 셀. CMu<=0(NOT_APPLICABLE)이거나 UNKNOWN/ERROR면 N/A.
B24: STATUS
B25: Overall Status | C25: =IF((IF(C17="ERROR",1,0)+IF(C18="ERROR",1,0)+IF(C19="ERROR",1,0))>0,"ERROR — 계산 불가 또는 입력값 모순",IF((IF(C17="UNKNOWN",1,0)+IF(C18="UNKNOWN",1,0)+IF(C19="UNKNOWN",1,0))>0,"INCOMPLETE — 일부 지표 UNKNOWN","OK — 전체 계산 완료 (NOT_APPLICABLE 포함 가능)"))
B26: blank = UNKNOWN / 0 = explicit zero / NOT_APPLICABLE ≠ ERROR·UNKNOWN (module status를 낮추지 않음)
B28: DASHBOARD CARD
B29: Contribution Margin per Unit | F29: Fixed Operating Cost | J29: Break-Even Quantity
B30: =C17 | F30: =C18 | J30: =C19

Sheet 09_BEP_PARITY_TEST
B2: 09. Python Engine vs Excel Formula — BEP Parity Test
B3: 각 케이스는 docs/features/bep/CASE.md의 TC1-23에 대응하며(+ TC24-26은 basis 불일치/NOT_APPLICABLE/multi-component 우선순위 보강 케이스), Excel에 동일 입력값을 리터럴로 심어 08_BEP_SIMULATOR와 같은 수식(build_bep_formulas)으로 독립 재계산하고, Python 참조값(core/engine/modes/bep.py 실행 결과, 빌드 시점에 고정)과 비교합니다. 허용오차 0.01. TC14/TC15/TC24는 Fixed Cost Allocation Status/Basis Consistency 컨트롤로, TC18/TC19/TC26은 Component Count 컨트롤로 시뮬레이션합니다. 26개 중 25개가 live Excel evaluation입니다 — TC13(통화 미지원)만 08_BEP_SIMULATOR에 항목별 통화 입력이 없어(MODE A/B/C Excel Simulator와 동일한 단순화) reference-only(00_GUIDE의 Hybrid HW+SaaS 블록과 동일 패턴)로 표시됩니다. Q_BEP가 숫자일 때는 Self-Check(|Q_BEP×CMu−FC|<=tol)로 Python 값을 그대로 복사하지 않았음을 독립 검증합니다.
B5: TC1. Simple positive CM
B6: Metric | C6: Excel Result | D6: Python Reference | E6: Difference | F6: PASS / FAIL
B7: Contribution Margin per Unit (CMu) | C7: =U7 | D7: 500 | E7: =IF(ISNUMBER(D7),IF(ISNUMBER(U7),ABS(U7-D7),"N/A"),"N/A") | F7: =IFERROR(IF(ISNUMBER(D7),IF(ISNUMBER(U7),IF(ABS(U7-D7)<=0.01,"PASS","FAIL"),"FAIL"),IF(NOT(ISNUMBER(U7)),IF(U7=D7,"PASS","FAIL"),"FAIL")),"FAIL") | I7: 1000 | J7: FALSE | L7: 400 | M7: 100 | N7: 0 | O7: 0 | P7: 50000 | Q7: per_month | R7: component | S7: consistent | T7: 1 | U7: =IF($T$7>1,"ERROR",IFERROR(IF(Y7="ERROR","ERROR",IF(OR(NOT(ISNUMBER(Y7)),ISBLANK($L$7),ISBLANK($M$7),ISBLANK($N$7),ISBLANK($O$7)),"UNKNOWN",IF($O$7>0,IF(Z7="ERROR","ERROR",IF(NOT(ISNUMBER(Z7)),"UNKNOWN",Y7-$L$7-$M$7-$N$7*Y7-$O$7*Z7)),Y7-$L$7-$M$7-$N$7*Y7))),"ERROR")) | V7: =IF($T$7>1,"ERROR",IFERROR(IF($R$7="invalid_direct","ERROR",IF($S$7="inconsistent","ERROR",IF($R$7="none",0,IF(OR($R$7="unresolved",$R$7="blended_only"),"UNKNOWN",IF(ISBLANK($P$7),"UNKNOWN",IF($P$7<0,"ERROR",$P$7)))))),"ERROR")) | W7: =IF($T$7>1,"ERROR",IFERROR(IF(OR(U7="ERROR",V7="ERROR"),"ERROR",IF(OR(NOT(ISNUMBER(U7)),NOT(ISNUMBER(V7))),"UNKNOWN",IF(U7<=0,"NOT_APPLICABLE",V7/U7))),"ERROR")) | X7: =IF($T$7>1,"",IF(OR($R$7="invalid_direct",$S$7="inconsistent"),"",IF($R$7="none","",IF(OR($R$7="unresolved",$R$7="blended_only"),"",IF(ISBLANK($P$7),"",IF($P$7<0,"",$Q$7)))))) | Y7: =IFERROR(IF(ISBLANK($I$7),"UNKNOWN",IF(ISBLANK($J$7),"UNKNOWN",IF($J$7=FALSE,$I$7,IF(ISBLANK($K$7),"UNKNOWN",$I$7/(1+$K$7))))),"ERROR") | Z7: =IFERROR(IF(ISBLANK($I$7),"UNKNOWN",IF(ISBLANK($J$7),"UNKNOWN",IF($J$7=TRUE,$I$7,IF(ISBLANK($K$7),"UNKNOWN",$I$7*(1+$K$7))))),"ERROR") | AA7: =IF($T$7>1,"MULTI_COMPONENT_BEP_NOT_SUPPORTED",IF($R$7="invalid_direct","INVALID_ALLOCATION_CONFIGURATION",IF($S$7="inconsistent","INCONSISTENT_FIXED_COST_BASIS",IF(AND($R$7="component",NOT(ISBLANK($P$7)),$P$7<0),"INVALID_NEGATIVE_COST",IF(U7="ERROR","CALCULATION_ERROR",IF($R$7="blended_only","FIXED_COST_BLENDED_ONLY_NOT_ALLOCATED",IF($R$7="unresolved","UNSUPPORTED_SHARED_COST_ALLOCATION",IF(NOT(ISNUMBER(U7)),"MISSING_DEPENDENCY",IF(AND($R$7="component",ISBLANK($P$7)),"MISSING_DEPENDENCY",IF(AND(U7=0,V7=0),"BREAK_EVEN_UNDEFINED_ZERO_MARGIN_ZERO_FIXED_COST",IF(U7=0,"BREAK_EVEN_UNDEFINED_ZERO_MARGIN",IF(U7<0,"BREAK_EVEN_UNDEFINED_NEGATIVE_MARGIN","NONE"))))))))))))
B8: Fixed Operating Cost (FC) | C8: =V7 | D8: 50000 | E8: =IF(ISNUMBER(D8),IF(ISNUMBER(V7),ABS(V7-D8),"N/A"),"N/A") | F8: =IFERROR(IF(ISNUMBER(D8),IF(ISNUMBER(V7),IF(ABS(V7-D8)<=0.01,"PASS","FAIL"),"FAIL"),IF(NOT(ISNUMBER(V7)),IF(V7=D8,"PASS","FAIL"),"FAIL")),"FAIL")
B9: Break-Even Quantity (Q_BEP) | C9: =W7 | D9: 100 | E9: =IF(ISNUMBER(D9),IF(ISNUMBER(W7),ABS(W7-D9),"N/A"),"N/A") | F9: =IFERROR(IF(ISNUMBER(D9),IF(ISNUMBER(W7),IF(ABS(W7-D9)<=0.01,"PASS","FAIL"),"FAIL"),IF(NOT(ISNUMBER(W7)),IF(W7=D9,"PASS","FAIL"),"FAIL")),"FAIL")
B10: Analysis Period Basis | C10: =X7 | D10: per_month | E10: =IF(ISNUMBER(D10),IF(ISNUMBER(X7),ABS(X7-D10),"N/A"),"N/A") | F10: =IFERROR(IF(ISNUMBER(D10),IF(ISNUMBER(X7),IF(ABS(X7-D10)<=0.01,"PASS","FAIL"),"FAIL"),IF(NOT(ISNUMBER(X7)),IF(X7=D10,"PASS","FAIL"),"FAIL")),"FAIL")
B11: Module Status Tier | C11: =IF(OR(U7="ERROR",V7="ERROR",W7="ERROR"),"ERROR",IF(OR(U7="UNKNOWN",V7="UNKNOWN",W7="UNKNOWN"),"INCOMPLETE","OK")) | D11: OK | F11: =IF(C11=D11,"PASS","FAIL")
B12: Primary Warning Code (diagnostic) | C12: =AA7 | D12: NONE | F12: =IF(AA7=D12,"PASS","FAIL")
B13: Self-Check: |Q_BEP × CMu − FC| ≤ tol | C13: =IF(NOT(ISNUMBER(W7)),"SKIP",IF(ABS(W7*U7-V7)<=0.01,"PASS","FAIL")) | F13: =IF(C13="FAIL","FAIL","PASS")
B15: TC2. Fixed cost = 0 (explicit)
B16: Metric | C16: Excel Result | D16: Python Reference | E16: Difference | F16: PASS / FAIL
B17: Contribution Margin per Unit (CMu) | C17: =U17 | D17: 500 | E17: =IF(ISNUMBER(D17),IF(ISNUMBER(U17),ABS(U17-D17),"N/A"),"N/A") | F17: =IFERROR(IF(ISNUMBER(D17),IF(ISNUMBER(U17),IF(ABS(U17-D17)<=0.01,"PASS","FAIL"),"FAIL"),IF(NOT(ISNUMBER(U17)),IF(U17=D17,"PASS","FAIL"),"FAIL")),"FAIL") | I17: 1000 | J17: FALSE | L17: 400 | M17: 100 | N17: 0 | O17: 0 | P17: 0 | Q17: per_month | R17: component | S17: consistent | T17: 1 | U17: =IF($T$17>1,"ERROR",IFERROR(IF(Y17="ERROR","ERROR",IF(OR(NOT(ISNUMBER(Y17)),ISBLANK($L$17),ISBLANK($M$17),ISBLANK($N$17),ISBLANK($O$17)),"UNKNOWN",IF($O$17>0,IF(Z17="ERROR","ERROR",IF(NOT(ISNUMBER(Z17)),"UNKNOWN",Y17-$L$17-$M$17-$N$17*Y17-$O$17*Z17)),Y17-$L$17-$M$17-$N$17*Y17))),"ERROR")) | V17: =IF($T$17>1,"ERROR",IFERROR(IF($R$17="invalid_direct","ERROR",IF($S$17="inconsistent","ERROR",IF($R$17="none",0,IF(OR($R$17="unresolved",$R$17="blended_only"),"UNKNOWN",IF(ISBLANK($P$17),"UNKNOWN",IF($P$17<0,"ERROR",$P$17)))))),"ERROR")) | W17: =IF($T$17>1,"ERROR",IFERROR(IF(OR(U17="ERROR",V17="ERROR"),"ERROR",IF(OR(NOT(ISNUMBER(U17)),NOT(ISNUMBER(V17))),"UNKNOWN",IF(U17<=0,"NOT_APPLICABLE",V17/U17))),"ERROR")) | X17: =IF($T$17>1,"",IF(OR($R$17="invalid_direct",$S$17="inconsistent"),"",IF($R$17="none","",IF(OR($R$17="unresolved",$R$17="blended_only"),"",IF(ISBLANK($P$17),"",IF($P$17<0,"",$Q$17)))))) | Y17: =IFERROR(IF(ISBLANK($I$17),"UNKNOWN",IF(ISBLANK($J$17),"UNKNOWN",IF($J$17=FALSE,$I$17,IF(ISBLANK($K$17),"UNKNOWN",$I$17/(1+$K$17))))),"ERROR") | Z17: =IFERROR(IF(ISBLANK($I$17),"UNKNOWN",IF(ISBLANK($J$17),"UNKNOWN",IF($J$17=TRUE,$I$17,IF(ISBLANK($K$17),"UNKNOWN",$I$17*(1+$K$17))))),"ERROR") | AA17: =IF($T$17>1,"MULTI_COMPONENT_BEP_NOT_SUPPORTED",IF($R$17="invalid_direct","INVALID_ALLOCATION_CONFIGURATION",IF($S$17="inconsistent","INCONSISTENT_FIXED_COST_BASIS",IF(AND($R$17="component",NOT(ISBLANK($P$17)),$P$17<0),"INVALID_NEGATIVE_COST",IF(U17="ERROR","CALCULATION_ERROR",IF($R$17="blended_only","FIXED_COST_BLENDED_ONLY_NOT_ALLOCATED",IF($R$17="unresolved","UNSUPPORTED_SHARED_COST_ALLOCATION",IF(NOT(ISNUMBER(U17)),"MISSING_DEPENDENCY",IF(AND($R$17="component",ISBLANK($P$17)),"MISSING_DEPENDENCY",IF(AND(U17=0,V17=0),"BREAK_EVEN_UNDEFINED_ZERO_MARGIN_ZERO_FIXED_COST",IF(U17=0,"BREAK_EVEN_UNDEFINED_ZERO_MARGIN",IF(U17<0,"BREAK_EVEN_UNDEFINED_NEGATIVE_MARGIN","NONE"))))))))))))
B18: Fixed Operating Cost (FC) | C18: =V17 | D18: 0 | E18: =IF(ISNUMBER(D18),IF(ISNUMBER(V17),ABS(V17-D18),"N/A"),"N/A") | F18: =IFERROR(IF(ISNUMBER(D18),IF(ISNUMBER(V17),IF(ABS(V17-D18)<=0.01,"PASS","FAIL"),"FAIL"),IF(NOT(ISNUMBER(V17)),IF(V17=D18,"PASS","FAIL"),"FAIL")),"FAIL")
B19: Break-Even Quantity (Q_BEP) | C19: =W17 | D19: 0 | E19: =IF(ISNUMBER(D19),IF(ISNUMBER(W17),ABS(W17-D19),"N/A"),"N/A") | F19: =IFERROR(IF(ISNUMBER(D19),IF(ISNUMBER(W17),IF(ABS(W17-D19)<=0.01,"PASS","FAIL"),"FAIL"),IF(NOT(ISNUMBER(W17)),IF(W17=D19,"PASS","FAIL"),"FAIL")),"FAIL")
B20: Analysis Period Basis | C20: =X17 | D20: per_month | E20: =IF(ISNUMBER(D20),IF(ISNUMBER(X17),ABS(X17-D20),"N/A"),"N/A") | F20: =IFERROR(IF(ISNUMBER(D20),IF(ISNUMBER(X17),IF(ABS(X17-D20)<=0.01,"PASS","FAIL"),"FAIL"),IF(NOT(ISNUMBER(X17)),IF(X17=D20,"PASS","FAIL"),"FAIL")),"FAIL")
B21: Module Status Tier | C21: =IF(OR(U17="ERROR",V17="ERROR",W17="ERROR"),"ERROR",IF(OR(U17="UNKNOWN",V17="UNKNOWN",W17="UNKNOWN"),"INCOMPLETE","OK")) | D21: OK | F21: =IF(C21=D21,"PASS","FAIL")
B22: Primary Warning Code (diagnostic) | C22: =AA17 | D22: NONE | F22: =IF(AA17=D22,"PASS","FAIL")
B23: Self-Check: |Q_BEP × CMu − FC| ≤ tol | C23: =IF(NOT(ISNUMBER(W17)),"SKIP",IF(ABS(W17*U17-V17)<=0.01,"PASS","FAIL")) | F23: =IF(C23="FAIL","FAIL","PASS")
B25: TC3. No fixed-cost item at all
B26: Metric | C26: Excel Result | D26: Python Reference | E26: Difference | F26: PASS / FAIL
B27: Contribution Margin per Unit (CMu) | C27: =U27 | D27: 500 | E27: =IF(ISNUMBER(D27),IF(ISNUMBER(U27),ABS(U27-D27),"N/A"),"N/A") | F27: =IFERROR(IF(ISNUMBER(D27),IF(ISNUMBER(U27),IF(ABS(U27-D27)<=0.01,"PASS","FAIL"),"FAIL"),IF(NOT(ISNUMBER(U27)),IF(U27=D27,"PASS","FAIL"),"FAIL")),"FAIL") | I27: 1000 | J27: FALSE | L27: 400 | M27: 100 | N27: 0 | O27: 0 | R27: none | S27: consistent | T27: 1 | U27: =IF($T$27>1,"ERROR",IFERROR(IF(Y27="ERROR","ERROR",IF(OR(NOT(ISNUMBER(Y27)),ISBLANK($L$27),ISBLANK($M$27),ISBLANK($N$27),ISBLANK($O$27)),"UNKNOWN",IF($O$27>0,IF(Z27="ERROR","ERROR",IF(NOT(ISNUMBER(Z27)),"UNKNOWN",Y27-$L$27-$M$27-$N$27*Y27-$O$27*Z27)),Y27-$L$27-$M$27-$N$27*Y27))),"ERROR")) | V27: =IF($T$27>1,"ERROR",IFERROR(IF($R$27="invalid_direct","ERROR",IF($S$27="inconsistent","ERROR",IF($R$27="none",0,IF(OR($R$27="unresolved",$R$27="blended_only"),"UNKNOWN",IF(ISBLANK($P$27),"UNKNOWN",IF($P$27<0,"ERROR",$P$27)))))),"ERROR")) | W27: =IF($T$27>1,"ERROR",IFERROR(IF(OR(U27="ERROR",V27="ERROR"),"ERROR",IF(OR(NOT(ISNUMBER(U27)),NOT(ISNUMBER(V27))),"UNKNOWN",IF(U27<=0,"NOT_APPLICABLE",V27/U27))),"ERROR")) | X27: =IF($T$27>1,"",IF(OR($R$27="invalid_direct",$S$27="inconsistent"),"",IF($R$27="none","",IF(OR($R$27="unresolved",$R$27="blended_only"),"",IF(ISBLANK($P$27),"",IF($P$27<0,"",$Q$27)))))) | Y27: =IFERROR(IF(ISBLANK($I$27),"UNKNOWN",IF(ISBLANK($J$27),"UNKNOWN",IF($J$27=FALSE,$I$27,IF(ISBLANK($K$27),"UNKNOWN",$I$27/(1+$K$27))))),"ERROR") | Z27: =IFERROR(IF(ISBLANK($I$27),"UNKNOWN",IF(ISBLANK($J$27),"UNKNOWN",IF($J$27=TRUE,$I$27,IF(ISBLANK($K$27),"UNKNOWN",$I$27*(1+$K$27))))),"ERROR") | AA27: =IF($T$27>1,"MULTI_COMPONENT_BEP_NOT_SUPPORTED",IF($R$27="invalid_direct","INVALID_ALLOCATION_CONFIGURATION",IF($S$27="inconsistent","INCONSISTENT_FIXED_COST_BASIS",IF(AND($R$27="component",NOT(ISBLANK($P$27)),$P$27<0),"INVALID_NEGATIVE_COST",IF(U27="ERROR","CALCULATION_ERROR",IF($R$27="blended_only","FIXED_COST_BLENDED_ONLY_NOT_ALLOCATED",IF($R$27="unresolved","UNSUPPORTED_SHARED_COST_ALLOCATION",IF(NOT(ISNUMBER(U27)),"MISSING_DEPENDENCY",IF(AND($R$27="component",ISBLANK($P$27)),"MISSING_DEPENDENCY",IF(AND(U27=0,V27=0),"BREAK_EVEN_UNDEFINED_ZERO_MARGIN_ZERO_FIXED_COST",IF(U27=0,"BREAK_EVEN_UNDEFINED_ZERO_MARGIN",IF(U27<0,"BREAK_EVEN_UNDEFINED_NEGATIVE_MARGIN","NONE"))))))))))))
B28: Fixed Operating Cost (FC) | C28: =V27 | D28: 0 | E28: =IF(ISNUMBER(D28),IF(ISNUMBER(V27),ABS(V27-D28),"N/A"),"N/A") | F28: =IFERROR(IF(ISNUMBER(D28),IF(ISNUMBER(V27),IF(ABS(V27-D28)<=0.01,"PASS","FAIL"),"FAIL"),IF(NOT(ISNUMBER(V27)),IF(V27=D28,"PASS","FAIL"),"FAIL")),"FAIL")
B29: Break-Even Quantity (Q_BEP) | C29: =W27 | D29: 0 | E29: =IF(ISNUMBER(D29),IF(ISNUMBER(W27),ABS(W27-D29),"N/A"),"N/A") | F29: =IFERROR(IF(ISNUMBER(D29),IF(ISNUMBER(W27),IF(ABS(W27-D29)<=0.01,"PASS","FAIL"),"FAIL"),IF(NOT(ISNUMBER(W27)),IF(W27=D29,"PASS","FAIL"),"FAIL")),"FAIL")
B30: Analysis Period Basis | C30: =X27 | E30: =IF(ISNUMBER(D30),IF(ISNUMBER(X27),ABS(X27-D30),"N/A"),"N/A") | F30: =IFERROR(IF(ISNUMBER(D30),IF(ISNUMBER(X27),IF(ABS(X27-D30)<=0.01,"PASS","FAIL"),"FAIL"),IF(NOT(ISNUMBER(X27)),IF(X27=D30,"PASS","FAIL"),"FAIL")),"FAIL")
B31: Module Status Tier | C31: =IF(OR(U27="ERROR",V27="ERROR",W27="ERROR"),"ERROR",IF(OR(U27="UNKNOWN",V27="UNKNOWN",W27="UNKNOWN"),"INCOMPLETE","OK")) | D31: OK | F31: =IF(C31=D31,"PASS","FAIL")
B32: Primary Warning Code (diagnostic) | C32: =AA27 | D32: NONE | F32: =IF(AA27=D32,"PASS","FAIL")
B33: Self-Check: |Q_BEP × CMu − FC| ≤ tol | C33: =IF(NOT(ISNUMBER(W27)),"SKIP",IF(ABS(W27*U27-V27)<=0.01,"PASS","FAIL")) | F33: =IF(C33="FAIL","FAIL","PASS")
B35: TC4. Fixed-cost item exists, amount null
B36: Metric | C36: Excel Result | D36: Python Reference | E36: Difference | F36: PASS / FAIL
B37: Contribution Margin per Unit (CMu) | C37: =U37 | D37: 500 | E37: =IF(ISNUMBER(D37),IF(ISNUMBER(U37),ABS(U37-D37),"N/A"),"N/A") | F37: =IFERROR(IF(ISNUMBER(D37),IF(ISNUMBER(U37),IF(ABS(U37-D37)<=0.01,"PASS","FAIL"),"FAIL"),IF(NOT(ISNUMBER(U37)),IF(U37=D37,"PASS","FAIL"),"FAIL")),"FAIL") | I37: 1000 | J37: FALSE | L37: 400 | M37: 100 | N37: 0 | O37: 0 | Q37: per_month | R37: component | S37: consistent | T37: 1 | U37: =IF($T$37>1,"ERROR",IFERROR(IF(Y37="ERROR","ERROR",IF(OR(NOT(ISNUMBER(Y37)),ISBLANK($L$37),ISBLANK($M$37),ISBLANK($N$37),ISBLANK($O$37)),"UNKNOWN",IF($O$37>0,IF(Z37="ERROR","ERROR",IF(NOT(ISNUMBER(Z37)),"UNKNOWN",Y37-$L$37-$M$37-$N$37*Y37-$O$37*Z37)),Y37-$L$37-$M$37-$N$37*Y37))),"ERROR")) | V37: =IF($T$37>1,"ERROR",IFERROR(IF($R$37="invalid_direct","ERROR",IF($S$37="inconsistent","ERROR",IF($R$37="none",0,IF(OR($R$37="unresolved",$R$37="blended_only"),"UNKNOWN",IF(ISBLANK($P$37),"UNKNOWN",IF($P$37<0,"ERROR",$P$37)))))),"ERROR")) | W37: =IF($T$37>1,"ERROR",IFERROR(IF(OR(U37="ERROR",V37="ERROR"),"ERROR",IF(OR(NOT(ISNUMBER(U37)),NOT(ISNUMBER(V37))),"UNKNOWN",IF(U37<=0,"NOT_APPLICABLE",V37/U37))),"ERROR")) | X37: =IF($T$37>1,"",IF(OR($R$37="invalid_direct",$S$37="inconsistent"),"",IF($R$37="none","",IF(OR($R$37="unresolved",$R$37="blended_only"),"",IF(ISBLANK($P$37),"",IF($P$37<0,"",$Q$37)))))) | Y37: =IFERROR(IF(ISBLANK($I$37),"UNKNOWN",IF(ISBLANK($J$37),"UNKNOWN",IF($J$37=FALSE,$I$37,IF(ISBLANK($K$37),"UNKNOWN",$I$37/(1+$K$37))))),"ERROR") | Z37: =IFERROR(IF(ISBLANK($I$37),"UNKNOWN",IF(ISBLANK($J$37),"UNKNOWN",IF($J$37=TRUE,$I$37,IF(ISBLANK($K$37),"UNKNOWN",$I$37*(1+$K$37))))),"ERROR") | AA37: =IF($T$37>1,"MULTI_COMPONENT_BEP_NOT_SUPPORTED",IF($R$37="invalid_direct","INVALID_ALLOCATION_CONFIGURATION",IF($S$37="inconsistent","INCONSISTENT_FIXED_COST_BASIS",IF(AND($R$37="component",NOT(ISBLANK($P$37)),$P$37<0),"INVALID_NEGATIVE_COST",IF(U37="ERROR","CALCULATION_ERROR",IF($R$37="blended_only","FIXED_COST_BLENDED_ONLY_NOT_ALLOCATED",IF($R$37="unresolved","UNSUPPORTED_SHARED_COST_ALLOCATION",IF(NOT(ISNUMBER(U37)),"MISSING_DEPENDENCY",IF(AND($R$37="component",ISBLANK($P$37)),"MISSING_DEPENDENCY",IF(AND(U37=0,V37=0),"BREAK_EVEN_UNDEFINED_ZERO_MARGIN_ZERO_FIXED_COST",IF(U37=0,"BREAK_EVEN_UNDEFINED_ZERO_MARGIN",IF(U37<0,"BREAK_EVEN_UNDEFINED_NEGATIVE_MARGIN","NONE"))))))))))))
B38: Fixed Operating Cost (FC) | C38: =V37 | D38: UNKNOWN | E38: =IF(ISNUMBER(D38),IF(ISNUMBER(V37),ABS(V37-D38),"N/A"),"N/A") | F38: =IFERROR(IF(ISNUMBER(D38),IF(ISNUMBER(V37),IF(ABS(V37-D38)<=0.01,"PASS","FAIL"),"FAIL"),IF(NOT(ISNUMBER(V37)),IF(V37=D38,"PASS","FAIL"),"FAIL")),"FAIL")
B39: Break-Even Quantity (Q_BEP) | C39: =W37 | D39: UNKNOWN | E39: =IF(ISNUMBER(D39),IF(ISNUMBER(W37),ABS(W37-D39),"N/A"),"N/A") | F39: =IFERROR(IF(ISNUMBER(D39),IF(ISNUMBER(W37),IF(ABS(W37-D39)<=0.01,"PASS","FAIL"),"FAIL"),IF(NOT(ISNUMBER(W37)),IF(W37=D39,"PASS","FAIL"),"FAIL")),"FAIL")
B40: Analysis Period Basis | C40: =X37 | E40: =IF(ISNUMBER(D40),IF(ISNUMBER(X37),ABS(X37-D40),"N/A"),"N/A") | F40: =IFERROR(IF(ISNUMBER(D40),IF(ISNUMBER(X37),IF(ABS(X37-D40)<=0.01,"PASS","FAIL"),"FAIL"),IF(NOT(ISNUMBER(X37)),IF(X37=D40,"PASS","FAIL"),"FAIL")),"FAIL")
B41: Module Status Tier | C41: =IF(OR(U37="ERROR",V37="ERROR",W37="ERROR"),"ERROR",IF(OR(U37="UNKNOWN",V37="UNKNOWN",W37="UNKNOWN"),"INCOMPLETE","OK")) | D41: INCOMPLETE | F41: =IF(C41=D41,"PASS","FAIL")
B42: Primary Warning Code (diagnostic) | C42: =AA37 | D42: MISSING_DEPENDENCY | F42: =IF(AA37=D42,"PASS","FAIL")
B43: Self-Check: |Q_BEP × CMu − FC| ≤ tol | C43: =IF(NOT(ISNUMBER(W37)),"SKIP",IF(ABS(W37*U37-V37)<=0.01,"PASS","FAIL")) | F43: =IF(C43="FAIL","FAIL","PASS")
B45: TC5. CM = 0, FC > 0
B46: Metric | C46: Excel Result | D46: Python Reference | E46: Difference | F46: PASS / FAIL
B47: Contribution Margin per Unit (CMu) | C47: =U47 | D47: 0 | E47: =IF(ISNUMBER(D47),IF(ISNUMBER(U47),ABS(U47-D47),"N/A"),"N/A") | F47: =IFERROR(IF(ISNUMBER(D47),IF(ISNUMBER(U47),IF(ABS(U47-D47)<=0.01,"PASS","FAIL"),"FAIL"),IF(NOT(ISNUMBER(U47)),IF(U47=D47,"PASS","FAIL"),"FAIL")),"FAIL") | I47: 1000 | J47: FALSE | L47: 600 | M47: 400 | N47: 0 | O47: 0 | P47: 50000 | Q47: per_month | R47: component | S47: consistent | T47: 1 | U47: =IF($T$47>1,"ERROR",IFERROR(IF(Y47="ERROR","ERROR",IF(OR(NOT(ISNUMBER(Y47)),ISBLANK($L$47),ISBLANK($M$47),ISBLANK($N$47),ISBLANK($O$47)),"UNKNOWN",IF($O$47>0,IF(Z47="ERROR","ERROR",IF(NOT(ISNUMBER(Z47)),"UNKNOWN",Y47-$L$47-$M$47-$N$47*Y47-$O$47*Z47)),Y47-$L$47-$M$47-$N$47*Y47))),"ERROR")) | V47: =IF($T$47>1,"ERROR",IFERROR(IF($R$47="invalid_direct","ERROR",IF($S$47="inconsistent","ERROR",IF($R$47="none",0,IF(OR($R$47="unresolved",$R$47="blended_only"),"UNKNOWN",IF(ISBLANK($P$47),"UNKNOWN",IF($P$47<0,"ERROR",$P$47)))))),"ERROR")) | W47: =IF($T$47>1,"ERROR",IFERROR(IF(OR(U47="ERROR",V47="ERROR"),"ERROR",IF(OR(NOT(ISNUMBER(U47)),NOT(ISNUMBER(V47))),"UNKNOWN",IF(U47<=0,"NOT_APPLICABLE",V47/U47))),"ERROR")) | X47: =IF($T$47>1,"",IF(OR($R$47="invalid_direct",$S$47="inconsistent"),"",IF($R$47="none","",IF(OR($R$47="unresolved",$R$47="blended_only"),"",IF(ISBLANK($P$47),"",IF($P$47<0,"",$Q$47)))))) | Y47: =IFERROR(IF(ISBLANK($I$47),"UNKNOWN",IF(ISBLANK($J$47),"UNKNOWN",IF($J$47=FALSE,$I$47,IF(ISBLANK($K$47),"UNKNOWN",$I$47/(1+$K$47))))),"ERROR") | Z47: =IFERROR(IF(ISBLANK($I$47),"UNKNOWN",IF(ISBLANK($J$47),"UNKNOWN",IF($J$47=TRUE,$I$47,IF(ISBLANK($K$47),"UNKNOWN",$I$47*(1+$K$47))))),"ERROR") | AA47: =IF($T$47>1,"MULTI_COMPONENT_BEP_NOT_SUPPORTED",IF($R$47="invalid_direct","INVALID_ALLOCATION_CONFIGURATION",IF($S$47="inconsistent","INCONSISTENT_FIXED_COST_BASIS",IF(AND($R$47="component",NOT(ISBLANK($P$47)),$P$47<0),"INVALID_NEGATIVE_COST",IF(U47="ERROR","CALCULATION_ERROR",IF($R$47="blended_only","FIXED_COST_BLENDED_ONLY_NOT_ALLOCATED",IF($R$47="unresolved","UNSUPPORTED_SHARED_COST_ALLOCATION",IF(NOT(ISNUMBER(U47)),"MISSING_DEPENDENCY",IF(AND($R$47="component",ISBLANK($P$47)),"MISSING_DEPENDENCY",IF(AND(U47=0,V47=0),"BREAK_EVEN_UNDEFINED_ZERO_MARGIN_ZERO_FIXED_COST",IF(U47=0,"BREAK_EVEN_UNDEFINED_ZERO_MARGIN",IF(U47<0,"BREAK_EVEN_UNDEFINED_NEGATIVE_MARGIN","NONE"))))))))))))
B48: Fixed Operating Cost (FC) | C48: =V47 | D48: 50000 | E48: =IF(ISNUMBER(D48),IF(ISNUMBER(V47),ABS(V47-D48),"N/A"),"N/A") | F48: =IFERROR(IF(ISNUMBER(D48),IF(ISNUMBER(V47),IF(ABS(V47-D48)<=0.01,"PASS","FAIL"),"FAIL"),IF(NOT(ISNUMBER(V47)),IF(V47=D48,"PASS","FAIL"),"FAIL")),"FAIL")
B49: Break-Even Quantity (Q_BEP) | C49: =W47 | D49: NOT_APPLICABLE | E49: =IF(ISNUMBER(D49),IF(ISNUMBER(W47),ABS(W47-D49),"N/A"),"N/A") | F49: =IFERROR(IF(ISNUMBER(D49),IF(ISNUMBER(W47),IF(ABS(W47-D49)<=0.01,"PASS","FAIL"),"FAIL"),IF(NOT(ISNUMBER(W47)),IF(W47=D49,"PASS","FAIL"),"FAIL")),"FAIL")
B50: Analysis Period Basis | C50: =X47 | D50: per_month | E50: =IF(ISNUMBER(D50),IF(ISNUMBER(X47),ABS(X47-D50),"N/A"),"N/A") | F50: =IFERROR(IF(ISNUMBER(D50),IF(ISNUMBER(X47),IF(ABS(X47-D50)<=0.01,"PASS","FAIL"),"FAIL"),IF(NOT(ISNUMBER(X47)),IF(X47=D50,"PASS","FAIL"),"FAIL")),"FAIL")
B51: Module Status Tier | C51: =IF(OR(U47="ERROR",V47="ERROR",W47="ERROR"),"ERROR",IF(OR(U47="UNKNOWN",V47="UNKNOWN",W47="UNKNOWN"),"INCOMPLETE","OK")) | D51: OK | F51: =IF(C51=D51,"PASS","FAIL")
B52: Primary Warning Code (diagnostic) | C52: =AA47 | D52: BREAK_EVEN_UNDEFINED_ZERO_MARGIN | F52: =IF(AA47=D52,"PASS","FAIL")
B53: Self-Check: |Q_BEP × CMu − FC| ≤ tol | C53: =IF(NOT(ISNUMBER(W47)),"SKIP",IF(ABS(W47*U47-V47)<=0.01,"PASS","FAIL")) | F53: =IF(C53="FAIL","FAIL","PASS")
B55: TC6. CM < 0, FC > 0
B56: Metric | C56: Excel Result | D56: Python Reference | E56: Difference | F56: PASS / FAIL
B57: Contribution Margin per Unit (CMu) | C57: =U57 | D57: -100 | E57: =IF(ISNUMBER(D57),IF(ISNUMBER(U57),ABS(U57-D57),"N/A"),"N/A") | F57: =IFERROR(IF(ISNUMBER(D57),IF(ISNUMBER(U57),IF(ABS(U57-D57)<=0.01,"PASS","FAIL"),"FAIL"),IF(NOT(ISNUMBER(U57)),IF(U57=D57,"PASS","FAIL"),"FAIL")),"FAIL") | I57: 1000 | J57: FALSE | L57: 700 | M57: 400 | N57: 0 | O57: 0 | P57: 50000 | Q57: per_month | R57: component | S57: consistent | T57: 1 | U57: =IF($T$57>1,"ERROR",IFERROR(IF(Y57="ERROR","ERROR",IF(OR(NOT(ISNUMBER(Y57)),ISBLANK($L$57),ISBLANK($M$57),ISBLANK($N$57),ISBLANK($O$57)),"UNKNOWN",IF($O$57>0,IF(Z57="ERROR","ERROR",IF(NOT(ISNUMBER(Z57)),"UNKNOWN",Y57-$L$57-$M$57-$N$57*Y57-$O$57*Z57)),Y57-$L$57-$M$57-$N$57*Y57))),"ERROR")) | V57: =IF($T$57>1,"ERROR",IFERROR(IF($R$57="invalid_direct","ERROR",IF($S$57="inconsistent","ERROR",IF($R$57="none",0,IF(OR($R$57="unresolved",$R$57="blended_only"),"UNKNOWN",IF(ISBLANK($P$57),"UNKNOWN",IF($P$57<0,"ERROR",$P$57)))))),"ERROR")) | W57: =IF($T$57>1,"ERROR",IFERROR(IF(OR(U57="ERROR",V57="ERROR"),"ERROR",IF(OR(NOT(ISNUMBER(U57)),NOT(ISNUMBER(V57))),"UNKNOWN",IF(U57<=0,"NOT_APPLICABLE",V57/U57))),"ERROR")) | X57: =IF($T$57>1,"",IF(OR($R$57="invalid_direct",$S$57="inconsistent"),"",IF($R$57="none","",IF(OR($R$57="unresolved",$R$57="blended_only"),"",IF(ISBLANK($P$57),"",IF($P$57<0,"",$Q$57)))))) | Y57: =IFERROR(IF(ISBLANK($I$57),"UNKNOWN",IF(ISBLANK($J$57),"UNKNOWN",IF($J$57=FALSE,$I$57,IF(ISBLANK($K$57),"UNKNOWN",$I$57/(1+$K$57))))),"ERROR") | Z57: =IFERROR(IF(ISBLANK($I$57),"UNKNOWN",IF(ISBLANK($J$57),"UNKNOWN",IF($J$57=TRUE,$I$57,IF(ISBLANK($K$57),"UNKNOWN",$I$57*(1+$K$57))))),"ERROR") | AA57: =IF($T$57>1,"MULTI_COMPONENT_BEP_NOT_SUPPORTED",IF($R$57="invalid_direct","INVALID_ALLOCATION_CONFIGURATION",IF($S$57="inconsistent","INCONSISTENT_FIXED_COST_BASIS",IF(AND($R$57="component",NOT(ISBLANK($P$57)),$P$57<0),"INVALID_NEGATIVE_COST",IF(U57="ERROR","CALCULATION_ERROR",IF($R$57="blended_only","FIXED_COST_BLENDED_ONLY_NOT_ALLOCATED",IF($R$57="unresolved","UNSUPPORTED_SHARED_COST_ALLOCATION",IF(NOT(ISNUMBER(U57)),"MISSING_DEPENDENCY",IF(AND($R$57="component",ISBLANK($P$57)),"MISSING_DEPENDENCY",IF(AND(U57=0,V57=0),"BREAK_EVEN_UNDEFINED_ZERO_MARGIN_ZERO_FIXED_COST",IF(U57=0,"BREAK_EVEN_UNDEFINED_ZERO_MARGIN",IF(U57<0,"BREAK_EVEN_UNDEFINED_NEGATIVE_MARGIN","NONE"))))))))))))
B58: Fixed Operating Cost (FC) | C58: =V57 | D58: 50000 | E58: =IF(ISNUMBER(D58),IF(ISNUMBER(V57),ABS(V57-D58),"N/A"),"N/A") | F58: =IFERROR(IF(ISNUMBER(D58),IF(ISNUMBER(V57),IF(ABS(V57-D58)<=0.01,"PASS","FAIL"),"FAIL"),IF(NOT(ISNUMBER(V57)),IF(V57=D58,"PASS","FAIL"),"FAIL")),"FAIL")
B59: Break-Even Quantity (Q_BEP) | C59: =W57 | D59: NOT_APPLICABLE | E59: =IF(ISNUMBER(D59),IF(ISNUMBER(W57),ABS(W57-D59),"N/A"),"N/A") | F59: =IFERROR(IF(ISNUMBER(D59),IF(ISNUMBER(W57),IF(ABS(W57-D59)<=0.01,"PASS","FAIL"),"FAIL"),IF(NOT(ISNUMBER(W57)),IF(W57=D59,"PASS","FAIL"),"FAIL")),"FAIL")
B60: Analysis Period Basis | C60: =X57 | D60: per_month | E60: =IF(ISNUMBER(D60),IF(ISNUMBER(X57),ABS(X57-D60),"N/A"),"N/A") | F60: =IFERROR(IF(ISNUMBER(D60),IF(ISNUMBER(X57),IF(ABS(X57-D60)<=0.01,"PASS","FAIL"),"FAIL"),IF(NOT(ISNUMBER(X57)),IF(X57=D60,"PASS","FAIL"),"FAIL")),"FAIL")
B61: Module Status Tier | C61: =IF(OR(U57="ERROR",V57="ERROR",W57="ERROR"),"ERROR",IF(OR(U57="UNKNOWN",V57="UNKNOWN",W57="UNKNOWN"),"INCOMPLETE","OK")) | D61: OK | F61: =IF(C61=D61,"PASS","FAIL")
B62: Primary Warning Code (diagnostic) | C62: =AA57 | D62: BREAK_EVEN_UNDEFINED_NEGATIVE_MARGIN | F62: =IF(AA57=D62,"PASS","FAIL")
B63: Self-Check: |Q_BEP × CMu − FC| ≤ tol | C63: =IF(NOT(ISNUMBER(W57)),"SKIP",IF(ABS(W57*U57-V57)<=0.01,"PASS","FAIL")) | F63: =IF(C63="FAIL","FAIL","PASS")
B65: TC7. VAT-inclusive display
B66: Metric | C66: Excel Result | D66: Python Reference | E66: Difference | F66: PASS / FAIL
B67: Contribution Margin per Unit (CMu) | C67: =U67 | D67: 500 | E67: =IF(ISNUMBER(D67),IF(ISNUMBER(U67),ABS(U67-D67),"N/A"),"N/A") | F67: =IFERROR(IF(ISNUMBER(D67),IF(ISNUMBER(U67),IF(ABS(U67-D67)<=0.01,"PASS","FAIL"),"FAIL"),IF(NOT(ISNUMBER(U67)),IF(U67=D67,"PASS","FAIL"),"FAIL")),"FAIL") | I67: 1100 | J67: TRUE | K67: 0.1 | L67: 400 | M67: 100 | N67: 0 | O67: 0 | P67: 50000 | Q67: per_month | R67: component | S67: consistent | T67: 1 | U67: =IF($T$67>1,"ERROR",IFERROR(IF(Y67="ERROR","ERROR",IF(OR(NOT(ISNUMBER(Y67)),ISBLANK($L$67),ISBLANK($M$67),ISBLANK($N$67),ISBLANK($O$67)),"UNKNOWN",IF($O$67>0,IF(Z67="ERROR","ERROR",IF(NOT(ISNUMBER(Z67)),"UNKNOWN",Y67-$L$67-$M$67-$N$67*Y67-$O$67*Z67)),Y67-$L$67-$M$67-$N$67*Y67))),"ERROR")) | V67: =IF($T$67>1,"ERROR",IFERROR(IF($R$67="invalid_direct","ERROR",IF($S$67="inconsistent","ERROR",IF($R$67="none",0,IF(OR($R$67="unresolved",$R$67="blended_only"),"UNKNOWN",IF(ISBLANK($P$67),"UNKNOWN",IF($P$67<0,"ERROR",$P$67)))))),"ERROR")) | W67: =IF($T$67>1,"ERROR",IFERROR(IF(OR(U67="ERROR",V67="ERROR"),"ERROR",IF(OR(NOT(ISNUMBER(U67)),NOT(ISNUMBER(V67))),"UNKNOWN",IF(U67<=0,"NOT_APPLICABLE",V67/U67))),"ERROR")) | X67: =IF($T$67>1,"",IF(OR($R$67="invalid_direct",$S$67="inconsistent"),"",IF($R$67="none","",IF(OR($R$67="unresolved",$R$67="blended_only"),"",IF(ISBLANK($P$67),"",IF($P$67<0,"",$Q$67)))))) | Y67: =IFERROR(IF(ISBLANK($I$67),"UNKNOWN",IF(ISBLANK($J$67),"UNKNOWN",IF($J$67=FALSE,$I$67,IF(ISBLANK($K$67),"UNKNOWN",$I$67/(1+$K$67))))),"ERROR") | Z67: =IFERROR(IF(ISBLANK($I$67),"UNKNOWN",IF(ISBLANK($J$67),"UNKNOWN",IF($J$67=TRUE,$I$67,IF(ISBLANK($K$67),"UNKNOWN",$I$67*(1+$K$67))))),"ERROR") | AA67: =IF($T$67>1,"MULTI_COMPONENT_BEP_NOT_SUPPORTED",IF($R$67="invalid_direct","INVALID_ALLOCATION_CONFIGURATION",IF($S$67="inconsistent","INCONSISTENT_FIXED_COST_BASIS",IF(AND($R$67="component",NOT(ISBLANK($P$67)),$P$67<0),"INVALID_NEGATIVE_COST",IF(U67="ERROR","CALCULATION_ERROR",IF($R$67="blended_only","FIXED_COST_BLENDED_ONLY_NOT_ALLOCATED",IF($R$67="unresolved","UNSUPPORTED_SHARED_COST_ALLOCATION",IF(NOT(ISNUMBER(U67)),"MISSING_DEPENDENCY",IF(AND($R$67="component",ISBLANK($P$67)),"MISSING_DEPENDENCY",IF(AND(U67=0,V67=0),"BREAK_EVEN_UNDEFINED_ZERO_MARGIN_ZERO_FIXED_COST",IF(U67=0,"BREAK_EVEN_UNDEFINED_ZERO_MARGIN",IF(U67<0,"BREAK_EVEN_UNDEFINED_NEGATIVE_MARGIN","NONE"))))))))))))
B68: Fixed Operating Cost (FC) | C68: =V67 | D68: 50000 | E68: =IF(ISNUMBER(D68),IF(ISNUMBER(V67),ABS(V67-D68),"N/A"),"N/A") | F68: =IFERROR(IF(ISNUMBER(D68),IF(ISNUMBER(V67),IF(ABS(V67-D68)<=0.01,"PASS","FAIL"),"FAIL"),IF(NOT(ISNUMBER(V67)),IF(V67=D68,"PASS","FAIL"),"FAIL")),"FAIL")
B69: Break-Even Quantity (Q_BEP) | C69: =W67 | D69: 100 | E69: =IF(ISNUMBER(D69),IF(ISNUMBER(W67),ABS(W67-D69),"N/A"),"N/A") | F69: =IFERROR(IF(ISNUMBER(D69),IF(ISNUMBER(W67),IF(ABS(W67-D69)<=0.01,"PASS","FAIL"),"FAIL"),IF(NOT(ISNUMBER(W67)),IF(W67=D69,"PASS","FAIL"),"FAIL")),"FAIL")
B70: Analysis Period Basis | C70: =X67 | D70: per_month | E70: =IF(ISNUMBER(D70),IF(ISNUMBER(X67),ABS(X67-D70),"N/A"),"N/A") | F70: =IFERROR(IF(ISNUMBER(D70),IF(ISNUMBER(X67),IF(ABS(X67-D70)<=0.01,"PASS","FAIL"),"FAIL"),IF(NOT(ISNUMBER(X67)),IF(X67=D70,"PASS","FAIL"),"FAIL")),"FAIL")
B71: Module Status Tier | C71: =IF(OR(U67="ERROR",V67="ERROR",W67="ERROR"),"ERROR",IF(OR(U67="UNKNOWN",V67="UNKNOWN",W67="UNKNOWN"),"INCOMPLETE","OK")) | D71: OK | F71: =IF(C71=D71,"PASS","FAIL")
B72: Primary Warning Code (diagnostic) | C72: =AA67 | D72: NONE | F72: =IF(AA67=D72,"PASS","FAIL")
B73: Self-Check: |Q_BEP × CMu − FC| ≤ tol | C73: =IF(NOT(ISNUMBER(W67)),"SKIP",IF(ABS(W67*U67-V67)<=0.01,"PASS","FAIL")) | F73: =IF(C73="FAIL","FAIL","PASS")
B75: TC8. VAT-exclusive display, same economics as TC7
B76: Metric | C76: Excel Result | D76: Python Reference | E76: Difference | F76: PASS / FAIL
B77: Contribution Margin per Unit (CMu) | C77: =U77 | D77: 500 | E77: =IF(ISNUMBER(D77),IF(ISNUMBER(U77),ABS(U77-D77),"N/A"),"N/A") | F77: =IFERROR(IF(ISNUMBER(D77),IF(ISNUMBER(U77),IF(ABS(U77-D77)<=0.01,"PASS","FAIL"),"FAIL"),IF(NOT(ISNUMBER(U77)),IF(U77=D77,"PASS","FAIL"),"FAIL")),"FAIL") | I77: 1000 | J77: FALSE | K77: 0.1 | L77: 400 | M77: 100 | N77: 0 | O77: 0 | P77: 50000 | Q77: per_month | R77: component | S77: consistent | T77: 1 | U77: =IF($T$77>1,"ERROR",IFERROR(IF(Y77="ERROR","ERROR",IF(OR(NOT(ISNUMBER(Y77)),ISBLANK($L$77),ISBLANK($M$77),ISBLANK($N$77),ISBLANK($O$77)),"UNKNOWN",IF($O$77>0,IF(Z77="ERROR","ERROR",IF(NOT(ISNUMBER(Z77)),"UNKNOWN",Y77-$L$77-$M$77-$N$77*Y77-$O$77*Z77)),Y77-$L$77-$M$77-$N$77*Y77))),"ERROR")) | V77: =IF($T$77>1,"ERROR",IFERROR(IF($R$77="invalid_direct","ERROR",IF($S$77="inconsistent","ERROR",IF($R$77="none",0,IF(OR($R$77="unresolved",$R$77="blended_only"),"UNKNOWN",IF(ISBLANK($P$77),"UNKNOWN",IF($P$77<0,"ERROR",$P$77)))))),"ERROR")) | W77: =IF($T$77>1,"ERROR",IFERROR(IF(OR(U77="ERROR",V77="ERROR"),"ERROR",IF(OR(NOT(ISNUMBER(U77)),NOT(ISNUMBER(V77))),"UNKNOWN",IF(U77<=0,"NOT_APPLICABLE",V77/U77))),"ERROR")) | X77: =IF($T$77>1,"",IF(OR($R$77="invalid_direct",$S$77="inconsistent"),"",IF($R$77="none","",IF(OR($R$77="unresolved",$R$77="blended_only"),"",IF(ISBLANK($P$77),"",IF($P$77<0,"",$Q$77)))))) | Y77: =IFERROR(IF(ISBLANK($I$77),"UNKNOWN",IF(ISBLANK($J$77),"UNKNOWN",IF($J$77=FALSE,$I$77,IF(ISBLANK($K$77),"UNKNOWN",$I$77/(1+$K$77))))),"ERROR") | Z77: =IFERROR(IF(ISBLANK($I$77),"UNKNOWN",IF(ISBLANK($J$77),"UNKNOWN",IF($J$77=TRUE,$I$77,IF(ISBLANK($K$77),"UNKNOWN",$I$77*(1+$K$77))))),"ERROR") | AA77: =IF($T$77>1,"MULTI_COMPONENT_BEP_NOT_SUPPORTED",IF($R$77="invalid_direct","INVALID_ALLOCATION_CONFIGURATION",IF($S$77="inconsistent","INCONSISTENT_FIXED_COST_BASIS",IF(AND($R$77="component",NOT(ISBLANK($P$77)),$P$77<0),"INVALID_NEGATIVE_COST",IF(U77="ERROR","CALCULATION_ERROR",IF($R$77="blended_only","FIXED_COST_BLENDED_ONLY_NOT_ALLOCATED",IF($R$77="unresolved","UNSUPPORTED_SHARED_COST_ALLOCATION",IF(NOT(ISNUMBER(U77)),"MISSING_DEPENDENCY",IF(AND($R$77="component",ISBLANK($P$77)),"MISSING_DEPENDENCY",IF(AND(U77=0,V77=0),"BREAK_EVEN_UNDEFINED_ZERO_MARGIN_ZERO_FIXED_COST",IF(U77=0,"BREAK_EVEN_UNDEFINED_ZERO_MARGIN",IF(U77<0,"BREAK_EVEN_UNDEFINED_NEGATIVE_MARGIN","NONE"))))))))))))
B78: Fixed Operating Cost (FC) | C78: =V77 | D78: 50000 | E78: =IF(ISNUMBER(D78),IF(ISNUMBER(V77),ABS(V77-D78),"N/A"),"N/A") | F78: =IFERROR(IF(ISNUMBER(D78),IF(ISNUMBER(V77),IF(ABS(V77-D78)<=0.01,"PASS","FAIL"),"FAIL"),IF(NOT(ISNUMBER(V77)),IF(V77=D78,"PASS","FAIL"),"FAIL")),"FAIL")
B79: Break-Even Quantity (Q_BEP) | C79: =W77 | D79: 100 | E79: =IF(ISNUMBER(D79),IF(ISNUMBER(W77),ABS(W77-D79),"N/A"),"N/A") | F79: =IFERROR(IF(ISNUMBER(D79),IF(ISNUMBER(W77),IF(ABS(W77-D79)<=0.01,"PASS","FAIL"),"FAIL"),IF(NOT(ISNUMBER(W77)),IF(W77=D79,"PASS","FAIL"),"FAIL")),"FAIL")
B80: Analysis Period Basis | C80: =X77 | D80: per_month | E80: =IF(ISNUMBER(D80),IF(ISNUMBER(X77),ABS(X77-D80),"N/A"),"N/A") | F80: =IFERROR(IF(ISNUMBER(D80),IF(ISNUMBER(X77),IF(ABS(X77-D80)<=0.01,"PASS","FAIL"),"FAIL"),IF(NOT(ISNUMBER(X77)),IF(X77=D80,"PASS","FAIL"),"FAIL")),"FAIL")
B81: Module Status Tier | C81: =IF(OR(U77="ERROR",V77="ERROR",W77="ERROR"),"ERROR",IF(OR(U77="UNKNOWN",V77="UNKNOWN",W77="UNKNOWN"),"INCOMPLETE","OK")) | D81: OK | F81: =IF(C81=D81,"PASS","FAIL")
B82: Primary Warning Code (diagnostic) | C82: =AA77 | D82: NONE | F82: =IF(AA77=D82,"PASS","FAIL")
B83: Self-Check: |Q_BEP × CMu − FC| ≤ tol | C83: =IF(NOT(ISNUMBER(W77)),"SKIP",IF(ABS(W77*U77-V77)<=0.01,"PASS","FAIL")) | F83: =IF(C83="FAIL","FAIL","PASS")
B85: TC9. Net-sales fee
B86: Metric | C86: Excel Result | D86: Python Reference | E86: Difference | F86: PASS / FAIL
B87: Contribution Margin per Unit (CMu) | C87: =U87 | D87: 700 | E87: =IF(ISNUMBER(D87),IF(ISNUMBER(U87),ABS(U87-D87),"N/A"),"N/A") | F87: =IFERROR(IF(ISNUMBER(D87),IF(ISNUMBER(U87),IF(ABS(U87-D87)<=0.01,"PASS","FAIL"),"FAIL"),IF(NOT(ISNUMBER(U87)),IF(U87=D87,"PASS","FAIL"),"FAIL")),"FAIL") | I87: 1000 | J87: FALSE | L87: 200 | M87: 0 | N87: 0.1 | O87: 0 | P87: 70000 | Q87: per_month | R87: component | S87: consistent | T87: 1 | U87: =IF($T$87>1,"ERROR",IFERROR(IF(Y87="ERROR","ERROR",IF(OR(NOT(ISNUMBER(Y87)),ISBLANK($L$87),ISBLANK($M$87),ISBLANK($N$87),ISBLANK($O$87)),"UNKNOWN",IF($O$87>0,IF(Z87="ERROR","ERROR",IF(NOT(ISNUMBER(Z87)),"UNKNOWN",Y87-$L$87-$M$87-$N$87*Y87-$O$87*Z87)),Y87-$L$87-$M$87-$N$87*Y87))),"ERROR")) | V87: =IF($T$87>1,"ERROR",IFERROR(IF($R$87="invalid_direct","ERROR",IF($S$87="inconsistent","ERROR",IF($R$87="none",0,IF(OR($R$87="unresolved",$R$87="blended_only"),"UNKNOWN",IF(ISBLANK($P$87),"UNKNOWN",IF($P$87<0,"ERROR",$P$87)))))),"ERROR")) | W87: =IF($T$87>1,"ERROR",IFERROR(IF(OR(U87="ERROR",V87="ERROR"),"ERROR",IF(OR(NOT(ISNUMBER(U87)),NOT(ISNUMBER(V87))),"UNKNOWN",IF(U87<=0,"NOT_APPLICABLE",V87/U87))),"ERROR")) | X87: =IF($T$87>1,"",IF(OR($R$87="invalid_direct",$S$87="inconsistent"),"",IF($R$87="none","",IF(OR($R$87="unresolved",$R$87="blended_only"),"",IF(ISBLANK($P$87),"",IF($P$87<0,"",$Q$87)))))) | Y87: =IFERROR(IF(ISBLANK($I$87),"UNKNOWN",IF(ISBLANK($J$87),"UNKNOWN",IF($J$87=FALSE,$I$87,IF(ISBLANK($K$87),"UNKNOWN",$I$87/(1+$K$87))))),"ERROR") | Z87: =IFERROR(IF(ISBLANK($I$87),"UNKNOWN",IF(ISBLANK($J$87),"UNKNOWN",IF($J$87=TRUE,$I$87,IF(ISBLANK($K$87),"UNKNOWN",$I$87*(1+$K$87))))),"ERROR") | AA87: =IF($T$87>1,"MULTI_COMPONENT_BEP_NOT_SUPPORTED",IF($R$87="invalid_direct","INVALID_ALLOCATION_CONFIGURATION",IF($S$87="inconsistent","INCONSISTENT_FIXED_COST_BASIS",IF(AND($R$87="component",NOT(ISBLANK($P$87)),$P$87<0),"INVALID_NEGATIVE_COST",IF(U87="ERROR","CALCULATION_ERROR",IF($R$87="blended_only","FIXED_COST_BLENDED_ONLY_NOT_ALLOCATED",IF($R$87="unresolved","UNSUPPORTED_SHARED_COST_ALLOCATION",IF(NOT(ISNUMBER(U87)),"MISSING_DEPENDENCY",IF(AND($R$87="component",ISBLANK($P$87)),"MISSING_DEPENDENCY",IF(AND(U87=0,V87=0),"BREAK_EVEN_UNDEFINED_ZERO_MARGIN_ZERO_FIXED_COST",IF(U87=0,"BREAK_EVEN_UNDEFINED_ZERO_MARGIN",IF(U87<0,"BREAK_EVEN_UNDEFINED_NEGATIVE_MARGIN","NONE"))))))))))))
B88: Fixed Operating Cost (FC) | C88: =V87 | D88: 70000 | E88: =IF(ISNUMBER(D88),IF(ISNUMBER(V87),ABS(V87-D88),"N/A"),"N/A") | F88: =IFERROR(IF(ISNUMBER(D88),IF(ISNUMBER(V87),IF(ABS(V87-D88)<=0.01,"PASS","FAIL"),"FAIL"),IF(NOT(ISNUMBER(V87)),IF(V87=D88,"PASS","FAIL"),"FAIL")),"FAIL")
B89: Break-Even Quantity (Q_BEP) | C89: =W87 | D89: 100 | E89: =IF(ISNUMBER(D89),IF(ISNUMBER(W87),ABS(W87-D89),"N/A"),"N/A") | F89: =IFERROR(IF(ISNUMBER(D89),IF(ISNUMBER(W87),IF(ABS(W87-D89)<=0.01,"PASS","FAIL"),"FAIL"),IF(NOT(ISNUMBER(W87)),IF(W87=D89,"PASS","FAIL"),"FAIL")),"FAIL")
B90: Analysis Period Basis | C90: =X87 | D90: per_month | E90: =IF(ISNUMBER(D90),IF(ISNUMBER(X87),ABS(X87-D90),"N/A"),"N/A") | F90: =IFERROR(IF(ISNUMBER(D90),IF(ISNUMBER(X87),IF(ABS(X87-D90)<=0.01,"PASS","FAIL"),"FAIL"),IF(NOT(ISNUMBER(X87)),IF(X87=D90,"PASS","FAIL"),"FAIL")),"FAIL")
B91: Module Status Tier | C91: =IF(OR(U87="ERROR",V87="ERROR",W87="ERROR"),"ERROR",IF(OR(U87="UNKNOWN",V87="UNKNOWN",W87="UNKNOWN"),"INCOMPLETE","OK")) | D91: OK | F91: =IF(C91=D91,"PASS","FAIL")
B92: Primary Warning Code (diagnostic) | C92: =AA87 | D92: NONE | F92: =IF(AA87=D92,"PASS","FAIL")
B93: Self-Check: |Q_BEP × CMu − FC| ≤ tol | C93: =IF(NOT(ISNUMBER(W87)),"SKIP",IF(ABS(W87*U87-V87)<=0.01,"PASS","FAIL")) | F93: =IF(C93="FAIL","FAIL","PASS")
B95: TC10. Gross-payment fee
B96: Metric | C96: Excel Result | D96: Python Reference | E96: Difference | F96: PASS / FAIL
B97: Contribution Margin per Unit (CMu) | C97: =U97 | D97: 945 | E97: =IF(ISNUMBER(D97),IF(ISNUMBER(U97),ABS(U97-D97),"N/A"),"N/A") | F97: =IFERROR(IF(ISNUMBER(D97),IF(ISNUMBER(U97),IF(ABS(U97-D97)<=0.01,"PASS","FAIL"),"FAIL"),IF(NOT(ISNUMBER(U97)),IF(U97=D97,"PASS","FAIL"),"FAIL")),"FAIL") | I97: 1000 | J97: FALSE | K97: 0.1 | L97: 0 | M97: 0 | N97: 0 | O97: 0.05 | P97: 94500 | Q97: per_month | R97: component | S97: consistent | T97: 1 | U97: =IF($T$97>1,"ERROR",IFERROR(IF(Y97="ERROR","ERROR",IF(OR(NOT(ISNUMBER(Y97)),ISBLANK($L$97),ISBLANK($M$97),ISBLANK($N$97),ISBLANK($O$97)),"UNKNOWN",IF($O$97>0,IF(Z97="ERROR","ERROR",IF(NOT(ISNUMBER(Z97)),"UNKNOWN",Y97-$L$97-$M$97-$N$97*Y97-$O$97*Z97)),Y97-$L$97-$M$97-$N$97*Y97))),"ERROR")) | V97: =IF($T$97>1,"ERROR",IFERROR(IF($R$97="invalid_direct","ERROR",IF($S$97="inconsistent","ERROR",IF($R$97="none",0,IF(OR($R$97="unresolved",$R$97="blended_only"),"UNKNOWN",IF(ISBLANK($P$97),"UNKNOWN",IF($P$97<0,"ERROR",$P$97)))))),"ERROR")) | W97: =IF($T$97>1,"ERROR",IFERROR(IF(OR(U97="ERROR",V97="ERROR"),"ERROR",IF(OR(NOT(ISNUMBER(U97)),NOT(ISNUMBER(V97))),"UNKNOWN",IF(U97<=0,"NOT_APPLICABLE",V97/U97))),"ERROR")) | X97: =IF($T$97>1,"",IF(OR($R$97="invalid_direct",$S$97="inconsistent"),"",IF($R$97="none","",IF(OR($R$97="unresolved",$R$97="blended_only"),"",IF(ISBLANK($P$97),"",IF($P$97<0,"",$Q$97)))))) | Y97: =IFERROR(IF(ISBLANK($I$97),"UNKNOWN",IF(ISBLANK($J$97),"UNKNOWN",IF($J$97=FALSE,$I$97,IF(ISBLANK($K$97),"UNKNOWN",$I$97/(1+$K$97))))),"ERROR") | Z97: =IFERROR(IF(ISBLANK($I$97),"UNKNOWN",IF(ISBLANK($J$97),"UNKNOWN",IF($J$97=TRUE,$I$97,IF(ISBLANK($K$97),"UNKNOWN",$I$97*(1+$K$97))))),"ERROR") | AA97: =IF($T$97>1,"MULTI_COMPONENT_BEP_NOT_SUPPORTED",IF($R$97="invalid_direct","INVALID_ALLOCATION_CONFIGURATION",IF($S$97="inconsistent","INCONSISTENT_FIXED_COST_BASIS",IF(AND($R$97="component",NOT(ISBLANK($P$97)),$P$97<0),"INVALID_NEGATIVE_COST",IF(U97="ERROR","CALCULATION_ERROR",IF($R$97="blended_only","FIXED_COST_BLENDED_ONLY_NOT_ALLOCATED",IF($R$97="unresolved","UNSUPPORTED_SHARED_COST_ALLOCATION",IF(NOT(ISNUMBER(U97)),"MISSING_DEPENDENCY",IF(AND($R$97="component",ISBLANK($P$97)),"MISSING_DEPENDENCY",IF(AND(U97=0,V97=0),"BREAK_EVEN_UNDEFINED_ZERO_MARGIN_ZERO_FIXED_COST",IF(U97=0,"BREAK_EVEN_UNDEFINED_ZERO_MARGIN",IF(U97<0,"BREAK_EVEN_UNDEFINED_NEGATIVE_MARGIN","NONE"))))))))))))
B98: Fixed Operating Cost (FC) | C98: =V97 | D98: 94500 | E98: =IF(ISNUMBER(D98),IF(ISNUMBER(V97),ABS(V97-D98),"N/A"),"N/A") | F98: =IFERROR(IF(ISNUMBER(D98),IF(ISNUMBER(V97),IF(ABS(V97-D98)<=0.01,"PASS","FAIL"),"FAIL"),IF(NOT(ISNUMBER(V97)),IF(V97=D98,"PASS","FAIL"),"FAIL")),"FAIL")
B99: Break-Even Quantity (Q_BEP) | C99: =W97 | D99: 100 | E99: =IF(ISNUMBER(D99),IF(ISNUMBER(W97),ABS(W97-D99),"N/A"),"N/A") | F99: =IFERROR(IF(ISNUMBER(D99),IF(ISNUMBER(W97),IF(ABS(W97-D99)<=0.01,"PASS","FAIL"),"FAIL"),IF(NOT(ISNUMBER(W97)),IF(W97=D99,"PASS","FAIL"),"FAIL")),"FAIL")
B100: Analysis Period Basis | C100: =X97 | D100: per_month | E100: =IF(ISNUMBER(D100),IF(ISNUMBER(X97),ABS(X97-D100),"N/A"),"N/A") | F100: =IFERROR(IF(ISNUMBER(D100),IF(ISNUMBER(X97),IF(ABS(X97-D100)<=0.01,"PASS","FAIL"),"FAIL"),IF(NOT(ISNUMBER(X97)),IF(X97=D100,"PASS","FAIL"),"FAIL")),"FAIL")
B101: Module Status Tier | C101: =IF(OR(U97="ERROR",V97="ERROR",W97="ERROR"),"ERROR",IF(OR(U97="UNKNOWN",V97="UNKNOWN",W97="UNKNOWN"),"INCOMPLETE","OK")) | D101: OK | F101: =IF(C101=D101,"PASS","FAIL")
B102: Primary Warning Code (diagnostic) | C102: =AA97 | D102: NONE | F102: =IF(AA97=D102,"PASS","FAIL")
B103: Self-Check: |Q_BEP × CMu − FC| ≤ tol | C103: =IF(NOT(ISNUMBER(W97)),"SKIP",IF(ABS(W97*U97-V97)<=0.01,"PASS","FAIL")) | F103: =IF(C103="FAIL","FAIL","PASS")
B105: TC11. v UNKNOWN, not needed (a=0)
B106: Metric | C106: Excel Result | D106: Python Reference | E106: Difference | F106: PASS / FAIL
B107: Contribution Margin per Unit (CMu) | C107: =U107 | D107: 600 | E107: =IF(ISNUMBER(D107),IF(ISNUMBER(U107),ABS(U107-D107),"N/A"),"N/A") | F107: =IFERROR(IF(ISNUMBER(D107),IF(ISNUMBER(U107),IF(ABS(U107-D107)<=0.01,"PASS","FAIL"),"FAIL"),IF(NOT(ISNUMBER(U107)),IF(U107=D107,"PASS","FAIL"),"FAIL")),"FAIL") | I107: 1000 | J107: FALSE | L107: 300 | M107: 0 | N107: 0.1 | O107: 0 | P107: 60000 | Q107: per_month | R107: component | S107: consistent | T107: 1 | U107: =IF($T$107>1,"ERROR",IFERROR(IF(Y107="ERROR","ERROR",IF(OR(NOT(ISNUMBER(Y107)),ISBLANK($L$107),ISBLANK($M$107),ISBLANK($N$107),ISBLANK($O$107)),"UNKNOWN",IF($O$107>0,IF(Z107="ERROR","ERROR",IF(NOT(ISNUMBER(Z107)),"UNKNOWN",Y107-$L$107-$M$107-$N$107*Y107-$O$107*Z107)),Y107-$L$107-$M$107-$N$107*Y107))),"ERROR")) | V107: =IF($T$107>1,"ERROR",IFERROR(IF($R$107="invalid_direct","ERROR",IF($S$107="inconsistent","ERROR",IF($R$107="none",0,IF(OR($R$107="unresolved",$R$107="blended_only"),"UNKNOWN",IF(ISBLANK($P$107),"UNKNOWN",IF($P$107<0,"ERROR",$P$107)))))),"ERROR")) | W107: =IF($T$107>1,"ERROR",IFERROR(IF(OR(U107="ERROR",V107="ERROR"),"ERROR",IF(OR(NOT(ISNUMBER(U107)),NOT(ISNUMBER(V107))),"UNKNOWN",IF(U107<=0,"NOT_APPLICABLE",V107/U107))),"ERROR")) | X107: =IF($T$107>1,"",IF(OR($R$107="invalid_direct",$S$107="inconsistent"),"",IF($R$107="none","",IF(OR($R$107="unresolved",$R$107="blended_only"),"",IF(ISBLANK($P$107),"",IF($P$107<0,"",$Q$107)))))) | Y107: =IFERROR(IF(ISBLANK($I$107),"UNKNOWN",IF(ISBLANK($J$107),"UNKNOWN",IF($J$107=FALSE,$I$107,IF(ISBLANK($K$107),"UNKNOWN",$I$107/(1+$K$107))))),"ERROR") | Z107: =IFERROR(IF(ISBLANK($I$107),"UNKNOWN",IF(ISBLANK($J$107),"UNKNOWN",IF($J$107=TRUE,$I$107,IF(ISBLANK($K$107),"UNKNOWN",$I$107*(1+$K$107))))),"ERROR") | AA107: =IF($T$107>1,"MULTI_COMPONENT_BEP_NOT_SUPPORTED",IF($R$107="invalid_direct","INVALID_ALLOCATION_CONFIGURATION",IF($S$107="inconsistent","INCONSISTENT_FIXED_COST_BASIS",IF(AND($R$107="component",NOT(ISBLANK($P$107)),$P$107<0),"INVALID_NEGATIVE_COST",IF(U107="ERROR","CALCULATION_ERROR",IF($R$107="blended_only","FIXED_COST_BLENDED_ONLY_NOT_ALLOCATED",IF($R$107="unresolved","UNSUPPORTED_SHARED_COST_ALLOCATION",IF(NOT(ISNUMBER(U107)),"MISSING_DEPENDENCY",IF(AND($R$107="component",ISBLANK($P$107)),"MISSING_DEPENDENCY",IF(AND(U107=0,V107=0),"BREAK_EVEN_UNDEFINED_ZERO_MARGIN_ZERO_FIXED_COST",IF(U107=0,"BREAK_EVEN_UNDEFINED_ZERO_MARGIN",IF(U107<0,"BREAK_EVEN_UNDEFINED_NEGATIVE_MARGIN","NONE"))))))))))))
B108: Fixed Operating Cost (FC) | C108: =V107 | D108: 60000 | E108: =IF(ISNUMBER(D108),IF(ISNUMBER(V107),ABS(V107-D108),"N/A"),"N/A") | F108: =IFERROR(IF(ISNUMBER(D108),IF(ISNUMBER(V107),IF(ABS(V107-D108)<=0.01,"PASS","FAIL"),"FAIL"),IF(NOT(ISNUMBER(V107)),IF(V107=D108,"PASS","FAIL"),"FAIL")),"FAIL")
B109: Break-Even Quantity (Q_BEP) | C109: =W107 | D109: 100 | E109: =IF(ISNUMBER(D109),IF(ISNUMBER(W107),ABS(W107-D109),"N/A"),"N/A") | F109: =IFERROR(IF(ISNUMBER(D109),IF(ISNUMBER(W107),IF(ABS(W107-D109)<=0.01,"PASS","FAIL"),"FAIL"),IF(NOT(ISNUMBER(W107)),IF(W107=D109,"PASS","FAIL"),"FAIL")),"FAIL")
B110: Analysis Period Basis | C110: =X107 | D110: per_month | E110: =IF(ISNUMBER(D110),IF(ISNUMBER(X107),ABS(X107-D110),"N/A"),"N/A") | F110: =IFERROR(IF(ISNUMBER(D110),IF(ISNUMBER(X107),IF(ABS(X107-D110)<=0.01,"PASS","FAIL"),"FAIL"),IF(NOT(ISNUMBER(X107)),IF(X107=D110,"PASS","FAIL"),"FAIL")),"FAIL")
B111: Module Status Tier | C111: =IF(OR(U107="ERROR",V107="ERROR",W107="ERROR"),"ERROR",IF(OR(U107="UNKNOWN",V107="UNKNOWN",W107="UNKNOWN"),"INCOMPLETE","OK")) | D111: OK | F111: =IF(C111=D111,"PASS","FAIL")
B112: Primary Warning Code (diagnostic) | C112: =AA107 | D112: NONE | F112: =IF(AA107=D112,"PASS","FAIL")
...

Sheet 10_SCENARIO_COMPARE
B2: 10. Scenario Compare — Orchestration over MODE A/B/C/BEP (Interactive)
B4: BASE INPUT (단일 컴포넌트 기준, 모든 시나리오가 공유)
B5: Base Actual Price | C5: 1000
B6: Base Price Includes VAT | C6: FALSE
B7: Base VAT Rate | C7: 0.1
B8: Base Target Market Price | C8: 1000
B9: Base Discount Rate | C9: 0
B10: Base Direct Cost Amount | C10: 400
B11: Base Variable Fixed Cost (override 불가) | C11: 100
B12: Base Net-Sales Fee Rate (override 불가) | C12: 0
B13: Base Gross-Payment Fee Rate (override 불가) | C13: 0
B14: Base Fixed Operating Cost Amount | C14: 50000
B15: Base Target Contribution Margin Rate | C15: 0.3
B17: SCENARIO CONTROL
B18: Baseline Scenario ID | C18: A | D18: 활성 Scenario ID 중 하나와 반드시 일치해야 함 — 첫 번째 시나리오를 자동 baseline으로 취급하지 않음
B19: Excel v0.1: 최대 5개 시나리오(A~E) — Python Core는 이 제한이 없음(2개 이상 임의 개수). 이는 presentation-layer 제한이며 계산 semantics 제한이 아님.
B21: SCENARIO IDENTITY (blank Scenario ID = 비활성)
B22: Scenario ID | C22: A | D22: B | E22: C | F22: D | G22: E
B23: Label | C23: Baseline | D23: Price Up | E23: Price Down
B25: OVERRIDE INPUT (Mode: inherit / null / value)
B26: Actual Price — Mode | C26: inherit | D26: value | E26: value | F26: inherit | G26: inherit
B27: Actual Price — Value | D27: 1200 | E27: 800
B28: Price Includes VAT — Mode | C28: inherit | D28: inherit | E28: inherit | F28: inherit | G28: inherit
B29: Price Includes VAT — Value
B30: Target Market Price — Mode | C30: inherit | D30: inherit | E30: inherit | F30: inherit | G30: inherit
B31: Target Market Price — Value
B32: Discount Rate — Mode | C32: inherit | D32: inherit | E32: inherit | F32: inherit | G32: inherit
B33: Discount Rate — Value
B34: Target CM Rate — Mode | C34: inherit | D34: inherit | E34: inherit | F34: inherit | G34: inherit
B35: Target CM Rate — Value
B36: VAT Rate — Mode | C36: inherit | D36: inherit | E36: inherit | F36: inherit | G36: inherit
B37: VAT Rate — Value
B38: Direct Cost Amount — Mode | C38: inherit | D38: inherit | E38: value | F38: inherit | G38: inherit
B39: Direct Cost Amount — Value | E39: 300
B40: Fixed Operating Cost Amount — Mode | C40: inherit | D40: inherit | E40: inherit | F40: inherit | G40: inherit
B41: Fixed Operating Cost Amount — Value
B43: RESULT SUMMARY (계산값 — 직접 입력 금지)
B44: MODE A: Net Sales ex VAT | C44: =IFERROR(IF(NOT(ISNUMBER(C59)),"UNKNOWN",IF(C60="UNKNOWN","UNKNOWN",IF(C60=FALSE,C59,IF(NOT(ISNUMBER(C61)),"UNKNOWN",C59/(1+C61))))),"ERROR") | D44: =IFERROR(IF(NOT(ISNUMBER(D59)),"UNKNOWN",IF(D60="UNKNOWN","UNKNOWN",IF(D60=FALSE,D59,IF(NOT(ISNUMBER(D61)),"UNKNOWN",D59/(1+D61))))),"ERROR") | E44: =IFERROR(IF(NOT(ISNUMBER(E59)),"UNKNOWN",IF(E60="UNKNOWN","UNKNOWN",IF(E60=FALSE,E59,IF(NOT(ISNUMBER(E61)),"UNKNOWN",E59/(1+E61))))),"ERROR") | F44: =IFERROR(IF(NOT(ISNUMBER(F59)),"UNKNOWN",IF(F60="UNKNOWN","UNKNOWN",IF(F60=FALSE,F59,IF(NOT(ISNUMBER(F61)),"UNKNOWN",F59/(1+F61))))),"ERROR") | G44: =IFERROR(IF(NOT(ISNUMBER(G59)),"UNKNOWN",IF(G60="UNKNOWN","UNKNOWN",IF(G60=FALSE,G59,IF(NOT(ISNUMBER(G61)),"UNKNOWN",G59/(1+G61))))),"ERROR")
B45: MODE A: Contribution Margin | C45: =IFERROR(IF(C44="ERROR","ERROR",IF(OR(NOT(ISNUMBER(C44)),NOT(ISNUMBER(C52))),"UNKNOWN",IF($C$13>0,IF(C66="ERROR","ERROR",IF(NOT(ISNUMBER(C66)),"UNKNOWN",C44-C52-$C$11-$C$12*C44-$C$13*C66)),C44-C52-$C$11-$C$12*C44))),"ERROR") | D45: =IFERROR(IF(D44="ERROR","ERROR",IF(OR(NOT(ISNUMBER(D44)),NOT(ISNUMBER(D52))),"UNKNOWN",IF($C$13>0,IF(D66="ERROR","ERROR",IF(NOT(ISNUMBER(D66)),"UNKNOWN",D44-D52-$C$11-$C$12*D44-$C$13*D66)),D44-D52-$C$11-$C$12*D44))),"ERROR") | E45: =IFERROR(IF(E44="ERROR","ERROR",IF(OR(NOT(ISNUMBER(E44)),NOT(ISNUMBER(E52))),"UNKNOWN",IF($C$13>0,IF(E66="ERROR","ERROR",IF(NOT(ISNUMBER(E66)),"UNKNOWN",E44-E52-$C$11-$C$12*E44-$C$13*E66)),E44-E52-$C$11-$C$12*E44))),"ERROR") | F45: =IFERROR(IF(F44="ERROR","ERROR",IF(OR(NOT(ISNUMBER(F44)),NOT(ISNUMBER(F52))),"UNKNOWN",IF($C$13>0,IF(F66="ERROR","ERROR",IF(NOT(ISNUMBER(F66)),"UNKNOWN",F44-F52-$C$11-$C$12*F44-$C$13*F66)),F44-F52-$C$11-$C$12*F44))),"ERROR") | G45: =IFERROR(IF(G44="ERROR","ERROR",IF(OR(NOT(ISNUMBER(G44)),NOT(ISNUMBER(G52))),"UNKNOWN",IF($C$13>0,IF(G66="ERROR","ERROR",IF(NOT(ISNUMBER(G66)),"UNKNOWN",G44-G52-$C$11-$C$12*G44-$C$13*G66)),G44-G52-$C$11-$C$12*G44))),"ERROR")
B46: MODE A: CM Rate | C46: =IFERROR(IF(C45="ERROR","ERROR",IF(NOT(ISNUMBER(C45)),"UNKNOWN",IF(C44=0,"ERROR",C45/C44))),"ERROR") | D46: =IFERROR(IF(D45="ERROR","ERROR",IF(NOT(ISNUMBER(D45)),"UNKNOWN",IF(D44=0,"ERROR",D45/D44))),"ERROR") | E46: =IFERROR(IF(E45="ERROR","ERROR",IF(NOT(ISNUMBER(E45)),"UNKNOWN",IF(E44=0,"ERROR",E45/E44))),"ERROR") | F46: =IFERROR(IF(F45="ERROR","ERROR",IF(NOT(ISNUMBER(F45)),"UNKNOWN",IF(F44=0,"ERROR",F45/F44))),"ERROR") | G46: =IFERROR(IF(G45="ERROR","ERROR",IF(NOT(ISNUMBER(G45)),"UNKNOWN",IF(G44=0,"ERROR",G45/G44))),"ERROR")
B47: MODE A: Status | C47: =IF(OR(C44="ERROR",C45="ERROR",C46="ERROR"),"ERROR",IF(OR(NOT(ISNUMBER(C44)),NOT(ISNUMBER(C45)),NOT(ISNUMBER(C46))),"UNKNOWN","OK")) | D47: =IF(OR(D44="ERROR",D45="ERROR",D46="ERROR"),"ERROR",IF(OR(NOT(ISNUMBER(D44)),NOT(ISNUMBER(D45)),NOT(ISNUMBER(D46))),"UNKNOWN","OK")) | E47: =IF(OR(E44="ERROR",E45="ERROR",E46="ERROR"),"ERROR",IF(OR(NOT(ISNUMBER(E44)),NOT(ISNUMBER(E45)),NOT(ISNUMBER(E46))),"UNKNOWN","OK")) | F47: =IF(OR(F44="ERROR",F45="ERROR",F46="ERROR"),"ERROR",IF(OR(NOT(ISNUMBER(F44)),NOT(ISNUMBER(F45)),NOT(ISNUMBER(F46))),"UNKNOWN","OK")) | G47: =IF(OR(G44="ERROR",G45="ERROR",G46="ERROR"),"ERROR",IF(OR(NOT(ISNUMBER(G44)),NOT(ISNUMBER(G45)),NOT(ISNUMBER(G46))),"UNKNOWN","OK"))
B48: MODE B: Required Selling Price | C48: =IFERROR(IF(C60="UNKNOWN","UNKNOWN",IF(C60=FALSE,C69,C70)),"ERROR") | D48: =IFERROR(IF(D60="UNKNOWN","UNKNOWN",IF(D60=FALSE,D69,D70)),"ERROR") | E48: =IFERROR(IF(E60="UNKNOWN","UNKNOWN",IF(E60=FALSE,E69,E70)),"ERROR") | F48: =IFERROR(IF(F60="UNKNOWN","UNKNOWN",IF(F60=FALSE,F69,F70)),"ERROR") | G48: =IFERROR(IF(G60="UNKNOWN","UNKNOWN",IF(G60=FALSE,G69,G70)),"ERROR")
B49: MODE B: Required List Price | C49: =IFERROR(IF(NOT(ISNUMBER(C48)),C48,IF(NOT(ISNUMBER(C63)),"UNKNOWN",IF(OR(C63<0,C63>=1),"ERROR",IF(C63=0,C48,C48/(1-C63))))),"ERROR") | D49: =IFERROR(IF(NOT(ISNUMBER(D48)),D48,IF(NOT(ISNUMBER(D63)),"UNKNOWN",IF(OR(D63<0,D63>=1),"ERROR",IF(D63=0,D48,D48/(1-D63))))),"ERROR") | E49: =IFERROR(IF(NOT(ISNUMBER(E48)),E48,IF(NOT(ISNUMBER(E63)),"UNKNOWN",IF(OR(E63<0,E63>=1),"ERROR",IF(E63=0,E48,E48/(1-E63))))),"ERROR") | F49: =IFERROR(IF(NOT(ISNUMBER(F48)),F48,IF(NOT(ISNUMBER(F63)),"UNKNOWN",IF(OR(F63<0,F63>=1),"ERROR",IF(F63=0,F48,F48/(1-F63))))),"ERROR") | G49: =IFERROR(IF(NOT(ISNUMBER(G48)),G48,IF(NOT(ISNUMBER(G63)),"UNKNOWN",IF(OR(G63<0,G63>=1),"ERROR",IF(G63=0,G48,G48/(1-G63))))),"ERROR")
B50: MODE B: Status | C50: =IF(OR(C48="ERROR",C49="ERROR"),"ERROR",IF(OR(NOT(ISNUMBER(C48)),NOT(ISNUMBER(C49))),"UNKNOWN","OK")) | D50: =IF(OR(D48="ERROR",D49="ERROR"),"ERROR",IF(OR(NOT(ISNUMBER(D48)),NOT(ISNUMBER(D49))),"UNKNOWN","OK")) | E50: =IF(OR(E48="ERROR",E49="ERROR"),"ERROR",IF(OR(NOT(ISNUMBER(E48)),NOT(ISNUMBER(E49))),"UNKNOWN","OK")) | F50: =IF(OR(F48="ERROR",F49="ERROR"),"ERROR",IF(OR(NOT(ISNUMBER(F48)),NOT(ISNUMBER(F49))),"UNKNOWN","OK")) | G50: =IF(OR(G48="ERROR",G49="ERROR"),"ERROR",IF(OR(NOT(ISNUMBER(G48)),NOT(ISNUMBER(G49))),"UNKNOWN","OK"))
B51: MODE C: Allowable Direct Cost | C51: =IFERROR(IF(C71="ERROR","ERROR",IF(NOT(ISNUMBER(C64)),"UNKNOWN",IF(OR(C64<0,C64>=1),"ERROR",IF(NOT(ISNUMBER(C71)),"UNKNOWN",IF($C$13>0,IF(C72="ERROR","ERROR",IF(NOT(ISNUMBER(C72)),"UNKNOWN",C71*(1-C64-$C$12)-$C$13*C72-$C$11)),C71*(1-C64-$C$12)-$C$11))))),"ERROR") | D51: =IFERROR(IF(D71="ERROR","ERROR",IF(NOT(ISNUMBER(D64)),"UNKNOWN",IF(OR(D64<0,D64>=1),"ERROR",IF(NOT(ISNUMBER(D71)),"UNKNOWN",IF($C$13>0,IF(D72="ERROR","ERROR",IF(NOT(ISNUMBER(D72)),"UNKNOWN",D71*(1-D64-$C$12)-$C$13*D72-$C$11)),D71*(1-D64-$C$12)-$C$11))))),"ERROR") | E51: =IFERROR(IF(E71="ERROR","ERROR",IF(NOT(ISNUMBER(E64)),"UNKNOWN",IF(OR(E64<0,E64>=1),"ERROR",IF(NOT(ISNUMBER(E71)),"UNKNOWN",IF($C$13>0,IF(E72="ERROR","ERROR",IF(NOT(ISNUMBER(E72)),"UNKNOWN",E71*(1-E64-$C$12)-$C$13*E72-$C$11)),E71*(1-E64-$C$12)-$C$11))))),"ERROR") | F51: =IFERROR(IF(F71="ERROR","ERROR",IF(NOT(ISNUMBER(F64)),"UNKNOWN",IF(OR(F64<0,F64>=1),"ERROR",IF(NOT(ISNUMBER(F71)),"UNKNOWN",IF($C$13>0,IF(F72="ERROR","ERROR",IF(NOT(ISNUMBER(F72)),"UNKNOWN",F71*(1-F64-$C$12)-$C$13*F72-$C$11)),F71*(1-F64-$C$12)-$C$11))))),"ERROR") | G51: =IFERROR(IF(G71="ERROR","ERROR",IF(NOT(ISNUMBER(G64)),"UNKNOWN",IF(OR(G64<0,G64>=1),"ERROR",IF(NOT(ISNUMBER(G71)),"UNKNOWN",IF($C$13>0,IF(G72="ERROR","ERROR",IF(NOT(ISNUMBER(G72)),"UNKNOWN",G71*(1-G64-$C$12)-$C$13*G72-$C$11)),G71*(1-G64-$C$12)-$C$11))))),"ERROR")
B52: MODE C: Actual Direct Cost | C52: =IF($C$38="inherit",$C$10,IF($C$38="null","UNKNOWN",$C$39)) | D52: =IF($D$38="inherit",$C$10,IF($D$38="null","UNKNOWN",$D$39)) | E52: =IF($E$38="inherit",$C$10,IF($E$38="null","UNKNOWN",$E$39)) | F52: =IF($F$38="inherit",$C$10,IF($F$38="null","UNKNOWN",$F$39)) | G52: =IF($G$38="inherit",$C$10,IF($G$38="null","UNKNOWN",$G$39))
B53: MODE C: Direct Cost Gap | C53: =IFERROR(IF(OR(C51="ERROR",C52="ERROR"),"ERROR",IF(OR(NOT(ISNUMBER(C51)),NOT(ISNUMBER(C52))),"UNKNOWN",C51-C52)),"ERROR") | D53: =IFERROR(IF(OR(D51="ERROR",D52="ERROR"),"ERROR",IF(OR(NOT(ISNUMBER(D51)),NOT(ISNUMBER(D52))),"UNKNOWN",D51-D52)),"ERROR") | E53: =IFERROR(IF(OR(E51="ERROR",E52="ERROR"),"ERROR",IF(OR(NOT(ISNUMBER(E51)),NOT(ISNUMBER(E52))),"UNKNOWN",E51-E52)),"ERROR") | F53: =IFERROR(IF(OR(F51="ERROR",F52="ERROR"),"ERROR",IF(OR(NOT(ISNUMBER(F51)),NOT(ISNUMBER(F52))),"UNKNOWN",F51-F52)),"ERROR") | G53: =IFERROR(IF(OR(G51="ERROR",G52="ERROR"),"ERROR",IF(OR(NOT(ISNUMBER(G51)),NOT(ISNUMBER(G52))),"UNKNOWN",G51-G52)),"ERROR")
B54: MODE C: Status | C54: =IF(OR(C51="ERROR",C52="ERROR",C53="ERROR"),"ERROR",IF(OR(NOT(ISNUMBER(C51)),NOT(ISNUMBER(C52)),NOT(ISNUMBER(C53))),"UNKNOWN","OK")) | D54: =IF(OR(D51="ERROR",D52="ERROR",D53="ERROR"),"ERROR",IF(OR(NOT(ISNUMBER(D51)),NOT(ISNUMBER(D52)),NOT(ISNUMBER(D53))),"UNKNOWN","OK")) | E54: =IF(OR(E51="ERROR",E52="ERROR",E53="ERROR"),"ERROR",IF(OR(NOT(ISNUMBER(E51)),NOT(ISNUMBER(E52)),NOT(ISNUMBER(E53))),"UNKNOWN","OK")) | F54: =IF(OR(F51="ERROR",F52="ERROR",F53="ERROR"),"ERROR",IF(OR(NOT(ISNUMBER(F51)),NOT(ISNUMBER(F52)),NOT(ISNUMBER(F53))),"UNKNOWN","OK")) | G54: =IF(OR(G51="ERROR",G52="ERROR",G53="ERROR"),"ERROR",IF(OR(NOT(ISNUMBER(G51)),NOT(ISNUMBER(G52)),NOT(ISNUMBER(G53))),"UNKNOWN","OK"))
B55: BEP: Fixed Operating Cost | C55: =IFERROR(IF(NOT(ISNUMBER(C65)),C65,IF(C65<0,"ERROR",C65)),"ERROR") | D55: =IFERROR(IF(NOT(ISNUMBER(D65)),D65,IF(D65<0,"ERROR",D65)),"ERROR") | E55: =IFERROR(IF(NOT(ISNUMBER(E65)),E65,IF(E65<0,"ERROR",E65)),"ERROR") | F55: =IFERROR(IF(NOT(ISNUMBER(F65)),F65,IF(F65<0,"ERROR",F65)),"ERROR") | G55: =IFERROR(IF(NOT(ISNUMBER(G65)),G65,IF(G65<0,"ERROR",G65)),"ERROR")
B56: BEP: Break-Even Quantity | C56: =IFERROR(IF(OR(C45="ERROR",C55="ERROR"),"ERROR",IF(OR(NOT(ISNUMBER(C45)),NOT(ISNUMBER(C55))),"UNKNOWN",IF(C45<=0,"NOT_APPLICABLE",C55/C45))),"ERROR") | D56: =IFERROR(IF(OR(D45="ERROR",D55="ERROR"),"ERROR",IF(OR(NOT(ISNUMBER(D45)),NOT(ISNUMBER(D55))),"UNKNOWN",IF(D45<=0,"NOT_APPLICABLE",D55/D45))),"ERROR") | E56: =IFERROR(IF(OR(E45="ERROR",E55="ERROR"),"ERROR",IF(OR(NOT(ISNUMBER(E45)),NOT(ISNUMBER(E55))),"UNKNOWN",IF(E45<=0,"NOT_APPLICABLE",E55/E45))),"ERROR") | F56: =IFERROR(IF(OR(F45="ERROR",F55="ERROR"),"ERROR",IF(OR(NOT(ISNUMBER(F45)),NOT(ISNUMBER(F55))),"UNKNOWN",IF(F45<=0,"NOT_APPLICABLE",F55/F45))),"ERROR") | G56: =IFERROR(IF(OR(G45="ERROR",G55="ERROR"),"ERROR",IF(OR(NOT(ISNUMBER(G45)),NOT(ISNUMBER(G55))),"UNKNOWN",IF(G45<=0,"NOT_APPLICABLE",G55/G45))),"ERROR")
B57: BEP: Status | C57: =IF(OR(C45="ERROR",C55="ERROR",C56="ERROR"),"ERROR",IF(OR(NOT(ISNUMBER(C45)),NOT(ISNUMBER(C55)),AND(NOT(ISNUMBER(C56)),C56<>"NOT_APPLICABLE")),"UNKNOWN","OK")) | D57: =IF(OR(D45="ERROR",D55="ERROR",D56="ERROR"),"ERROR",IF(OR(NOT(ISNUMBER(D45)),NOT(ISNUMBER(D55)),AND(NOT(ISNUMBER(D56)),D56<>"NOT_APPLICABLE")),"UNKNOWN","OK")) | E57: =IF(OR(E45="ERROR",E55="ERROR",E56="ERROR"),"ERROR",IF(OR(NOT(ISNUMBER(E45)),NOT(ISNUMBER(E55)),AND(NOT(ISNUMBER(E56)),E56<>"NOT_APPLICABLE")),"UNKNOWN","OK")) | F57: =IF(OR(F45="ERROR",F55="ERROR",F56="ERROR"),"ERROR",IF(OR(NOT(ISNUMBER(F45)),NOT(ISNUMBER(F55)),AND(NOT(ISNUMBER(F56)),F56<>"NOT_APPLICABLE")),"UNKNOWN","OK")) | G57: =IF(OR(G45="ERROR",G55="ERROR",G56="ERROR"),"ERROR",IF(OR(NOT(ISNUMBER(G45)),NOT(ISNUMBER(G55)),AND(NOT(ISNUMBER(G56)),G56<>"NOT_APPLICABLE")),"UNKNOWN","OK"))
B58: SCENARIO OVERALL STATUS | C58: =IF(OR(C47="ERROR",C50="ERROR",C54="ERROR",C57="ERROR"),"ERROR",IF(OR(C47="UNKNOWN",C50="UNKNOWN",C54="UNKNOWN",C57="UNKNOWN"),"INCOMPLETE","OK")) | D58: =IF(OR(D47="ERROR",D50="ERROR",D54="ERROR",D57="ERROR"),"ERROR",IF(OR(D47="UNKNOWN",D50="UNKNOWN",D54="UNKNOWN",D57="UNKNOWN"),"INCOMPLETE","OK")) | E58: =IF(OR(E47="ERROR",E50="ERROR",E54="ERROR",E57="ERROR"),"ERROR",IF(OR(E47="UNKNOWN",E50="UNKNOWN",E54="UNKNOWN",E57="UNKNOWN"),"INCOMPLETE","OK")) | F58: =IF(OR(F47="ERROR",F50="ERROR",F54="ERROR",F57="ERROR"),"ERROR",IF(OR(F47="UNKNOWN",F50="UNKNOWN",F54="UNKNOWN",F57="UNKNOWN"),"INCOMPLETE","OK")) | G58: =IF(OR(G47="ERROR",G50="ERROR",G54="ERROR",G57="ERROR"),"ERROR",IF(OR(G47="UNKNOWN",G50="UNKNOWN",G54="UNKNOWN",G57="UNKNOWN"),"INCOMPLETE","OK"))
C59: =IF($C$26="inherit",$C$5,IF($C$26="null","UNKNOWN",$C$27)) | D59: =IF($D$26="inherit",$C$5,IF($D$26="null","UNKNOWN",$D$27)) | E59: =IF($E$26="inherit",$C$5,IF($E$26="null","UNKNOWN",$E$27)) | F59: =IF($F$26="inherit",$C$5,IF($F$26="null","UNKNOWN",$F$27)) | G59: =IF($G$26="inherit",$C$5,IF($G$26="null","UNKNOWN",$G$27))
C60: =IF($C$28="inherit",$C$6,IF($C$28="null","UNKNOWN",$C$29)) | D60: =IF($D$28="inherit",$C$6,IF($D$28="null","UNKNOWN",$D$29)) | E60: =IF($E$28="inherit",$C$6,IF($E$28="null","UNKNOWN",$E$29)) | F60: =IF($F$28="inherit",$C$6,IF($F$28="null","UNKNOWN",$F$29)) | G60: =IF($G$28="inherit",$C$6,IF($G$28="null","UNKNOWN",$G$29))
C61: =IF($C$36="inherit",$C$7,IF($C$36="null","UNKNOWN",$C$37)) | D61: =IF($D$36="inherit",$C$7,IF($D$36="null","UNKNOWN",$D$37)) | E61: =IF($E$36="inherit",$C$7,IF($E$36="null","UNKNOWN",$E$37)) | F61: =IF($F$36="inherit",$C$7,IF($F$36="null","UNKNOWN",$F$37)) | G61: =IF($G$36="inherit",$C$7,IF($G$36="null","UNKNOWN",$G$37))
C62: =IF($C$30="inherit",$C$8,IF($C$30="null","UNKNOWN",$C$31)) | D62: =IF($D$30="inherit",$C$8,IF($D$30="null","UNKNOWN",$D$31)) | E62: =IF($E$30="inherit",$C$8,IF($E$30="null","UNKNOWN",$E$31)) | F62: =IF($F$30="inherit",$C$8,IF($F$30="null","UNKNOWN",$F$31)) | G62: =IF($G$30="inherit",$C$8,IF($G$30="null","UNKNOWN",$G$31))
C63: =IF($C$32="inherit",$C$9,IF($C$32="null","UNKNOWN",$C$33)) | D63: =IF($D$32="inherit",$C$9,IF($D$32="null","UNKNOWN",$D$33)) | E63: =IF($E$32="inherit",$C$9,IF($E$32="null","UNKNOWN",$E$33)) | F63: =IF($F$32="inherit",$C$9,IF($F$32="null","UNKNOWN",$F$33)) | G63: =IF($G$32="inherit",$C$9,IF($G$32="null","UNKNOWN",$G$33))
C64: =IF($C$34="inherit",$C$15,IF($C$34="null","UNKNOWN",$C$35)) | D64: =IF($D$34="inherit",$C$15,IF($D$34="null","UNKNOWN",$D$35)) | E64: =IF($E$34="inherit",$C$15,IF($E$34="null","UNKNOWN",$E$35)) | F64: =IF($F$34="inherit",$C$15,IF($F$34="null","UNKNOWN",$F$35)) | G64: =IF($G$34="inherit",$C$15,IF($G$34="null","UNKNOWN",$G$35))
C65: =IF($C$40="inherit",$C$14,IF($C$40="null","UNKNOWN",$C$41)) | D65: =IF($D$40="inherit",$C$14,IF($D$40="null","UNKNOWN",$D$41)) | E65: =IF($E$40="inherit",$C$14,IF($E$40="null","UNKNOWN",$E$41)) | F65: =IF($F$40="inherit",$C$14,IF($F$40="null","UNKNOWN",$F$41)) | G65: =IF($G$40="inherit",$C$14,IF($G$40="null","UNKNOWN",$G$41))
C66: =IFERROR(IF(NOT(ISNUMBER(C59)),"UNKNOWN",IF(C60="UNKNOWN","UNKNOWN",IF(C60=TRUE,C59,IF(NOT(ISNUMBER(C61)),"UNKNOWN",C59*(1+C61))))),"ERROR") | D66: =IFERROR(IF(NOT(ISNUMBER(D59)),"UNKNOWN",IF(D60="UNKNOWN","UNKNOWN",IF(D60=TRUE,D59,IF(NOT(ISNUMBER(D61)),"UNKNOWN",D59*(1+D61))))),"ERROR") | E66: =IFERROR(IF(NOT(ISNUMBER(E59)),"UNKNOWN",IF(E60="UNKNOWN","UNKNOWN",IF(E60=TRUE,E59,IF(NOT(ISNUMBER(E61)),"UNKNOWN",E59*(1+E61))))),"ERROR") | F66: =IFERROR(IF(NOT(ISNUMBER(F59)),"UNKNOWN",IF(F60="UNKNOWN","UNKNOWN",IF(F60=TRUE,F59,IF(NOT(ISNUMBER(F61)),"UNKNOWN",F59*(1+F61))))),"ERROR") | G66: =IFERROR(IF(NOT(ISNUMBER(G59)),"UNKNOWN",IF(G60="UNKNOWN","UNKNOWN",IF(G60=TRUE,G59,IF(NOT(ISNUMBER(G61)),"UNKNOWN",G59*(1+G61))))),"ERROR")
C67: =IFERROR(IF(NOT(ISNUMBER(C52)),C52,C52+$C$11),"ERROR") | D67: =IFERROR(IF(NOT(ISNUMBER(D52)),D52,D52+$C$11),"ERROR") | E67: =IFERROR(IF(NOT(ISNUMBER(E52)),E52,E52+$C$11),"ERROR") | F67: =IFERROR(IF(NOT(ISNUMBER(F52)),F52,F52+$C$11),"ERROR") | G67: =IFERROR(IF(NOT(ISNUMBER(G52)),G52,G52+$C$11),"ERROR")
C68: =IFERROR(IF(NOT(ISNUMBER(C64)),"UNKNOWN",IF(OR(C64<0,C64>=1),"ERROR",IF($C$13=0,IF(1-C64-$C$12<=0,"ERROR",1-C64-$C$12),IF(NOT(ISNUMBER(C61)),"UNKNOWN",IF(1-C64-$C$12-$C$13*(1+C61)<=0,"ERROR",1-C64-$C$12-$C$13*(1+C61)))))),"ERROR") | D68: =IFERROR(IF(NOT(ISNUMBER(D64)),"UNKNOWN",IF(OR(D64<0,D64>=1),"ERROR",IF($C$13=0,IF(1-D64-$C$12<=0,"ERROR",1-D64-$C$12),IF(NOT(ISNUMBER(D61)),"UNKNOWN",IF(1-D64-$C$12-$C$13*(1+D61)<=0,"ERROR",1-D64-$C$12-$C$13*(1+D61)))))),"ERROR") | E68: =IFERROR(IF(NOT(ISNUMBER(E64)),"UNKNOWN",IF(OR(E64<0,E64>=1),"ERROR",IF($C$13=0,IF(1-E64-$C$12<=0,"ERROR",1-E64-$C$12),IF(NOT(ISNUMBER(E61)),"UNKNOWN",IF(1-E64-$C$12-$C$13*(1+E61)<=0,"ERROR",1-E64-$C$12-$C$13*(1+E61)))))),"ERROR") | F68: =IFERROR(IF(NOT(ISNUMBER(F64)),"UNKNOWN",IF(OR(F64<0,F64>=1),"ERROR",IF($C$13=0,IF(1-F64-$C$12<=0,"ERROR",1-F64-$C$12),IF(NOT(ISNUMBER(F61)),"UNKNOWN",IF(1-F64-$C$12-$C$13*(1+F61)<=0,"ERROR",1-F64-$C$12-$C$13*(1+F61)))))),"ERROR") | G68: =IFERROR(IF(NOT(ISNUMBER(G64)),"UNKNOWN",IF(OR(G64<0,G64>=1),"ERROR",IF($C$13=0,IF(1-G64-$C$12<=0,"ERROR",1-G64-$C$12),IF(NOT(ISNUMBER(G61)),"UNKNOWN",IF(1-G64-$C$12-$C$13*(1+G61)<=0,"ERROR",1-G64-$C$12-$C$13*(1+G61)))))),"ERROR")
C69: =IFERROR(IF(NOT(ISNUMBER(C67)),C67,IF(NOT(ISNUMBER(C68)),C68,C67/C68)),"ERROR") | D69: =IFERROR(IF(NOT(ISNUMBER(D67)),D67,IF(NOT(ISNUMBER(D68)),D68,D67/D68)),"ERROR") | E69: =IFERROR(IF(NOT(ISNUMBER(E67)),E67,IF(NOT(ISNUMBER(E68)),E68,E67/E68)),"ERROR") | F69: =IFERROR(IF(NOT(ISNUMBER(F67)),F67,IF(NOT(ISNUMBER(F68)),F68,F67/F68)),"ERROR") | G69: =IFERROR(IF(NOT(ISNUMBER(G67)),G67,IF(NOT(ISNUMBER(G68)),G68,G67/G68)),"ERROR")
C70: =IFERROR(IF(NOT(ISNUMBER(C69)),C69,IF(NOT(ISNUMBER(C61)),"UNKNOWN",C69*(1+C61))),"ERROR") | D70: =IFERROR(IF(NOT(ISNUMBER(D69)),D69,IF(NOT(ISNUMBER(D61)),"UNKNOWN",D69*(1+D61))),"ERROR") | E70: =IFERROR(IF(NOT(ISNUMBER(E69)),E69,IF(NOT(ISNUMBER(E61)),"UNKNOWN",E69*(1+E61))),"ERROR") | F70: =IFERROR(IF(NOT(ISNUMBER(F69)),F69,IF(NOT(ISNUMBER(F61)),"UNKNOWN",F69*(1+F61))),"ERROR") | G70: =IFERROR(IF(NOT(ISNUMBER(G69)),G69,IF(NOT(ISNUMBER(G61)),"UNKNOWN",G69*(1+G61))),"ERROR")
C71: =IFERROR(IF(NOT(ISNUMBER(C62)),"UNKNOWN",IF(C60="UNKNOWN","UNKNOWN",IF(C60=FALSE,C62,IF(NOT(ISNUMBER(C61)),"UNKNOWN",C62/(1+C61))))),"ERROR") | D71: =IFERROR(IF(NOT(ISNUMBER(D62)),"UNKNOWN",IF(D60="UNKNOWN","UNKNOWN",IF(D60=FALSE,D62,IF(NOT(ISNUMBER(D61)),"UNKNOWN",D62/(1+D61))))),"ERROR") | E71: =IFERROR(IF(NOT(ISNUMBER(E62)),"UNKNOWN",IF(E60="UNKNOWN","UNKNOWN",IF(E60=FALSE,E62,IF(NOT(ISNUMBER(E61)),"UNKNOWN",E62/(1+E61))))),"ERROR") | F71: =IFERROR(IF(NOT(ISNUMBER(F62)),"UNKNOWN",IF(F60="UNKNOWN","UNKNOWN",IF(F60=FALSE,F62,IF(NOT(ISNUMBER(F61)),"UNKNOWN",F62/(1+F61))))),"ERROR") | G71: =IFERROR(IF(NOT(ISNUMBER(G62)),"UNKNOWN",IF(G60="UNKNOWN","UNKNOWN",IF(G60=FALSE,G62,IF(NOT(ISNUMBER(G61)),"UNKNOWN",G62/(1+G61))))),"ERROR")
C72: =IFERROR(IF(NOT(ISNUMBER(C62)),"UNKNOWN",IF(C60="UNKNOWN","UNKNOWN",IF(C60=TRUE,C62,IF(NOT(ISNUMBER(C61)),"UNKNOWN",C62*(1+C61))))),"ERROR") | D72: =IFERROR(IF(NOT(ISNUMBER(D62)),"UNKNOWN",IF(D60="UNKNOWN","UNKNOWN",IF(D60=TRUE,D62,IF(NOT(ISNUMBER(D61)),"UNKNOWN",D62*(1+D61))))),"ERROR") | E72: =IFERROR(IF(NOT(ISNUMBER(E62)),"UNKNOWN",IF(E60="UNKNOWN","UNKNOWN",IF(E60=TRUE,E62,IF(NOT(ISNUMBER(E61)),"UNKNOWN",E62*(1+E61))))),"ERROR") | F72: =IFERROR(IF(NOT(ISNUMBER(F62)),"UNKNOWN",IF(F60="UNKNOWN","UNKNOWN",IF(F60=TRUE,F62,IF(NOT(ISNUMBER(F61)),"UNKNOWN",F62*(1+F61))))),"ERROR") | G72: =IFERROR(IF(NOT(ISNUMBER(G62)),"UNKNOWN",IF(G60="UNKNOWN","UNKNOWN",IF(G60=TRUE,G62,IF(NOT(ISNUMBER(G61)),"UNKNOWN",G62*(1+G61))))),"ERROR")
B75: DELTA vs. Baseline (SPEC.md section 13/14)
B76: Baseline Column Index (내부 계산용, MATCH) | C76: =IFERROR(MATCH($C$18,$C$22:$G$22,0),0) | D76: 0이면 baseline_scenario_id를 활성 Scenario ID 중에서 찾지 못한 것 (request-level ERROR)
B77: net_sales_ex_vat_delta | C77: =IF(C76=0,"ERROR",IF(OR($C$44="ERROR",INDEX($C$44:$G$44,1,C76)="ERROR"),"ERROR",IF(OR($C$44="UNKNOWN",INDEX($C$44:$G$44,1,C76)="UNKNOWN"),"UNKNOWN",IF(OR($C$44="NOT_APPLICABLE",INDEX($C$44:$G$44,1,C76)="NOT_APPLICABLE"),"NOT_APPLICABLE",$C$44-INDEX($C$44:$G$44,1,C76))))) | D77: =IF(C76=0,"ERROR",IF(OR($D$44="ERROR",INDEX($C$44:$G$44,1,C76)="ERROR"),"ERROR",IF(OR($D$44="UNKNOWN",INDEX($C$44:$G$44,1,C76)="UNKNOWN"),"UNKNOWN",IF(OR($D$44="NOT_APPLICABLE",INDEX($C$44:$G$44,1,C76)="NOT_APPLICABLE"),"NOT_APPLICABLE",$D$44-INDEX($C$44:$G$44,1,C76))))) | E77: =IF(C76=0,"ERROR",IF(OR($E$44="ERROR",INDEX($C$44:$G$44,1,C76)="ERROR"),"ERROR",IF(OR($E$44="UNKNOWN",INDEX($C$44:$G$44,1,C76)="UNKNOWN"),"UNKNOWN",IF(OR($E$44="NOT_APPLICABLE",INDEX($C$44:$G$44,1,C76)="NOT_APPLICABLE"),"NOT_APPLICABLE",$E$44-INDEX($C$44:$G$44,1,C76))))) | F77: =IF(C76=0,"ERROR",IF(OR($F$44="ERROR",INDEX($C$44:$G$44,1,C76)="ERROR"),"ERROR",IF(OR($F$44="UNKNOWN",INDEX($C$44:$G$44,1,C76)="UNKNOWN"),"UNKNOWN",IF(OR($F$44="NOT_APPLICABLE",INDEX($C$44:$G$44,1,C76)="NOT_APPLICABLE"),"NOT_APPLICABLE",$F$44-INDEX($C$44:$G$44,1,C76))))) | G77: =IF(C76=0,"ERROR",IF(OR($G$44="ERROR",INDEX($C$44:$G$44,1,C76)="ERROR"),"ERROR",IF(OR($G$44="UNKNOWN",INDEX($C$44:$G$44,1,C76)="UNKNOWN"),"UNKNOWN",IF(OR($G$44="NOT_APPLICABLE",INDEX($C$44:$G$44,1,C76)="NOT_APPLICABLE"),"NOT_APPLICABLE",$G$44-INDEX($C$44:$G$44,1,C76)))))
B78: contribution_margin_delta | C78: =IF(C76=0,"ERROR",IF(OR($C$45="ERROR",INDEX($C$45:$G$45,1,C76)="ERROR"),"ERROR",IF(OR($C$45="UNKNOWN",INDEX($C$45:$G$45,1,C76)="UNKNOWN"),"UNKNOWN",IF(OR($C$45="NOT_APPLICABLE",INDEX($C$45:$G$45,1,C76)="NOT_APPLICABLE"),"NOT_APPLICABLE",$C$45-INDEX($C$45:$G$45,1,C76))))) | D78: =IF(C76=0,"ERROR",IF(OR($D$45="ERROR",INDEX($C$45:$G$45,1,C76)="ERROR"),"ERROR",IF(OR($D$45="UNKNOWN",INDEX($C$45:$G$45,1,C76)="UNKNOWN"),"UNKNOWN",IF(OR($D$45="NOT_APPLICABLE",INDEX($C$45:$G$45,1,C76)="NOT_APPLICABLE"),"NOT_APPLICABLE",$D$45-INDEX($C$45:$G$45,1,C76))))) | E78: =IF(C76=0,"ERROR",IF(OR($E$45="ERROR",INDEX($C$45:$G$45,1,C76)="ERROR"),"ERROR",IF(OR($E$45="UNKNOWN",INDEX($C$45:$G$45,1,C76)="UNKNOWN"),"UNKNOWN",IF(OR($E$45="NOT_APPLICABLE",INDEX($C$45:$G$45,1,C76)="NOT_APPLICABLE"),"NOT_APPLICABLE",$E$45-INDEX($C$45:$G$45,1,C76))))) | F78: =IF(C76=0,"ERROR",IF(OR($F$45="ERROR",INDEX($C$45:$G$45,1,C76)="ERROR"),"ERROR",IF(OR($F$45="UNKNOWN",INDEX($C$45:$G$45,1,C76)="UNKNOWN"),"UNKNOWN",IF(OR($F$45="NOT_APPLICABLE",INDEX($C$45:$G$45,1,C76)="NOT_APPLICABLE"),"NOT_APPLICABLE",$F$45-INDEX($C$45:$G$45,1,C76))))) | G78: =IF(C76=0,"ERROR",IF(OR($G$45="ERROR",INDEX($C$45:$G$45,1,C76)="ERROR"),"ERROR",IF(OR($G$45="UNKNOWN",INDEX($C$45:$G$45,1,C76)="UNKNOWN"),"UNKNOWN",IF(OR($G$45="NOT_APPLICABLE",INDEX($C$45:$G$45,1,C76)="NOT_APPLICABLE"),"NOT_APPLICABLE",$G$45-INDEX($C$45:$G$45,1,C76)))))
B79: contribution_margin_rate_delta | C79: =IF(C76=0,"ERROR",IF(OR($C$46="ERROR",INDEX($C$46:$G$46,1,C76)="ERROR"),"ERROR",IF(OR($C$46="UNKNOWN",INDEX($C$46:$G$46,1,C76)="UNKNOWN"),"UNKNOWN",IF(OR($C$46="NOT_APPLICABLE",INDEX($C$46:$G$46,1,C76)="NOT_APPLICABLE"),"NOT_APPLICABLE",$C$46-INDEX($C$46:$G$46,1,C76))))) | D79: =IF(C76=0,"ERROR",IF(OR($D$46="ERROR",INDEX($C$46:$G$46,1,C76)="ERROR"),"ERROR",IF(OR($D$46="UNKNOWN",INDEX($C$46:$G$46,1,C76)="UNKNOWN"),"UNKNOWN",IF(OR($D$46="NOT_APPLICABLE",INDEX($C$46:$G$46,1,C76)="NOT_APPLICABLE"),"NOT_APPLICABLE",$D$46-INDEX($C$46:$G$46,1,C76))))) | E79: =IF(C76=0,"ERROR",IF(OR($E$46="ERROR",INDEX($C$46:$G$46,1,C76)="ERROR"),"ERROR",IF(OR($E$46="UNKNOWN",INDEX($C$46:$G$46,1,C76)="UNKNOWN"),"UNKNOWN",IF(OR($E$46="NOT_APPLICABLE",INDEX($C$46:$G$46,1,C76)="NOT_APPLICABLE"),"NOT_APPLICABLE",$E$46-INDEX($C$46:$G$46,1,C76))))) | F79: =IF(C76=0,"ERROR",IF(OR($F$46="ERROR",INDEX($C$46:$G$46,1,C76)="ERROR"),"ERROR",IF(OR($F$46="UNKNOWN",INDEX($C$46:$G$46,1,C76)="UNKNOWN"),"UNKNOWN",IF(OR($F$46="NOT_APPLICABLE",INDEX($C$46:$G$46,1,C76)="NOT_APPLICABLE"),"NOT_APPLICABLE",$F$46-INDEX($C$46:$G$46,1,C76))))) | G79: =IF(C76=0,"ERROR",IF(OR($G$46="ERROR",INDEX($C$46:$G$46,1,C76)="ERROR"),"ERROR",IF(OR($G$46="UNKNOWN",INDEX($C$46:$G$46,1,C76)="UNKNOWN"),"UNKNOWN",IF(OR($G$46="NOT_APPLICABLE",INDEX($C$46:$G$46,1,C76)="NOT_APPLICABLE"),"NOT_APPLICABLE",$G$46-INDEX($C$46:$G$46,1,C76)))))
B80: break_even_quantity_delta | C80: =IF(C76=0,"ERROR",IF(OR($C$56="ERROR",INDEX($C$56:$G$56,1,C76)="ERROR"),"ERROR",IF(OR($C$56="UNKNOWN",INDEX($C$56:$G$56,1,C76)="UNKNOWN"),"UNKNOWN",IF(OR($C$56="NOT_APPLICABLE",INDEX($C$56:$G$56,1,C76)="NOT_APPLICABLE"),"NOT_APPLICABLE",$C$56-INDEX($C$56:$G$56,1,C76))))) | D80: =IF(C76=0,"ERROR",IF(OR($D$56="ERROR",INDEX($C$56:$G$56,1,C76)="ERROR"),"ERROR",IF(OR($D$56="UNKNOWN",INDEX($C$56:$G$56,1,C76)="UNKNOWN"),"UNKNOWN",IF(OR($D$56="NOT_APPLICABLE",INDEX($C$56:$G$56,1,C76)="NOT_APPLICABLE"),"NOT_APPLICABLE",$D$56-INDEX($C$56:$G$56,1,C76))))) | E80: =IF(C76=0,"ERROR",IF(OR($E$56="ERROR",INDEX($C$56:$G$56,1,C76)="ERROR"),"ERROR",IF(OR($E$56="UNKNOWN",INDEX($C$56:$G$56,1,C76)="UNKNOWN"),"UNKNOWN",IF(OR($E$56="NOT_APPLICABLE",INDEX($C$56:$G$56,1,C76)="NOT_APPLICABLE"),"NOT_APPLICABLE",$E$56-INDEX($C$56:$G$56,1,C76))))) | F80: =IF(C76=0,"ERROR",IF(OR($F$56="ERROR",INDEX($C$56:$G$56,1,C76)="ERROR"),"ERROR",IF(OR($F$56="UNKNOWN",INDEX($C$56:$G$56,1,C76)="UNKNOWN"),"UNKNOWN",IF(OR($F$56="NOT_APPLICABLE",INDEX($C$56:$G$56,1,C76)="NOT_APPLICABLE"),"NOT_APPLICABLE",$F$56-INDEX($C$56:$G$56,1,C76))))) | G80: =IF(C76=0,"ERROR",IF(OR($G$56="ERROR",INDEX($C$56:$G$56,1,C76)="ERROR"),"ERROR",IF(OR($G$56="UNKNOWN",INDEX($C$56:$G$56,1,C76)="UNKNOWN"),"UNKNOWN",IF(OR($G$56="NOT_APPLICABLE",INDEX($C$56:$G$56,1,C76)="NOT_APPLICABLE"),"NOT_APPLICABLE",$G$56-INDEX($C$56:$G$56,1,C76)))))
B82: REQUEST-LEVEL STATUS
B83: Active Scenario Count | C83: =COUNTIF($C$22:$G$22,"?*")
B84: Duplicate Scenario ID Exists? | C84: =SUMPRODUCT((COUNTIF($C$22:$G$22,$C$22:$G$22)>1)*($C$22:$G$22<>""))>0
B85: Request-Level Status | C85: =IF($C$83<2,"ERROR: SCENARIO_COUNT_BELOW_MINIMUM",IF($C$84=TRUE,"ERROR: DUPLICATE_SCENARIO_ID",IF(ISBLANK($C$18),"ERROR: MISSING_BASELINE_SCENARIO_ID",IF(C76=0,"ERROR: BASELINE_SCENARIO_ID_NOT_FOUND","OK"))))
B86: Scenario Compare Overall Status | C86: =IF(C85<>"OK",C85,IF((IF($C$58="ERROR",1,0)+IF($D$58="ERROR",1,0)+IF($E$58="ERROR",1,0)+IF($F$58="ERROR",1,0)+IF($G$58="ERROR",1,0))>0,"ERROR",IF((IF($C$58="INCOMPLETE",1,0)+IF($D$58="INCOMPLETE",1,0)+IF($E$58="INCOMPLETE",1,0)+IF($F$58="INCOMPLETE",1,0)+IF($G$58="INCOMPLETE",1,0))>0,"INCOMPLETE","OK")))
B88: Excel-only 표기 한계: Request-Level Status가 OK가 아닐 때도 각 시나리오 컬럼의 개별 계산 셀은 계속 숫자를 보여줍니다(수식 자체를 동적으로 비활성화할 수 없음) — 이 경우 Scenario Compare Overall Status가 request-level 오류를 표시하므로 개별 셀 값은 무시해야 합니다. Python Core는 이 경우 scenarios=[] 를 반환해 계산 자체를 하지 않습니다(진짜 실행 0회).

Sheet 11_SCENARIO_COMPARE_PARITY
B2: 11. Python Engine vs Excel Formula — Scenario Compare Parity Test
B3: 각 케이스는 docs/features/scenario_compare/CASE.md TC1-37 중 Excel에서 표현 가능한 대표 케이스에 대응하며, core/engine/scenario_compare.py의 run_scenario_compare()를 동일 base_input/overrides로 실행한 Python 참조값과, 같은 조건을 Excel 수식(build_scenario_compare_column_formulas)으로 독립 재계산한 값을 비교합니다. 각 케이스는 최소 2개(baseline + 1개 변형) scenario 컬럼을 사용하며, Scenario ID/Baseline ID/override mode(inherit/null/value)까지 리터럴로 심습니다. 허용오차 0.01.
B5: TC1. Baseline current price (no overrides)
B6: Check | C6: Excel Result | D6: Python Reference | E6: Difference | F6: PASS / FAIL
I7: 1000
I8: FALSE
I9: 0.1
I10: 1000
I11: 0
I12: 400
I13: 100
I14: 0
I15: 0
I16: 50000
I17: 0.3
I18: A | J18: A | K18: B
J19: inherit | K19: inherit
J21: inherit | K21: inherit
J23: inherit | K23: inherit
J25: inherit | K25: inherit
J27: inherit | K27: inherit
J29: inherit | K29: inherit
J31: inherit | K31: inherit
J33: inherit | K33: inherit
J35: inherit | K35: inherit
J37: =IFERROR(IF(NOT(ISNUMBER(J58)),"UNKNOWN",IF(J59="UNKNOWN","UNKNOWN",IF(J59=FALSE,J58,IF(NOT(ISNUMBER(J60)),"UNKNOWN",J58/(1+J60))))),"ERROR") | K37: =IFERROR(IF(NOT(ISNUMBER(K58)),"UNKNOWN",IF(K59="UNKNOWN","UNKNOWN",IF(K59=FALSE,K58,IF(NOT(ISNUMBER(K60)),"UNKNOWN",K58/(1+K60))))),"ERROR")
J38: =IFERROR(IF(J37="ERROR","ERROR",IF(OR(NOT(ISNUMBER(J37)),NOT(ISNUMBER(J64))),"UNKNOWN",IF(J66>0,IF(J48="ERROR","ERROR",IF(NOT(ISNUMBER(J48)),"UNKNOWN",J37-J64-$I$13-$I$14*J37-J66*J48)),J37-J64-$I$13-$I$14*J37))),"ERROR") | K38: =IFERROR(IF(K37="ERROR","ERROR",IF(OR(NOT(ISNUMBER(K37)),NOT(ISNUMBER(K64))),"UNKNOWN",IF(K66>0,IF(K48="ERROR","ERROR",IF(NOT(ISNUMBER(K48)),"UNKNOWN",K37-K64-$I$13-$I$14*K37-K66*K48)),K37-K64-$I$13-$I$14*K37))),"ERROR")
J39: =IFERROR(IF(J38="ERROR","ERROR",IF(NOT(ISNUMBER(J38)),"UNKNOWN",IF(J37=0,"ERROR",J38/J37))),"ERROR") | K39: =IFERROR(IF(K38="ERROR","ERROR",IF(NOT(ISNUMBER(K38)),"UNKNOWN",IF(K37=0,"ERROR",K38/K37))),"ERROR")
J40: =IF(OR(J37="ERROR",J38="ERROR",J39="ERROR"),"ERROR",IF(OR(NOT(ISNUMBER(J37)),NOT(ISNUMBER(J38)),NOT(ISNUMBER(J39))),"UNKNOWN","OK")) | K40: =IF(OR(K37="ERROR",K38="ERROR",K39="ERROR"),"ERROR",IF(OR(NOT(ISNUMBER(K37)),NOT(ISNUMBER(K38)),NOT(ISNUMBER(K39))),"UNKNOWN","OK"))
J41: =IFERROR(IF(NOT(ISNUMBER(J64)),J64,J64+$I$13),"ERROR") | K41: =IFERROR(IF(NOT(ISNUMBER(K64)),K64,K64+$I$13),"ERROR")
J42: =IFERROR(IF(NOT(ISNUMBER(J63)),"UNKNOWN",IF(OR(J63<0,J63>=1),"ERROR",IF(J66=0,IF(1-J63-$I$14<=0,"ERROR",1-J63-$I$14),IF(NOT(ISNUMBER(J60)),"UNKNOWN",IF(1-J63-$I$14-J66*(1+J60)<=0,"ERROR",1-J63-$I$14-J66*(1+J60)))))),"ERROR") | K42: =IFERROR(IF(NOT(ISNUMBER(K63)),"UNKNOWN",IF(OR(K63<0,K63>=1),"ERROR",IF(K66=0,IF(1-K63-$I$14<=0,"ERROR",1-K63-$I$14),IF(NOT(ISNUMBER(K60)),"UNKNOWN",IF(1-K63-$I$14-K66*(1+K60)<=0,"ERROR",1-K63-$I$14-K66*(1+K60)))))),"ERROR")
J43: =IFERROR(IF(NOT(ISNUMBER(J41)),J41,IF(NOT(ISNUMBER(J42)),J42,J41/J42)),"ERROR") | K43: =IFERROR(IF(NOT(ISNUMBER(K41)),K41,IF(NOT(ISNUMBER(K42)),K42,K41/K42)),"ERROR")
J44: =IFERROR(IF(NOT(ISNUMBER(J43)),J43,IF(NOT(ISNUMBER(J60)),"UNKNOWN",J43*(1+J60))),"ERROR") | K44: =IFERROR(IF(NOT(ISNUMBER(K43)),K43,IF(NOT(ISNUMBER(K60)),"UNKNOWN",K43*(1+K60))),"ERROR")
J45: =IFERROR(IF(J59="UNKNOWN","UNKNOWN",IF(J59=FALSE,J43,J44)),"ERROR") | K45: =IFERROR(IF(K59="UNKNOWN","UNKNOWN",IF(K59=FALSE,K43,K44)),"ERROR")
J46: =IFERROR(IF(NOT(ISNUMBER(J45)),J45,IF(NOT(ISNUMBER(J62)),"UNKNOWN",IF(OR(J62<0,J62>=1),"ERROR",IF(J62=0,J45,J45/(1-J62))))),"ERROR") | K46: =IFERROR(IF(NOT(ISNUMBER(K45)),K45,IF(NOT(ISNUMBER(K62)),"UNKNOWN",IF(OR(K62<0,K62>=1),"ERROR",IF(K62=0,K45,K45/(1-K62))))),"ERROR")
J47: =IF(OR(J45="ERROR",J46="ERROR"),"ERROR",IF(OR(NOT(ISNUMBER(J45)),NOT(ISNUMBER(J46))),"UNKNOWN","OK")) | K47: =IF(OR(K45="ERROR",K46="ERROR"),"ERROR",IF(OR(NOT(ISNUMBER(K45)),NOT(ISNUMBER(K46))),"UNKNOWN","OK"))
J48: =IFERROR(IF(NOT(ISNUMBER(J58)),"UNKNOWN",IF(J59="UNKNOWN","UNKNOWN",IF(J59=TRUE,J58,IF(NOT(ISNUMBER(J60)),"UNKNOWN",J58*(1+J60))))),"ERROR") | K48: =IFERROR(IF(NOT(ISNUMBER(K58)),"UNKNOWN",IF(K59="UNKNOWN","UNKNOWN",IF(K59=TRUE,K58,IF(NOT(ISNUMBER(K60)),"UNKNOWN",K58*(1+K60))))),"ERROR")
J49: =IFERROR(IF(NOT(ISNUMBER(J61)),"UNKNOWN",IF(J59="UNKNOWN","UNKNOWN",IF(J59=FALSE,J61,IF(NOT(ISNUMBER(J60)),"UNKNOWN",J61/(1+J60))))),"ERROR") | K49: =IFERROR(IF(NOT(ISNUMBER(K61)),"UNKNOWN",IF(K59="UNKNOWN","UNKNOWN",IF(K59=FALSE,K61,IF(NOT(ISNUMBER(K60)),"UNKNOWN",K61/(1+K60))))),"ERROR")
J50: =IFERROR(IF(NOT(ISNUMBER(J61)),"UNKNOWN",IF(J59="UNKNOWN","UNKNOWN",IF(J59=TRUE,J61,IF(NOT(ISNUMBER(J60)),"UNKNOWN",J61*(1+J60))))),"ERROR") | K50: =IFERROR(IF(NOT(ISNUMBER(K61)),"UNKNOWN",IF(K59="UNKNOWN","UNKNOWN",IF(K59=TRUE,K61,IF(NOT(ISNUMBER(K60)),"UNKNOWN",K61*(1+K60))))),"ERROR")
J51: =IFERROR(IF(J49="ERROR","ERROR",IF(NOT(ISNUMBER(J63)),"UNKNOWN",IF(OR(J63<0,J63>=1),"ERROR",IF(NOT(ISNUMBER(J49)),"UNKNOWN",IF(J66>0,IF(J50="ERROR","ERROR",IF(NOT(ISNUMBER(J50)),"UNKNOWN",J49*(1-J63-$I$14)-J66*J50-$I$13)),J49*(1-J63-$I$14)-$I$13))))),"ERROR") | K51: =IFERROR(IF(K49="ERROR","ERROR",IF(NOT(ISNUMBER(K63)),"UNKNOWN",IF(OR(K63<0,K63>=1),"ERROR",IF(NOT(ISNUMBER(K49)),"UNKNOWN",IF(K66>0,IF(K50="ERROR","ERROR",IF(NOT(ISNUMBER(K50)),"UNKNOWN",K49*(1-K63-$I$14)-K66*K50-$I$13)),K49*(1-K63-$I$14)-$I$13))))),"ERROR")
J52: =IFERROR(IF(OR(J51="ERROR",J64="ERROR"),"ERROR",IF(OR(NOT(ISNUMBER(J51)),NOT(ISNUMBER(J64))),"UNKNOWN",J51-J64)),"ERROR") | K52: =IFERROR(IF(OR(K51="ERROR",K64="ERROR"),"ERROR",IF(OR(NOT(ISNUMBER(K51)),NOT(ISNUMBER(K64))),"UNKNOWN",K51-K64)),"ERROR")
J53: =IF(OR(J51="ERROR",J64="ERROR",J52="ERROR"),"ERROR",IF(OR(NOT(ISNUMBER(J51)),NOT(ISNUMBER(J64)),NOT(ISNUMBER(J52))),"UNKNOWN","OK")) | K53: =IF(OR(K51="ERROR",K64="ERROR",K52="ERROR"),"ERROR",IF(OR(NOT(ISNUMBER(K51)),NOT(ISNUMBER(K64)),NOT(ISNUMBER(K52))),"UNKNOWN","OK"))
J54: =IFERROR(IF(NOT(ISNUMBER(J65)),J65,IF(J65<0,"ERROR",J65)),"ERROR") | K54: =IFERROR(IF(NOT(ISNUMBER(K65)),K65,IF(K65<0,"ERROR",K65)),"ERROR")
J55: =IFERROR(IF(OR(J38="ERROR",J54="ERROR"),"ERROR",IF(OR(NOT(ISNUMBER(J38)),NOT(ISNUMBER(J54))),"UNKNOWN",IF(J38<=0,"NOT_APPLICABLE",J54/J38))),"ERROR") | K55: =IFERROR(IF(OR(K38="ERROR",K54="ERROR"),"ERROR",IF(OR(NOT(ISNUMBER(K38)),NOT(ISNUMBER(K54))),"UNKNOWN",IF(K38<=0,"NOT_APPLICABLE",K54/K38))),"ERROR")
J56: =IF(OR(J38="ERROR",J54="ERROR",J55="ERROR"),"ERROR",IF(OR(NOT(ISNUMBER(J38)),NOT(ISNUMBER(J54)),AND(NOT(ISNUMBER(J55)),J55<>"NOT_APPLICABLE")),"UNKNOWN","OK")) | K56: =IF(OR(K38="ERROR",K54="ERROR",K55="ERROR"),"ERROR",IF(OR(NOT(ISNUMBER(K38)),NOT(ISNUMBER(K54)),AND(NOT(ISNUMBER(K55)),K55<>"NOT_APPLICABLE")),"UNKNOWN","OK"))
J57: =IF(OR(J40="ERROR",J47="ERROR",J53="ERROR",J56="ERROR"),"ERROR",IF(OR(J40="UNKNOWN",J47="UNKNOWN",J53="UNKNOWN",J56="UNKNOWN"),"INCOMPLETE","OK")) | K57: =IF(OR(K40="ERROR",K47="ERROR",K53="ERROR",K56="ERROR"),"ERROR",IF(OR(K40="UNKNOWN",K47="UNKNOWN",K53="UNKNOWN",K56="UNKNOWN"),"INCOMPLETE","OK"))
J58: =IF($J$19="inherit",$I$7,IF($J$19="null","UNKNOWN",$J$20)) | K58: =IF($K$19="inherit",$I$7,IF($K$19="null","UNKNOWN",$K$20))
J59: =IF($J$21="inherit",$I$8,IF($J$21="null","UNKNOWN",$J$22)) | K59: =IF($K$21="inherit",$I$8,IF($K$21="null","UNKNOWN",$K$22))
J60: =IF($J$23="inherit",$I$9,IF($J$23="null","UNKNOWN",$J$24)) | K60: =IF($K$23="inherit",$I$9,IF($K$23="null","UNKNOWN",$K$24))
J61: =IF($J$25="inherit",$I$10,IF($J$25="null","UNKNOWN",$J$26)) | K61: =IF($K$25="inherit",$I$10,IF($K$25="null","UNKNOWN",$K$26))
J62: =IF($J$27="inherit",$I$11,IF($J$27="null","UNKNOWN",$J$28)) | K62: =IF($K$27="inherit",$I$11,IF($K$27="null","UNKNOWN",$K$28))
J63: =IF($J$29="inherit",$I$17,IF($J$29="null","UNKNOWN",$J$30)) | K63: =IF($K$29="inherit",$I$17,IF($K$29="null","UNKNOWN",$K$30))
J64: =IF($J$31="inherit",$I$12,IF($J$31="null","UNKNOWN",$J$32)) | K64: =IF($K$31="inherit",$I$12,IF($K$31="null","UNKNOWN",$K$32))
J65: =IF($J$33="inherit",$I$16,IF($J$33="null","UNKNOWN",$J$34)) | K65: =IF($K$33="inherit",$I$16,IF($K$33="null","UNKNOWN",$K$34))
J66: =IF($J$35="inherit",$I$15,IF($J$35="null","UNKNOWN",$J$36)) | K66: =IF($K$35="inherit",$I$15,IF($K$35="null","UNKNOWN",$K$36))
I67: =IFERROR(MATCH($I$18,$J$18:$K$18,0),0)
J68: =IF(I67=0,"ERROR",IF(OR($J$37="ERROR",INDEX($J$37:$K$37,1,I67)="ERROR"),"ERROR",IF(OR($J$37="UNKNOWN",INDEX($J$37:$K$37,1,I67)="UNKNOWN"),"UNKNOWN",IF(OR($J$37="NOT_APPLICABLE",INDEX($J$37:$K$37,1,I67)="NOT_APPLICABLE"),"NOT_APPLICABLE",$J$37-INDEX($J$37:$K$37,1,I67))))) | K68: =IF(I67=0,"ERROR",IF(OR($K$37="ERROR",INDEX($J$37:$K$37,1,I67)="ERROR"),"ERROR",IF(OR($K$37="UNKNOWN",INDEX($J$37:$K$37,1,I67)="UNKNOWN"),"UNKNOWN",IF(OR($K$37="NOT_APPLICABLE",INDEX($J$37:$K$37,1,I67)="NOT_APPLICABLE"),"NOT_APPLICABLE",$K$37-INDEX($J$37:$K$37,1,I67)))))
J69: =IF(I67=0,"ERROR",IF(OR($J$38="ERROR",INDEX($J$38:$K$38,1,I67)="ERROR"),"ERROR",IF(OR($J$38="UNKNOWN",INDEX($J$38:$K$38,1,I67)="UNKNOWN"),"UNKNOWN",IF(OR($J$38="NOT_APPLICABLE",INDEX($J$38:$K$38,1,I67)="NOT_APPLICABLE"),"NOT_APPLICABLE",$J$38-INDEX($J$38:$K$38,1,I67))))) | K69: =IF(I67=0,"ERROR",IF(OR($K$38="ERROR",INDEX($J$38:$K$38,1,I67)="ERROR"),"ERROR",IF(OR($K$38="UNKNOWN",INDEX($J$38:$K$38,1,I67)="UNKNOWN"),"UNKNOWN",IF(OR($K$38="NOT_APPLICABLE",INDEX($J$38:$K$38,1,I67)="NOT_APPLICABLE"),"NOT_APPLICABLE",$K$38-INDEX($J$38:$K$38,1,I67)))))
J70: =IF(I67=0,"ERROR",IF(OR($J$39="ERROR",INDEX($J$39:$K$39,1,I67)="ERROR"),"ERROR",IF(OR($J$39="UNKNOWN",INDEX($J$39:$K$39,1,I67)="UNKNOWN"),"UNKNOWN",IF(OR($J$39="NOT_APPLICABLE",INDEX($J$39:$K$39,1,I67)="NOT_APPLICABLE"),"NOT_APPLICABLE",$J$39-INDEX($J$39:$K$39,1,I67))))) | K70: =IF(I67=0,"ERROR",IF(OR($K$39="ERROR",INDEX($J$39:$K$39,1,I67)="ERROR"),"ERROR",IF(OR($K$39="UNKNOWN",INDEX($J$39:$K$39,1,I67)="UNKNOWN"),"UNKNOWN",IF(OR($K$39="NOT_APPLICABLE",INDEX($J$39:$K$39,1,I67)="NOT_APPLICABLE"),"NOT_APPLICABLE",$K$39-INDEX($J$39:$K$39,1,I67)))))
J71: =IF(I67=0,"ERROR",IF(OR($J$55="ERROR",INDEX($J$55:$K$55,1,I67)="ERROR"),"ERROR",IF(OR($J$55="UNKNOWN",INDEX($J$55:$K$55,1,I67)="UNKNOWN"),"UNKNOWN",IF(OR($J$55="NOT_APPLICABLE",INDEX($J$55:$K$55,1,I67)="NOT_APPLICABLE"),"NOT_APPLICABLE",$J$55-INDEX($J$55:$K$55,1,I67))))) | K71: =IF(I67=0,"ERROR",IF(OR($K$55="ERROR",INDEX($J$55:$K$55,1,I67)="ERROR"),"ERROR",IF(OR($K$55="UNKNOWN",INDEX($J$55:$K$55,1,I67)="UNKNOWN"),"UNKNOWN",IF(OR($K$55="NOT_APPLICABLE",INDEX($J$55:$K$55,1,I67)="NOT_APPLICABLE"),"NOT_APPLICABLE",$K$55-INDEX($J$55:$K$55,1,I67)))))
B73: Scenario A: scenario_status | C73: =J57 | D73: OK | F73: =IF(J57=D73,"PASS","FAIL")
B74: Scenario A: contribution_margin | C74: =J38 | D74: 500 | E74: =IF(ISNUMBER(D74),IF(ISNUMBER(J38),ABS(J38-D74),"N/A"),"N/A") | F74: =IFERROR(IF(ISNUMBER(D74),IF(ISNUMBER(J38),IF(ABS(J38-D74)<=0.01,"PASS","FAIL"),"FAIL"),IF(NOT(ISNUMBER(J38)),IF(J38=D74,"PASS","FAIL"),"FAIL")),"FAIL")
B75: Scenario A: break_even_quantity_exact | C75: =J55 | D75: 100 | E75: =IF(ISNUMBER(D75),IF(ISNUMBER(J55),ABS(J55-D75),"N/A"),"N/A") | F75: =IFERROR(IF(ISNUMBER(D75),IF(ISNUMBER(J55),IF(ABS(J55-D75)<=0.01,"PASS","FAIL"),"FAIL"),IF(NOT(ISNUMBER(J55)),IF(J55=D75,"PASS","FAIL"),"FAIL")),"FAIL")
B76: Scenario A: net_sales_ex_vat_delta | C76: =J68 | D76: 0 | F76: =IFERROR(IF(ISNUMBER(D76),IF(ISNUMBER(J68),IF(ABS(J68-D76)<=0.01,"PASS","FAIL"),"FAIL"),IF(NOT(ISNUMBER(J68)),IF(J68=D76,"PASS","FAIL"),"FAIL")),"FAIL")
B77: Scenario A: contribution_margin_delta | C77: =J69 | D77: 0 | F77: =IFERROR(IF(ISNUMBER(D77),IF(ISNUMBER(J69),IF(ABS(J69-D77)<=0.01,"PASS","FAIL"),"FAIL"),IF(NOT(ISNUMBER(J69)),IF(J69=D77,"PASS","FAIL"),"FAIL")),"FAIL")
B78: Scenario A: contribution_margin_rate_delta | C78: =J70 | D78: 0 | F78: =IFERROR(IF(ISNUMBER(D78),IF(ISNUMBER(J70),IF(ABS(J70-D78)<=0.01,"PASS","FAIL"),"FAIL"),IF(NOT(ISNUMBER(J70)),IF(J70=D78,"PASS","FAIL"),"FAIL")),"FAIL")
B79: Scenario A: break_even_quantity_delta | C79: =J71 | D79: 0 | F79: =IFERROR(IF(ISNUMBER(D79),IF(ISNUMBER(J71),IF(ABS(J71-D79)<=0.01,"PASS","FAIL"),"FAIL"),IF(NOT(ISNUMBER(J71)),IF(J71=D79,"PASS","FAIL"),"FAIL")),"FAIL")
B80: Scenario B: scenario_status | C80: =K57 | D80: OK | F80: =IF(K57=D80,"PASS","FAIL")
B81: Scenario B: contribution_margin | C81: =K38 | D81: 500 | E81: =IF(ISNUMBER(D81),IF(ISNUMBER(K38),ABS(K38-D81),"N/A"),"N/A") | F81: =IFERROR(IF(ISNUMBER(D81),IF(ISNUMBER(K38),IF(ABS(K38-D81)<=0.01,"PASS","FAIL"),"FAIL"),IF(NOT(ISNUMBER(K38)),IF(K38=D81,"PASS","FAIL"),"FAIL")),"FAIL")
B82: Scenario B: break_even_quantity_exact | C82: =K55 | D82: 100 | E82: =IF(ISNUMBER(D82),IF(ISNUMBER(K55),ABS(K55-D82),"N/A"),"N/A") | F82: =IFERROR(IF(ISNUMBER(D82),IF(ISNUMBER(K55),IF(ABS(K55-D82)<=0.01,"PASS","FAIL"),"FAIL"),IF(NOT(ISNUMBER(K55)),IF(K55=D82,"PASS","FAIL"),"FAIL")),"FAIL")
B83: Scenario B: net_sales_ex_vat_delta | C83: =K68 | D83: 0 | F83: =IFERROR(IF(ISNUMBER(D83),IF(ISNUMBER(K68),IF(ABS(K68-D83)<=0.01,"PASS","FAIL"),"FAIL"),IF(NOT(ISNUMBER(K68)),IF(K68=D83,"PASS","FAIL"),"FAIL")),"FAIL")
